Workbook
Name Receitas: X!$V$2:$V$15
Name CatReceitas: 'Plano de Contas'!$B$4:$H$4
Name RecebimentosVencidos: XX!$A$1:$K$999
Name MesAtual: X!$Q$5
Name Plano_receitas: 'Plano de Contas'!$B$5:$H$195
Name Categorias: X!$V$2:$V$15
Name bancos: Cadastros!$B$6:$B$19
Name Tcentrocustos: X!$G$2:$G$6
Name CatDespesas: 'Plano de Contas'!$J$4:$Z$4
Name Meses: X!$I$2:$I$14
Name CentroCustos: Cadastros!$M$6:$M$19
Name Fornecedores: Cadastros!$I$6:$I$998
Name formaspgto: Cadastros!$K$6:$K$79
Name Tfornecedores: X!$N$2:$N$1001
Name Tbancos: X!$A$2:$A$1001
Name plano_despesas: 'Plano de Contas'!$J$5:$Z$195
Name Clientes: Cadastros!$G$6:$G$998
Name Tclientes: X!$L$2:$L$1001

Sheet inicio
A2: IMPORTANTE | H2: ACESSE NOSSO SITE E CONHEÇA NOSSAS OUTRAS PLANILHAS
H3: macrobit.com.br
A4: Para utilizar sua planilha você deve clicar em "Arquivo" e depois em "Fazer Cópia"! Assim você salvará uma cópia associada a sua conta google.
A8: Jamais peça acesso a planilha da Macro Bit, o procedimento correto é salvar a sua própria cópia do arquivo Raiz!
A11: Em caso de dúvidas, chame nosso suporte no whatsapp: (22) 98152-6045

Sheet Plano de Contas
B2: CATEGORIAS DE RECEITAS | J2: CATEGORIAS DE DESPESAS
B4: Receitas Operacionais | D4: Outras Receitas Operacionais | F4: Receitas Financeiras | H4: Receitas não operacionais | J4: Deduções sobre vendas | L4: Custo das Vendas | N4: Despesas administrativas | P4: Despesa com Pessoal | R4: Despesa Comercial | T4: Despesa Financeira | V4: Despesas não operacionais | X4: Impostos | Z4: Participação e Dividendos
B5: Dinheiro | D5: Entradas Caixinha | F5: Juros | H5: Aportes de Sócio | J5: Comissão 10% | L5: Pão | N5: Luz | P5: Salários | T5: Tarifas Bancárias | V5: Financiamento | X5: PIS | Z5: Retiradas dos Sócios
B6: Credito | F6: Rentabilidade de Aplicações | H6: Venda de bens - Valor residual | J6: Motoboy | L6: Carne | N6: Água | P6: 13º Salário | T6: Taxas e Desp. de Cobrança | V6: Gastos Não Identificados | X6: COFINS | Z6: Participação no Lucro
B7: Debito | H7: Empréstimos bancários | J7: Tx. Cartão | L7: Queijos | N7: Internet | P7: Adiantamento Salarial | T7: Outras Despesas Financeiras | V7: Investimento em Patrimonio | X7: CSLL
B8: Pix | H8: Valores de terceiros | J8: Devoluções | L8: Bacon | N8: Aluguel | P8: Aquisição de Equipamentos | T8: Juros | V8: Combustível | X8: INSS - Funcionarios
B9: Ifood | H9: Empréstimo Luiz | J9: DAS | L9: Congelados | N9: Contador | P9: Assistência médica | T9: Multas | V9: Doblô | X9: INSS - Patronal
B10: V. Refeição | H10: Empréstimo Diogo | J10: Taxa Ifood | L10: Picanha e Costela | N10: Marketing | P10: Bonificação Fixo | T10: IOF | V10: Obras e Manutenção | X10: IRRF
H11: Emprestimo Iago | L11: Frutas | N11: Segurança | P11: Férias | V11: Empréstimos Luiz | X11: ISS
L12: Gás | N12: Sistema | P12: FGTS | V12: Empréstimos Diogo | X12: ICMS
L13: Bebidas | N13: Limpeza | P13: Horas-extras | V13: Tarifas
L14: Mercado | P14: INSS (funcionários) | V14: Diferença de Caixa
P15: INSS (patronal) | V15: Multas e Juros
P16: IRPF | V16: Outros
P17: Plano de saúde dos Sócios
P18: Pró labore
P19: Refeição de Funcionários / Ticket
P20: Rescisões trabalhistas
P21: Salários Escritório
P22: Seguro de Vida
P23: Treinamentos e Capacitações
P24: Uniformes / EPI / EPC
P25: Vale-transportes

Sheet Cadastros
B2: Cadastros
B5: CONTAS BANCÁRIAS | C5: Centro de Custos | D5: SALDO | E5: DATA | G5: Clientes | I5: Fornecedores | K5: Formas de Pagamento | M5: Centro de Custos
B6: Banco Inter | C6: Projeto 01 | D6: 5240 | E6: 44562 | G6: Rogério Ceni | I6: Fornecedor 01 | K6: Dinheiro | M6: Projeto 01
B7: Nubank | C7: Projeto 02 | D7: 2500 | E7: 44562 | G7: Roger Machado | I7: Fornecedor 02 | K7: Pix | M7: Projeto 02
G8: Luiz Castro | I8: Fornecedor 03 | K8: Cartão | M8: Projeto 03
G9: Rafael Paiva | K9: Boleto | M9: Projeto 04

Sheet Entradas
B2: Descrição | C2: Categoria | D2: Classificação | E2: Data da Competência | F2: Data do Recebimento | G2: Status | H2: Cliente | I2: Valores | J2: Forma de Recebimento | K2: Conta Financeira | L2: Centro de Custos
B3: Vendas em dinheiro | C3: Receitas Operacionais | D3: Dinheiro | E3: 45973 | F3: 45973 | G3: Realizado | H3: Rogério Ceni | I3: 500 | J3: Dinheiro | K3: Banco Inter | L3: Projeto 01
B4: Vendas em dinheiro | C4: Receitas Operacionais | D4: Dinheiro | E4: 45974 | F4: 45974 | G4: Realizado | H4: Roger Machado | I4: 350 | J4: Pix | K4: Nubank | L4: Projeto 02
B5: Vendas em pix | C5: Receitas Operacionais | D5: Dinheiro | E5: 45975 | F5: 45975 | G5: Previsto | H5: Luiz Castro | I5: 500 | J5: Cartão | K5: Banco Inter | L5: Projeto 01
B6: Vendas Crédito | C6: Receitas Operacionais | D6: Dinheiro | E6: 45976 | F6: 45976 | G6: Realizado | H6: Rafael Paiva | I6: 3500 | J6: Boleto | K6: Nubank | L6: Projeto 02
B7: Vendas no débito | C7: Receitas Operacionais | D7: Dinheiro | E7: 45977 | F7: 45977 | G7: Realizado | H7: Rogério Ceni | I7: 2500 | J7: Dinheiro | K7: Banco Inter | L7: Projeto 01
B8: Vendas em dinheiro | C8: Receitas Operacionais | D8: Dinheiro | E8: 45978 | F8: 45978 | G8: Realizado | H8: Roger Machado | I8: 350 | J8: Pix | K8: Nubank | L8: Projeto 02
B9: Vendas em pix | C9: Receitas Operacionais | D9: Dinheiro | E9: 45979 | F9: 45979 | G9: Previsto | H9: Luiz Castro | I9: 800 | J9: Cartão | K9: Banco Inter | L9: Projeto 01
B10: Vendas Crédito | C10: Receitas Operacionais | D10: Dinheiro | E10: 45980 | F10: 45980 | G10: Realizado | H10: Rafael Paiva | I10: 1200 | J10: Boleto | K10: Nubank | L10: Projeto 02
B11: Vendas no débito | C11: Receitas Operacionais | D11: Dinheiro | E11: 45981 | F11: 45981 | G11: Realizado | H11: Rogério Ceni | I11: 500 | J11: Dinheiro | K11: Banco Inter | L11: Projeto 01
B12: Vendas em dinheiro | C12: Receitas Operacionais | D12: Dinheiro | E12: 45982 | F12: 45982 | G12: Realizado | H12: Roger Machado | I12: 350 | J12: Pix | K12: Nubank | L12: Projeto 02
B13: Vendas em pix | C13: Receitas Operacionais | D13: Dinheiro | E13: 45983 | F13: 45983 | G13: Previsto | H13: Luiz Castro | I13: 800 | J13: Cartão | K13: Banco Inter | L13: Projeto 01
B14: Vendas Crédito | C14: Receitas Operacionais | D14: Dinheiro | E14: 45984 | F14: 45984 | G14: Realizado | H14: Rafael Paiva | I14: 1200 | J14: Boleto | K14: Nubank | L14: Projeto 02
... B26: Vendas no Crédito | C26: Receitas Operacionais | D26: Dinheiro | E26: 45996 | F26: 45996 | G26: Previsto | H26: Rafael Paiva | I26: 2500 | J26: Boleto | K26: Nubank | L26: Projeto 02

Sheet Saídas
B2: Descrição | C2: Categoria | D2: Classificação | E2: Data da Competência | F2: Data do Pagamento | G2: Status | H2: Fornecedor | I2: Valores | J2: Forma de Recebimento | K2: Conta Financeira | L2: Centro de Custos
B3: Compra de queijo | C3: Custo das Vendas | D3: Pão | E3: 45973 | F3: 45973 | G3: Previsto | H3: Fornecedor 01 | I3: 123 | J3: Dinheiro | K3: Banco Inter | L3: Projeto 01
B4: Bebidas | C4: Custo das Vendas | D4: Bebidas | E4: 45974 | F4: 45974 | G4: Realizado | H4: Fornecedor 02 | I4: 250 | J4: Pix | K4: Nubank | L4: Projeto 02
B5: Salário José | C5: Despesa com Pessoal | D5: Salários | E5: 45975 | F5: 45975 | G5: Previsto | H5: Fornecedor 03 | I5: 1320 | J5: Cartão | K5: Banco Inter | L5: Projeto 01
B6: Salário Mária | C6: Despesa com Pessoal | D6: Salários | E6: 45976 | F6: 45976 | G6: Previsto | H6: Fornecedor 01 | I6: 1320 | J6: Boleto | K6: Nubank | L6: Projeto 02
B7: Aluguel | C7: Despesas administrativas | D7: Aluguel | E7: 45977 | F7: 45977 | G7: Previsto | H7: Fornecedor 02 | I7: 1320 | J7: Dinheiro | K7: Banco Inter | L7: Projeto 01
B8: Luz | C8: Despesas administrativas | D8: Luz | E8: 45978 | F8: 45978 | G8: Previsto | H8: Fornecedor 03 | I8: 450 | J8: Pix | K8: Nubank | L8: Projeto 02
B9: Pão | C9: Custo das Vendas | D9: Pão | E9: 45979 | F9: 45979 | G9: Realizado | H9: Fornecedor 01 | I9: 450 | J9: Cartão | K9: Banco Inter | L9: Projeto 01
B10: Salário José | C10: Despesa com Pessoal | D10: Salários | E10: 45980 | F10: 45980 | G10: Previsto | H10: Fornecedor 02 | I10: 1320 | J10: Boleto | K10: Nubank | L10: Projeto 02
B11: Salário Mária | C11: Despesa com Pessoal | D11: Salários | E11: 45981 | F11: 45981 | G11: Previsto | H11: Fornecedor 03 | I11: 1320 | J11: Dinheiro | K11: Banco Inter | L11: Projeto 01
B12: Aluguel | C12: Despesas administrativas | D12: Aluguel | E12: 45982 | F12: 45982 | G12: Previsto | H12: Fornecedor 01 | I12: 2500 | J12: Pix | K12: Nubank | L12: Projeto 02
B13: Taxa do cartão | C13: Deduções Sobre Vendas | D13: Taxas e Desp. de Cobrança | E13: 45983 | F13: 45983 | G13: Realizado | H13: Fornecedor 02 | I13: 925 | J13: Cartão | K13: Banco Inter | L13: Projeto 01
B14: Impostos | C14: Impostos | D14: DAS | E14: 45984 | F14: 45984 | G14: Realizado | H14: Fornecedor 03 | I14: 650 | J14: Boleto | K14: Nubank | L14: Projeto 02
... B18: Teste de caixa negativo | C18: Despesas não operacionais | D18: Investimento em Patrimonio | E18: 45988 | F18: 45988 | G18: Previsto | H18: Fornecedor 01 | I18: 35000 | J18: Cartão | K18: Nubank | L18: Projeto 02

Sheet Transf Interna
B2: Conta de Origem | C2: Conta de Destino | D2: Data | E2: Valor
B3: Banco Inter | C3: Nubank | D3: 44927 | E3: 1500
B4: Banco Inter | C4: Nubank | D4: 44958 | E4: 1500
B5: Banco Inter | C5: Nubank | D5: 44986 | E5: 50000
B6: Banco Inter | C6: Nubank | D6: 45017 | E6: 1500
B7: Banco Inter | C7: Nubank | D7: 45047 | E7: 1500
B8: Banco Inter | C8: Nubank | D8: 45078 | E8: 1500
B9: Banco Inter | C9: Nubank | D9: 45108 | E9: 1500

Sheet Contas a Receber
B2: Contas a Receber | D2: FILTROS PARA CONTAS A RECEBER | K2: CONTAS A RECEBER
D3: Ano: | E3: 2025 | K3: Inicio | L3: =DATE( 'Contas a Receber'!E3,VLOOKUP('Contas a Receber'!$E$4,X!$I$2:$J$14,2,FALSE),1) -> 45658
B4: TOTAL A RECEBER | D4: Mês: | E4: Todos
B5: =SUM(E9:E1005) -> 16600 | D5: Cliente: | E5: Todos | K5: Final | L5: =IF('Contas a Receber'!E4="Todos",EDATE(L3,12),EDATE(L3,1)) -> 46023
D6: Centro de custos: | E6: Todos
B8: Descrição da conta | C8: Cliente | D8: Vencimento | E8: Valor
B9: =IFERROR(__xludf.DUMMYFUNCTION("IFERROR( INDEX( SORT( FILTER( {Entradas[Data do Recebimento],Entradas[Descrição]}, Entradas[Status]=""Previsto"", Entradas[Data do Recebimento]>='Contas a Receber'!$L$3, Entradas[Data do Recebimento]<'Contas a R"&"eceber'!$L$5, IF($E$5=""Todos"", Entradas[Cliente]<>""-"", Entradas[Cliente]=$E$5), IF(E6=""Todos"", Entradas[Centro de Custos]<>""-"", Entradas[Centro de Custos]=E6) ), 1, TRUE ), ,2 ), ""Não há contas com o filtro"&" selecionado"" ) "),"Vendas em pix") -> Vendas em pix | C9: =IFERROR(__xludf.DUMMYFUNCTION("IFERROR( INDEX( SORT( FILTER( {Entradas[Data do Recebimento],Entradas[Cliente]}, Entradas[Status]=""Previsto"", Entradas[Data do Recebimento]>='Contas a Receber'!$L$3, Entradas[Data do Recebimento]<'Contas a Rec"&"eber'!$L$5, IF($E$5=""Todos"", Entradas[Cliente]<>""-"", Entradas[Cliente]=$E$5), IF(E6=""Todos"", Entradas[Centro de Custos]<>""-"", Entradas[Centro de Custos]=E6) ), 1, TRUE ), ,2 ), ""Não há contas com o filtro s"&"elecionado"" ) "),"Luiz Castro") -> Luiz Castro | D9: =IFERROR(__xludf.DUMMYFUNCTION("IFERROR( INDEX( SORT( FILTER( {Entradas[Data do Recebimento],Entradas[Data do Recebimento]}, Entradas[Status]=""Previsto"", Entradas[Data do Recebimento]>='Contas a Receber'!$L$3, Entradas[Data do Recebimento]<'"&"Contas a Receber'!$L$5, IF($E$5=""Todos"", Entradas[Cliente]<>""-"", Entradas[Cliente]=$E$5), IF(E6=""Todos"", Entradas[Centro de Custos]<>""-"", Entradas[Centro de Custos]=E6) ), 1, TRUE ), ,2 ), ""Não há contas co"&"m o filtro selecionado"" ) "),45975.0) -> 45975 | E9: =IFERROR(__xludf.DUMMYFUNCTION("IFERROR( INDEX( SORT( FILTER( {Entradas[Data do Recebimento],Entradas[Valores]}, Entradas[Status]=""Previsto"", Entradas[Data do Recebimento]>='Contas a Receber'!$L$3, Entradas[Data do Recebimento]<'Contas a Rec"&"eber'!$L$5, IF($E$5=""Todos"", Entradas[Cliente]<>""-"", Entradas[Cliente]=$E$5), IF(E6=""Todos"", Entradas[Centro de Custos]<>""-"", Entradas[Centro de Custos]=E6) ), 1, TRUE ), ,2 ), ""Não há contas com o filtro s"&"elecionado"" ) "),500.0) -> 500
B10: =IFERROR(__xludf.DUMMYFUNCTION("""COMPUTED_VALUE"""),"Vendas em pix") -> Vendas em pix | C10: =IFERROR(__xludf.DUMMYFUNCTION("""COMPUTED_VALUE"""),"Luiz Castro") -> Luiz Castro | D10: =IFERROR(__xludf.DUMMYFUNCTION("""COMPUTED_VALUE"""),45979.0) -> 45979 | E10: =IFERROR(__xludf.DUMMYFUNCTION("""COMPUTED_VALUE"""),800.0) -> 800
B11: =IFERROR(__xludf.DUMMYFUNCTION("""COMPUTED_VALUE"""),"Vendas em pix") -> Vendas em pix | C11: =IFERROR(__xludf.DUMMYFUNCTION("""COMPUTED_VALUE"""),"Luiz Castro") -> Luiz Castro | D11: =IFERROR(__xludf.DUMMYFUNCTION("""COMPUTED_VALUE"""),45983.0) -> 45983 | E11: =IFERROR(__xludf.DUMMYFUNCTION("""COMPUTED_VALUE"""),800.0) -> 800
B12: =IFERROR(__xludf.DUMMYFUNCTION("""COMPUTED_VALUE"""),"Venda de carro João 1/3") -> Venda de carro João 1/3 | C12: =IFERROR(__xludf.DUMMYFUNCTION("""COMPUTED_VALUE"""),"Roger Machado") -> Roger Machado | D12: =IFERROR(__xludf.DUMMYFUNCTION("""COMPUTED_VALUE"""),45986.0) -> 45986 | E12: =IFERROR(__xludf.DUMMYFUNCTION("""COMPUTED_VALUE"""),5000.0) -> 5000
B13: =IFERROR(__xludf.DUMMYFUNCTION("""COMPUTED_VALUE"""),"Venda de carro João 2/3") -> Venda de carro João 2/3 | C13: =IFERROR(__xludf.DUMMYFUNCTION("""COMPUTED_VALUE"""),"Luiz Castro") -> Luiz Castro | D13: =IFERROR(__xludf.DUMMYFUNCTION("""COMPUTED_VALUE"""),45987.0) -> 45987 | E13: =IFERROR(__xludf.DUMMYFUNCTION("""COMPUTED_VALUE"""),5000.0) -> 5000
B14: =IFERROR(__xludf.DUMMYFUNCTION("""COMPUTED_VALUE"""),"Vendas em pix") -> Vendas em pix | C14: =IFERROR(__xludf.DUMMYFUNCTION("""COMPUTED_VALUE"""),"Roger Machado") -> Roger Machado | D14: =IFERROR(__xludf.DUMMYFUNCTION("""COMPUTED_VALUE"""),45990.0) -> 45990 | E14: =IFERROR(__xludf.DUMMYFUNCTION("""COMPUTED_VALUE"""),800.0) -> 800
B15: =IFERROR(__xludf.DUMMYFUNCTION("""COMPUTED_VALUE"""),"Vendas no Débito") -> Vendas no Débito | C15: =IFERROR(__xludf.DUMMYFUNCTION("""COMPUTED_VALUE"""),"Luiz Castro") -> Luiz Castro | D15: =IFERROR(__xludf.DUMMYFUNCTION("""COMPUTED_VALUE"""),45995.0) -> 45995 | E15: =IFERROR(__xludf.DUMMYFUNCTION("""COMPUTED_VALUE"""),1200.0) -> 1200
B16: =IFERROR(__xludf.DUMMYFUNCTION("""COMPUTED_VALUE"""),"Vendas no Crédito") -> Vendas no Crédito | C16: =IFERROR(__xludf.DUMMYFUNCTION("""COMPUTED_VALUE"""),"Rafael Paiva") -> Rafael Paiva | D16: =IFERROR(__xludf.DUMMYFUNCTION("""COMPUTED_VALUE"""),45996.0) -> 45996 | E16: =IFERROR(__xludf.DUMMYFUNCTION("""COMPUTED_VALUE"""),2500.0) -> 2500

Sheet Contas a Pagar
B2: Contas a Receber | D2: FILTROS PARA CONTAS A RECEBER | K2: CONTAS A RECEBER
D3: Ano: | E3: 2025 | K3: Inicio | L3: =DATE( 'Contas a Pagar'!E3,VLOOKUP('Contas a Pagar'!$E$4,X!$I$2:$J$14,2,FALSE),1) -> 45658
B4: TOTAL A PAGAR | D4: Mês: | E4: Todos
B5: =SUM(E9:E1005) -> 55313 | D5: Fornecedor | E5: Todos | K5: Final | L5: =IF('Contas a Pagar'!E4="Todos",EDATE(L3,12),EDATE(L3,1)) -> 46023
D6: Centro de custos: | E6: Todos
B8: Descrição da conta | C8: Fornecedores | D8: Vencimento | E8: Valor
B9: =IFERROR(__xludf.DUMMYFUNCTION("IFERROR( INDEX( SORT( FILTER( {Saidas[Data do Pagamento],Saidas[Descrição]}, Saidas[Status]=""Previsto"", Saidas[Data do Pagamento]>='Contas a Pagar'!$L$3, Saidas[Data do Pagamento]<'Contas a Pagar'!$L$5, "&" IF($E$5=""Todos"", Saidas[Fornecedor]<>""-"", Saidas[Fornecedor]=$E$5), IF(E6=""Todos"", Saidas[Centro de Custos]<>""-"", Saidas[Centro de Custos]=E6) ), 1, TRUE ), ,2 ), ""Não há contas com o filtro selecionado"" ) "),"Compra de queijo") -> Compra de queijo | C9: =IFERROR(__xludf.DUMMYFUNCTION("IFERROR( INDEX( SORT( FILTER( {Saidas[Data do Pagamento],Saidas[Fornecedor]}, Saidas[Status]=""Previsto"", Saidas[Data do Pagamento]>='Contas a Pagar'!$L$3, Saidas[Data do Pagamento]<'Contas a Pagar'!$L$5, "&" IF($E$5=""Todos"", Saidas[Fornecedor]<>""-"", Saidas[Fornecedor]=$E$5), IF(E6=""Todos"", Saidas[Centro de Custos]<>""-"", Saidas[Centro de Custos]=E6) ), 1, TRUE ), ,2 ), ""Não há contas com o filtro selecionado"" ) "),"Fornecedor 01") -> Fornecedor 01 | D9: =IFERROR(__xludf.DUMMYFUNCTION("IFERROR( INDEX( SORT( FILTER( {Saidas[Data do Pagamento],Saidas[Data do Pagamento]}, Saidas[Status]=""Previsto"", Saidas[Data do Pagamento]>='Contas a Pagar'!$L$3, Saidas[Data do Pagamento]<'Contas a Pagar'!$L$5"&", IF($E$5=""Todos"", Saidas[Fornecedor]<>""-"", Saidas[Fornecedor]=$E$5), IF(E6=""Todos"", Saidas[Centro de Custos]<>""-"", Saidas[Centro de Custos]=E6) ), 1, TRUE ), ,2 ), ""Não há contas com o filtro selecionado"""&" ) "),45973.0) -> 45973 | E9: =IFERROR(__xludf.DUMMYFUNCTION("IFERROR( INDEX( SORT( FILTER( {Saidas[Data do Pagamento],Saidas[Valores]}, Saidas[Status]=""Previsto"", Saidas[Data do Pagamento]>='Contas a Pagar'!$L$3, Saidas[Data do Pagamento]<'Contas a Pagar'!$L$5, "&"IF($E$5=""Todos"", Saidas[Fornecedor]<>""-"", Saidas[Fornecedor]=$E$5), IF(E6=""Todos"", Saidas[Centro de Custos]<>""-"", Saidas[Centro de Custos]=E6) ), 1, TRUE ), ,2 ), ""Não há contas com o filtro selecionado"" ) "),123.0) -> 123
B10: =IFERROR(__xludf.DUMMYFUNCTION("""COMPUTED_VALUE"""),"Salário José") -> Salário José | C10: =IFERROR(__xludf.DUMMYFUNCTION("""COMPUTED_VALUE"""),"Fornecedor 03") -> Fornecedor 03 | D10: =IFERROR(__xludf.DUMMYFUNCTION("""COMPUTED_VALUE"""),45975.0) -> 45975 | E10: =IFERROR(__xludf.DUMMYFUNCTION("""COMPUTED_VALUE"""),1320.0) -> 1320
B11: =IFERROR(__xludf.DUMMYFUNCTION("""COMPUTED_VALUE"""),"Salário Mária") -> Salário Mária | C11: =IFERROR(__xludf.DUMMYFUNCTION("""COMPUTED_VALUE"""),"Fornecedor 01") -> Fornecedor 01 | D11: =IFERROR(__xludf.DUMMYFUNCTION("""COMPUTED_VALUE"""),45976.0) -> 45976 | E11: =IFERROR(__xludf.DUMMYFUNCTION("""COMPUTED_VALUE"""),1320.0) -> 1320
B12: =IFERROR(__xludf.DUMMYFUNCTION("""COMPUTED_VALUE"""),"Aluguel") -> Aluguel | C12: =IFERROR(__xludf.DUMMYFUNCTION("""COMPUTED_VALUE"""),"Fornecedor 02") -> Fornecedor 02 | D12: =IFERROR(__xludf.DUMMYFUNCTION("""COMPUTED_VALUE"""),45977.0) -> 45977 | E12: =IFERROR(__xludf.DUMMYFUNCTION("""COMPUTED_VALUE"""),1320.0) -> 1320
B13: =IFERROR(__xludf.DUMMYFUNCTION("""COMPUTED_VALUE"""),"Luz") -> Luz | C13: =IFERROR(__xludf.DUMMYFUNCTION("""COMPUTED_VALUE"""),"Fornecedor 03") -> Fornecedor 03 | D13: =IFERROR(__xludf.DUMMYFUNCTION("""COMPUTED_VALUE"""),45978.0) -> 45978 | E13: =IFERROR(__xludf.DUMMYFUNCTION("""COMPUTED_VALUE"""),450.0) -> 450
B14: =IFERROR(__xludf.DUMMYFUNCTION("""COMPUTED_VALUE"""),"Salário José") -> Salário José | C14: =IFERROR(__xludf.DUMMYFUNCTION("""COMPUTED_VALUE"""),"Fornecedor 02") -> Fornecedor 02 | D14: =IFERROR(__xludf.DUMMYFUNCTION("""COMPUTED_VALUE"""),45980.0) -> 45980 | E14: =IFERROR(__xludf.DUMMYFUNCTION("""COMPUTED_VALUE"""),1320.0) -> 1320
B15: =IFERROR(__xludf.DUMMYFUNCTION("""COMPUTED_VALUE"""),"Salário Mária") -> Salário Mária | C15: =IFERROR(__xludf.DUMMYFUNCTION("""COMPUTED_VALUE"""),"Fornecedor 03") -> Fornecedor 03 | D15: =IFERROR(__xludf.DUMMYFUNCTION("""COMPUTED_VALUE"""),45981.0) -> 45981 | E15: =IFERROR(__xludf.DUMMYFUNCTION("""COMPUTED_VALUE"""),1320.0) -> 1320
B16: =IFERROR(__xludf.DUMMYFUNCTION("""COMPUTED_VALUE"""),"Aluguel") -> Aluguel | C16: =IFERROR(__xludf.DUMMYFUNCTION("""COMPUTED_VALUE"""),"Fornecedor 01") -> Fornecedor 01 | D16: =IFERROR(__xludf.DUMMYFUNCTION("""COMPUTED_VALUE"""),45982.0) -> 45982 | E16: =IFERROR(__xludf.DUMMYFUNCTION("""COMPUTED_VALUE"""),2500.0) -> 2500
B17: =IFERROR(__xludf.DUMMYFUNCTION("""COMPUTED_VALUE"""),"Salário José") -> Salário José | C17: =IFERROR(__xludf.DUMMYFUNCTION("""COMPUTED_VALUE"""),"Fornecedor 01") -> Fornecedor 01 | D17: =IFERROR(__xludf.DUMMYFUNCTION("""COMPUTED_VALUE"""),45985.0) -> 45985 | E17: =IFERROR(__xludf.DUMMYFUNCTION("""COMPUTED_VALUE"""),1320.0) -> 1320
B18: =IFERROR(__xludf.DUMMYFUNCTION("""COMPUTED_VALUE"""),"Salário Mária") -> Salário Mária | C18: =IFERROR(__xludf.DUMMYFUNCTION("""COMPUTED_VALUE"""),"Fornecedor 02") -> Fornecedor 02 | D18: =IFERROR(__xludf.DUMMYFUNCTION("""COMPUTED_VALUE"""),45986.0) -> 45986 | E18: =IFERROR(__xludf.DUMMYFUNCTION("""COMPUTED_VALUE"""),1320.0) -> 1320
B19: =IFERROR(__xludf.DUMMYFUNCTION("""COMPUTED_VALUE"""),"Custo da Mercadoria") -> Custo da Mercadoria | C19: =IFERROR(__xludf.DUMMYFUNCTION("""COMPUTED_VALUE"""),"Fornecedor 03") -> Fornecedor 03 | D19: =IFERROR(__xludf.DUMMYFUNCTION("""COMPUTED_VALUE"""),45987.0) -> 45987 | E19: =IFERROR(__xludf.DUMMYFUNCTION("""COMPUTED_VALUE"""),8000.0) -> 8000
B20: =IFERROR(__xludf.DUMMYFUNCTION("""COMPUTED_VALUE"""),"Teste de caixa negativo") -> Teste de caixa negativo | C20: =IFERROR(__xludf.DUMMYFUNCTION("""COMPUTED_VALUE"""),"Fornecedor 01") -> Fornecedor 01 | D20: =IFERROR(__xludf.DUMMYFUNCTION("""COMPUTED_VALUE"""),45988.0) -> 45988 | E20: =IFERROR(__xludf.DUMMYFUNCTION("""COMPUTED_VALUE"""),35000.0) -> 35000

Sheet Fluxo de Caixa
B2: Fluxo de Caixa | D2: FILTROS DO FLUXO DE CAIXA
D3: Ano: | E3: 2025 | F3: Status: | G3: Previsto | H3: Banco: | I3: Todos | K3: Centro de custos: | L3: Todos
C6: =DATE(E3,1,1) -> 45658 | D6: =EDATE(C6,1) -> 45689 | E6: =EDATE(D6,1) -> 45717 | F6: =EDATE(E6,1) -> 45748 | G6: =EDATE(F6,1) -> 45778 | H6: =EDATE(G6,1) -> 45809 | I6: =EDATE(H6,1) -> 45839 | J6: =EDATE(I6,1) -> 45870 | K6: =EDATE(J6,1) -> 45901 | ... N6: =EDATE(M6,1) -> 45992 | O6: Total do Ano
B8: Saldo Inícial | C8: =SUMIFS(Entradas[Valores],Entradas[Data do Recebimento],"<"&C$6,Entradas[Status],X!$E$2,Entradas[Conta Financeira],X!$E$3)-SUMIFS(Saidas[Valores],Saidas[Data do Pagamento],"<"&C$6,Saidas[Status],X!$E$2,Saidas[Conta Financeira],X!$E$3)+SUMIFS(Cadastros!$D$6:$D$19,Cadastros!$E$6:$E$19,"<"&C6,Cadastros!$B$6:$B$19,X!$E$3)+SUMIFS(Transferência_Interna[Valor],Transferência_Interna[Conta de Destino],X!$E$3,Transferência_Interna[Data],"<"&C$6)-SUMIFS(Transferência_Interna[Valor],Transferência_Interna[Conta de Origem],X!$E$3,Transferência_Interna[Data],"<"&C$6) -> 7740 | D8: =SUMIFS(Entradas[Valores],Entradas[Data do Recebimento],"<"&D$6,Entradas[Status],X!$E$2,Entradas[Conta Financeira],X!$E$3)-SUMIFS(Saidas[Valores],Saidas[Data do Pagamento],"<"&D$6,Saidas[Status],X!$E$2,Saidas[Conta Financeira],X!$E$3)+SUMIFS(Cadastros!$D$6:$D$19,Cadastros!$E$6:$E$19,"<"&D6,Cadastros!$B$6:$B$19,X!$E$3)+SUMIFS(Transferência_Interna[Valor],Transferência_Interna[Conta de Destino],X!$E$3,Transferência_Interna[Data],"<"&D$6)-SUMIFS(Transferência_Interna[Valor],Transferência_Interna[Conta de Origem],X!$E$3,Transferência_Interna[Data],"<"&D$6) -> 7740 | E8: =SUMIFS(Entradas[Valores],Entradas[Data do Recebimento],"<"&E$6,Entradas[Status],X!$E$2,Entradas[Conta Financeira],X!$E$3)-SUMIFS(Saidas[Valores],Saidas[Data do Pagamento],"<"&E$6,Saidas[Status],X!$E$2,Saidas[Conta Financeira],X!$E$3)+SUMIFS(Cadastros!$D$6:$D$19,Cadastros!$E$6:$E$19,"<"&E6,Cadastros!$B$6:$B$19,X!$E$3)+SUMIFS(Transferência_Interna[Valor],Transferência_Interna[Conta de Destino],X!$E$3,Transferência_Interna[Data],"<"&E$6)-SUMIFS(Transferência_Interna[Valor],Transferência_Interna[Conta de Origem],X!$E$3,Transferência_Interna[Data],"<"&E$6) -> 7740 | F8: =SUMIFS(Entradas[Valores],Entradas[Data do Recebimento],"<"&F$6,Entradas[Status],X!$E$2,Entradas[Conta Financeira],X!$E$3)-SUMIFS(Saidas[Valores],Saidas[Data do Pagamento],"<"&F$6,Saidas[Status],X!$E$2,Saidas[Conta Financeira],X!$E$3)+SUMIFS(Cadastros!$D$6:$D$19,Cadastros!$E$6:$E$19,"<"&F6,Cadastros!$B$6:$B$19,X!$E$3)+SUMIFS(Transferência_Interna[Valor],Transferência_Interna[Conta de Destino],X!$E$3,Transferência_Interna[Data],"<"&F$6)-SUMIFS(Transferência_Interna[Valor],Transferência_Interna[Conta de Origem],X!$E$3,Transferência_Interna[Data],"<"&F$6) -> 7740 | G8: =SUMIFS(Entradas[Valores],Entradas[Data do Recebimento],"<"&G$6,Entradas[Status],X!$E$2,Entradas[Conta Financeira],X!$E$3)-SUMIFS(Saidas[Valores],Saidas[Data do Pagamento],"<"&G$6,Saidas[Status],X!$E$2,Saidas[Conta Financeira],X!$E$3)+SUMIFS(Cadastros!$D$6:$D$19,Cadastros!$E$6:$E$19,"<"&G6,Cadastros!$B$6:$B$19,X!$E$3)+SUMIFS(Transferência_Interna[Valor],Transferência_Interna[Conta de Destino],X!$E$3,Transferência_Interna[Data],"<"&G$6)-SUMIFS(Transferência_Interna[Valor],Transferência_Interna[Conta de Origem],X!$E$3,Transferência_Interna[Data],"<"&G$6) -> 7740 | H8: =SUMIFS(Entradas[Valores],Entradas[Data do Recebimento],"<"&H$6,Entradas[Status],X!$E$2,Entradas[Conta Financeira],X!$E$3)-SUMIFS(Saidas[Valores],Saidas[Data do Pagamento],"<"&H$6,Saidas[Status],X!$E$2,Saidas[Conta Financeira],X!$E$3)+SUMIFS(Cadastros!$D$6:$D$19,Cadastros!$E$6:$E$19,"<"&H6,Cadastros!$B$6:$B$19,X!$E$3)+SUMIFS(Transferência_Interna[Valor],Transferência_Interna[Conta de Destino],X!$E$3,Transferência_Interna[Data],"<"&H$6)-SUMIFS(Transferência_Interna[Valor],Transferência_Interna[Conta de Origem],X!$E$3,Transferência_Interna[Data],"<"&H$6) -> 7740 | I8: =SUMIFS(Entradas[Valores],Entradas[Data do Recebimento],"<"&I$6,Entradas[Status],X!$E$2,Entradas[Conta Financeira],X!$E$3)-SUMIFS(Saidas[Valores],Saidas[Data do Pagamento],"<"&I$6,Saidas[Status],X!$E$2,Saidas[Conta Financeira],X!$E$3)+SUMIFS(Cadastros!$D$6:$D$19,Cadastros!$E$6:$E$19,"<"&I6,Cadastros!$B$6:$B$19,X!$E$3)+SUMIFS(Transferência_Interna[Valor],Transferência_Interna[Conta de Destino],X!$E$3,Transferência_Interna[Data],"<"&I$6)-SUMIFS(Transferência_Interna[Valor],Transferência_Interna[Conta de Origem],X!$E$3,Transferência_Interna[Data],"<"&I$6) -> 7740 | J8: =SUMIFS(Entradas[Valores],Entradas[Data do Recebimento],"<"&J$6,Entradas[Status],X!$E$2,Entradas[Conta Financeira],X!$E$3)-SUMIFS(Saidas[Valores],Saidas[Data do Pagamento],"<"&J$6,Saidas[Status],X!$E$2,Saidas[Conta Financeira],X!$E$3)+SUMIFS(Cadastros!$D$6:$D$19,Cadastros!$E$6:$E$19,"<"&J6,Cadastros!$B$6:$B$19,X!$E$3)+SUMIFS(Transferência_Interna[Valor],Transferência_Interna[Conta de Destino],X!$E$3,Transferência_Interna[Data],"<"&J$6)-SUMIFS(Transferência_Interna[Valor],Transferência_Interna[Conta de Origem],X!$E$3,Transferência_Interna[Data],"<"&J$6) -> 7740 | ... N8: =SUMIFS(Entradas[Valores],Entradas[Data do Recebimento],"<"&N$6,Entradas[Status],X!$E$2,Entradas[Conta Financeira],X!$E$3)-SUMIFS(Saidas[Valores],Saidas[Data do Pagamento],"<"&N$6,Saidas[Status],X!$E$2,Saidas[Conta Financeira],X!$E$3)+SUMIFS(Cadastros!$D$6:$D$19,Cadastros!$E$6:$E$19,"<"&N6,Cadastros!$B$6:$B$19,X!$E$3)+SUMIFS(Transferência_Interna[Valor],Transferência_Interna[Conta de Destino],X!$E$3,Transferência_Interna[Data],"<"&N$6)-SUMIFS(Transferência_Interna[Valor],Transferência_Interna[Conta de Origem],X!$E$3,Transferência_Interna[Data],"<"&N$6) -> -34673
B9: Entradas | C9: =SUM(C10:C13) -> 0 | D9: =SUM(D10:D13) -> 0 | E9: =SUM(E10:E13) -> 0 | F9: =SUM(F10:F13) -> 0 | G9: =SUM(G10:G13) -> 0 | H9: =SUM(H10:H13) -> 0 | I9: =SUM(I10:I13) -> 0 | J9: =SUM(J10:J13) -> 0 | ... N9: =SUM(N10:N13) -> 3700 | O9: =SUM(C9:N9) -> 16600
B10: =X!V2 -> Receitas Operacionais | C10: =SUMIFS(Entradas[Valores],Entradas[Data do Recebimento],">="&C$6,Entradas[Data do Recebimento],"<"&EDATE(C$6,1),Entradas[Categoria],$B10,Entradas[Status],X!$E$2,Entradas[Conta Financeira],X!$E$3,Entradas[Centro de Custos],X!$E$4) -> 0 | D10: =SUMIFS(Entradas[Valores],Entradas[Data do Recebimento],">="&D$6,Entradas[Data do Recebimento],"<"&EDATE(D$6,1),Entradas[Categoria],$B10,Entradas[Status],X!$E$2,Entradas[Conta Financeira],X!$E$3,Entradas[Centro de Custos],X!$E$4) -> 0 | E10: =SUMIFS(Entradas[Valores],Entradas[Data do Recebimento],">="&E$6,Entradas[Data do Recebimento],"<"&EDATE(E$6,1),Entradas[Categoria],$B10,Entradas[Status],X!$E$2,Entradas[Conta Financeira],X!$E$3,Entradas[Centro de Custos],X!$E$4) -> 0 | F10: =SUMIFS(Entradas[Valores],Entradas[Data do Recebimento],">="&F$6,Entradas[Data do Recebimento],"<"&EDATE(F$6,1),Entradas[Categoria],$B10,Entradas[Status],X!$E$2,Entradas[Conta Financeira],X!$E$3,Entradas[Centro de Custos],X!$E$4) -> 0 | G10: =SUMIFS(Entradas[Valores],Entradas[Data do Recebimento],">="&G$6,Entradas[Data do Recebimento],"<"&EDATE(G$6,1),Entradas[Categoria],$B10,Entradas[Status],X!$E$2,Entradas[Conta Financeira],X!$E$3,Entradas[Centro de Custos],X!$E$4) -> 0 | H10: =SUMIFS(Entradas[Valores],Entradas[Data do Recebimento],">="&H$6,Entradas[Data do Recebimento],"<"&EDATE(H$6,1),Entradas[Categoria],$B10,Entradas[Status],X!$E$2,Entradas[Conta Financeira],X!$E$3,Entradas[Centro de Custos],X!$E$4) -> 0 | I10: =SUMIFS(Entradas[Valores],Entradas[Data do Recebimento],">="&I$6,Entradas[Data do Recebimento],"<"&EDATE(I$6,1),Entradas[Categoria],$B10,Entradas[Status],X!$E$2,Entradas[Conta Financeira],X!$E$3,Entradas[Centro de Custos],X!$E$4) -> 0 | J10: =SUMIFS(Entradas[Valores],Entradas[Data do Recebimento],">="&J$6,Entradas[Data do Recebimento],"<"&EDATE(J$6,1),Entradas[Categoria],$B10,Entradas[Status],X!$E$2,Entradas[Conta Financeira],X!$E$3,Entradas[Centro de Custos],X!$E$4) -> 0 | ... N10: =SUMIFS(Entradas[Valores],Entradas[Data do Recebimento],">="&N$6,Entradas[Data do Recebimento],"<"&EDATE(N$6,1),Entradas[Categoria],$B10,Entradas[Status],X!$E$2,Entradas[Conta Financeira],X!$E$3,Entradas[Centro de Custos],X!$E$4) -> 3700 | O10: =SUM(C10:N10) -> 6600
B11: =X!V3 -> Outras Receitas Operacionais | C11: =SUMIFS(Entradas[Valores],Entradas[Data do Recebimento],">="&C$6,Entradas[Data do Recebimento],"<"&EDATE(C$6,1),Entradas[Categoria],$B11,Entradas[Status],X!$E$2,Entradas[Conta Financeira],X!$E$3,Entradas[Centro de Custos],X!$E$4) -> 0 | D11: =SUMIFS(Entradas[Valores],Entradas[Data do Recebimento],">="&D$6,Entradas[Data do Recebimento],"<"&EDATE(D$6,1),Entradas[Categoria],$B11,Entradas[Status],X!$E$2,Entradas[Conta Financeira],X!$E$3,Entradas[Centro de Custos],X!$E$4) -> 0 | E11: =SUMIFS(Entradas[Valores],Entradas[Data do Recebimento],">="&E$6,Entradas[Data do Recebimento],"<"&EDATE(E$6,1),Entradas[Categoria],$B11,Entradas[Status],X!$E$2,Entradas[Conta Financeira],X!$E$3,Entradas[Centro de Custos],X!$E$4) -> 0 | F11: =SUMIFS(Entradas[Valores],Entradas[Data do Recebimento],">="&F$6,Entradas[Data do Recebimento],"<"&EDATE(F$6,1),Entradas[Categoria],$B11,Entradas[Status],X!$E$2,Entradas[Conta Financeira],X!$E$3,Entradas[Centro de Custos],X!$E$4) -> 0 | G11: =SUMIFS(Entradas[Valores],Entradas[Data do Recebimento],">="&G$6,Entradas[Data do Recebimento],"<"&EDATE(G$6,1),Entradas[Categoria],$B11,Entradas[Status],X!$E$2,Entradas[Conta Financeira],X!$E$3,Entradas[Centro de Custos],X!$E$4) -> 0 | H11: =SUMIFS(Entradas[Valores],Entradas[Data do Recebimento],">="&H$6,Entradas[Data do Recebimento],"<"&EDATE(H$6,1),Entradas[Categoria],$B11,Entradas[Status],X!$E$2,Entradas[Conta Financeira],X!$E$3,Entradas[Centro de Custos],X!$E$4) -> 0 | I11: =SUMIFS(Entradas[Valores],Entradas[Data do Recebimento],">="&I$6,Entradas[Data do Recebimento],"<"&EDATE(I$6,1),Entradas[Categoria],$B11,Entradas[Status],X!$E$2,Entradas[Conta Financeira],X!$E$3,Entradas[Centro de Custos],X!$E$4) -> 0 | J11: =SUMIFS(Entradas[Valores],Entradas[Data do Recebimento],">="&J$6,Entradas[Data do Recebimento],"<"&EDATE(J$6,1),Entradas[Categoria],$B11,Entradas[Status],X!$E$2,Entradas[Conta Financeira],X!$E$3,Entradas[Centro de Custos],X!$E$4) -> 0 | ... N11: =SUMIFS(Entradas[Valores],Entradas[Data do Recebimento],">="&N$6,Entradas[Data do Recebimento],"<"&EDATE(N$6,1),Entradas[Categoria],$B11,Entradas[Status],X!$E$2,Entradas[Conta Financeira],X!$E$3,Entradas[Centro de Custos],X!$E$4) -> 0 | O11: =SUM(C11:N11) -> 0
B12: =X!V4 -> Receitas Financeiras | C12: =SUMIFS(Entradas[Valores],Entradas[Data do Recebimento],">="&C$6,Entradas[Data do Recebimento],"<"&EDATE(C$6,1),Entradas[Categoria],$B12,Entradas[Status],X!$E$2,Entradas[Conta Financeira],X!$E$3,Entradas[Centro de Custos],X!$E$4) -> 0 | D12: =SUMIFS(Entradas[Valores],Entradas[Data do Recebimento],">="&D$6,Entradas[Data do Recebimento],"<"&EDATE(D$6,1),Entradas[Categoria],$B12,Entradas[Status],X!$E$2,Entradas[Conta Financeira],X!$E$3,Entradas[Centro de Custos],X!$E$4) -> 0 | E12: =SUMIFS(Entradas[Valores],Entradas[Data do Recebimento],">="&E$6,Entradas[Data do Recebimento],"<"&EDATE(E$6,1),Entradas[Categoria],$B12,Entradas[Status],X!$E$2,Entradas[Conta Financeira],X!$E$3,Entradas[Centro de Custos],X!$E$4) -> 0 | F12: =SUMIFS(Entradas[Valores],Entradas[Data do Recebimento],">="&F$6,Entradas[Data do Recebimento],"<"&EDATE(F$6,1),Entradas[Categoria],$B12,Entradas[Status],X!$E$2,Entradas[Conta Financeira],X!$E$3,Entradas[Centro de Custos],X!$E$4) -> 0 | G12: =SUMIFS(Entradas[Valores],Entradas[Data do Recebimento],">="&G$6,Entradas[Data do Recebimento],"<"&EDATE(G$6,1),Entradas[Categoria],$B12,Entradas[Status],X!$E$2,Entradas[Conta Financeira],X!$E$3,Entradas[Centro de Custos],X!$E$4) -> 0 | H12: =SUMIFS(Entradas[Valores],Entradas[Data do Recebimento],">="&H$6,Entradas[Data do Recebimento],"<"&EDATE(H$6,1),Entradas[Categoria],$B12,Entradas[Status],X!$E$2,Entradas[Conta Financeira],X!$E$3,Entradas[Centro de Custos],X!$E$4) -> 0 | I12: =SUMIFS(Entradas[Valores],Entradas[Data do Recebimento],">="&I$6,Entradas[Data do Recebimento],"<"&EDATE(I$6,1),Entradas[Categoria],$B12,Entradas[Status],X!$E$2,Entradas[Conta Financeira],X!$E$3,Entradas[Centro de Custos],X!$E$4) -> 0 | J12: =SUMIFS(Entradas[Valores],Entradas[Data do Recebimento],">="&J$6,Entradas[Data do Recebimento],"<"&EDATE(J$6,1),Entradas[Categoria],$B12,Entradas[Status],X!$E$2,Entradas[Conta Financeira],X!$E$3,Entradas[Centro de Custos],X!$E$4) -> 0 | ... N12: =SUMIFS(Entradas[Valores],Entradas[Data do Recebimento],">="&N$6,Entradas[Data do Recebimento],"<"&EDATE(N$6,1),Entradas[Categoria],$B12,Entradas[Status],X!$E$2,Entradas[Conta Financeira],X!$E$3,Entradas[Centro de Custos],X!$E$4) -> 0 | O12: =SUM(C12:N12) -> 0
B13: =X!V5 -> Receitas não operacionais | C13: =SUMIFS(Entradas[Valores],Entradas[Data do Recebimento],">="&C$6,Entradas[Data do Recebimento],"<"&EDATE(C$6,1),Entradas[Categoria],$B13,Entradas[Status],X!$E$2,Entradas[Conta Financeira],X!$E$3,Entradas[Centro de Custos],X!$E$4) -> 0 | D13: =SUMIFS(Entradas[Valores],Entradas[Data do Recebimento],">="&D$6,Entradas[Data do Recebimento],"<"&EDATE(D$6,1),Entradas[Categoria],$B13,Entradas[Status],X!$E$2,Entradas[Conta Financeira],X!$E$3,Entradas[Centro de Custos],X!$E$4) -> 0 | E13: =SUMIFS(Entradas[Valores],Entradas[Data do Recebimento],">="&E$6,Entradas[Data do Recebimento],"<"&EDATE(E$6,1),Entradas[Categoria],$B13,Entradas[Status],X!$E$2,Entradas[Conta Financeira],X!$E$3,Entradas[Centro de Custos],X!$E$4) -> 0 | F13: =SUMIFS(Entradas[Valores],Entradas[Data do Recebimento],">="&F$6,Entradas[Data do Recebimento],"<"&EDATE(F$6,1),Entradas[Categoria],$B13,Entradas[Status],X!$E$2,Entradas[Conta Financeira],X!$E$3,Entradas[Centro de Custos],X!$E$4) -> 0 | G13: =SUMIFS(Entradas[Valores],Entradas[Data do Recebimento],">="&G$6,Entradas[Data do Recebimento],"<"&EDATE(G$6,1),Entradas[Categoria],$B13,Entradas[Status],X!$E$2,Entradas[Conta Financeira],X!$E$3,Entradas[Centro de Custos],X!$E$4) -> 0 | H13: =SUMIFS(Entradas[Valores],Entradas[Data do Recebimento],">="&H$6,Entradas[Data do Recebimento],"<"&EDATE(H$6,1),Entradas[Categoria],$B13,Entradas[Status],X!$E$2,Entradas[Conta Financeira],X!$E$3,Entradas[Centro de Custos],X!$E$4) -> 0 | I13: =SUMIFS(Entradas[Valores],Entradas[Data do Recebimento],">="&I$6,Entradas[Data do Recebimento],"<"&EDATE(I$6,1),Entradas[Categoria],$B13,Entradas[Status],X!$E$2,Entradas[Conta Financeira],X!$E$3,Entradas[Centro de Custos],X!$E$4) -> 0 | J13: =SUMIFS(Entradas[Valores],Entradas[Data do Recebimento],">="&J$6,Entradas[Data do Recebimento],"<"&EDATE(J$6,1),Entradas[Categoria],$B13,Entradas[Status],X!$E$2,Entradas[Conta Financeira],X!$E$3,Entradas[Centro de Custos],X!$E$4) -> 0 | ... N13: =SUMIFS(Entradas[Valores],Entradas[Data do Recebimento],">="&N$6,Entradas[Data do Recebimento],"<"&EDATE(N$6,1),Entradas[Categoria],$B13,Entradas[Status],X!$E$2,Entradas[Conta Financeira],X!$E$3,Entradas[Centro de Custos],X!$E$4) -> 0 | O13: =SUM(C13:N13) -> 10000
B14: Saídas | C14: =SUM(C15:C24) -> 0 | D14: =SUM(D15:D24) -> 0 | E14: =SUM(E15:E24) -> 0 | F14: =SUM(F15:F24) -> 0 | G14: =SUM(G15:G24) -> 0 | H14: =SUM(H15:H24) -> 0 | I14: =SUM(I15:I24) -> 0 | J14: =SUM(J15:J24) -> 0 | ... N14: =SUM(N15:N24) -> 0 | O14: =SUM(C14:N14) -> 55313
B15: =X!V6 -> Deduções sobre vendas | C15: =SUMIFS(Saidas[Valores],Saidas[Data do Pagamento],">="&C$6,Saidas[Data do Pagamento],"<"&EDATE(C$6,1),Saidas[Categoria],$B15,Saidas[Status],X!$E$2,Saidas[Conta Financeira],X!$E$3,Saidas[Centro de Custos],X!$E$4) -> 0 | D15: =SUMIFS(Saidas[Valores],Saidas[Data do Pagamento],">="&D$6,Saidas[Data do Pagamento],"<"&EDATE(D$6,1),Saidas[Categoria],$B15,Saidas[Status],X!$E$2,Saidas[Conta Financeira],X!$E$3,Saidas[Centro de Custos],X!$E$4) -> 0 | E15: =SUMIFS(Saidas[Valores],Saidas[Data do Pagamento],">="&E$6,Saidas[Data do Pagamento],"<"&EDATE(E$6,1),Saidas[Categoria],$B15,Saidas[Status],X!$E$2,Saidas[Conta Financeira],X!$E$3,Saidas[Centro de Custos],X!$E$4) -> 0 | F15: =SUMIFS(Saidas[Valores],Saidas[Data do Pagamento],">="&F$6,Saidas[Data do Pagamento],"<"&EDATE(F$6,1),Saidas[Categoria],$B15,Saidas[Status],X!$E$2,Saidas[Conta Financeira],X!$E$3,Saidas[Centro de Custos],X!$E$4) -> 0 | G15: =SUMIFS(Saidas[Valores],Saidas[Data do Pagamento],">="&G$6,Saidas[Data do Pagamento],"<"&EDATE(G$6,1),Saidas[Categoria],$B15,Saidas[Status],X!$E$2,Saidas[Conta Financeira],X!$E$3,Saidas[Centro de Custos],X!$E$4) -> 0 | H15: =SUMIFS(Saidas[Valores],Saidas[Data do Pagamento],">="&H$6,Saidas[Data do Pagamento],"<"&EDATE(H$6,1),Saidas[Categoria],$B15,Saidas[Status],X!$E$2,Saidas[Conta Financeira],X!$E$3,Saidas[Centro de Custos],X!$E$4) -> 0 | I15: =SUMIFS(Saidas[Valores],Saidas[Data do Pagamento],">="&I$6,Saidas[Data do Pagamento],"<"&EDATE(I$6,1),Saidas[Categoria],$B15,Saidas[Status],X!$E$2,Saidas[Conta Financeira],X!$E$3,Saidas[Centro de Custos],X!$E$4) -> 0 | J15: =SUMIFS(Saidas[Valores],Saidas[Data do Pagamento],">="&J$6,Saidas[Data do Pagamento],"<"&EDATE(J$6,1),Saidas[Categoria],$B15,Saidas[Status],X!$E$2,Saidas[Conta Financeira],X!$E$3,Saidas[Centro de Custos],X!$E$4) -> 0 | ... N15: =SUMIFS(Saidas[Valores],Saidas[Data do Pagamento],">="&N$6,Saidas[Data do Pagamento],"<"&EDATE(N$6,1),Saidas[Categoria],$B15,Saidas[Status],X!$E$2,Saidas[Conta Financeira],X!$E$3,Saidas[Centro de Custos],X!$E$4) -> 0 | O15: =SUM(C15:N15) -> 0
B16: =X!V7 -> Custo das Vendas | C16: =SUMIFS(Saidas[Valores],Saidas[Data do Pagamento],">="&C$6,Saidas[Data do Pagamento],"<"&EDATE(C$6,1),Saidas[Categoria],$B16,Saidas[Status],X!$E$2,Saidas[Conta Financeira],X!$E$3,Saidas[Centro de Custos],X!$E$4) -> 0 | D16: =SUMIFS(Saidas[Valores],Saidas[Data do Pagamento],">="&D$6,Saidas[Data do Pagamento],"<"&EDATE(D$6,1),Saidas[Categoria],$B16,Saidas[Status],X!$E$2,Saidas[Conta Financeira],X!$E$3,Saidas[Centro de Custos],X!$E$4) -> 0 | E16: =SUMIFS(Saidas[Valores],Saidas[Data do Pagamento],">="&E$6,Saidas[Data do Pagamento],"<"&EDATE(E$6,1),Saidas[Categoria],$B16,Saidas[Status],X!$E$2,Saidas[Conta Financeira],X!$E$3,Saidas[Centro de Custos],X!$E$4) -> 0 | F16: =SUMIFS(Saidas[Valores],Saidas[Data do Pagamento],">="&F$6,Saidas[Data do Pagamento],"<"&EDATE(F$6,1),Saidas[Categoria],$B16,Saidas[Status],X!$E$2,Saidas[Conta Financeira],X!$E$3,Saidas[Centro de Custos],X!$E$4) -> 0 | G16: =SUMIFS(Saidas[Valores],Saidas[Data do Pagamento],">="&G$6,Saidas[Data do Pagamento],"<"&EDATE(G$6,1),Saidas[Categoria],$B16,Saidas[Status],X!$E$2,Saidas[Conta Financeira],X!$E$3,Saidas[Centro de Custos],X!$E$4) -> 0 | H16: =SUMIFS(Saidas[Valores],Saidas[Data do Pagamento],">="&H$6,Saidas[Data do Pagamento],"<"&EDATE(H$6,1),Saidas[Categoria],$B16,Saidas[Status],X!$E$2,Saidas[Conta Financeira],X!$E$3,Saidas[Centro de Custos],X!$E$4) -> 0 | I16: =SUMIFS(Saidas[Valores],Saidas[Data do Pagamento],">="&I$6,Saidas[Data do Pagamento],"<"&EDATE(I$6,1),Saidas[Categoria],$B16,Saidas[Status],X!$E$2,Saidas[Conta Financeira],X!$E$3,Saidas[Centro de Custos],X!$E$4) -> 0 | J16: =SUMIFS(Saidas[Valores],Saidas[Data do Pagamento],">="&J$6,Saidas[Data do Pagamento],"<"&EDATE(J$6,1),Saidas[Categoria],$B16,Saidas[Status],X!$E$2,Saidas[Conta Financeira],X!$E$3,Saidas[Centro de Custos],X!$E$4) -> 0 | ... N16: =SUMIFS(Saidas[Valores],Saidas[Data do Pagamento],">="&N$6,Saidas[Data do Pagamento],"<"&EDATE(N$6,1),Saidas[Categoria],$B16,Saidas[Status],X!$E$2,Saidas[Conta Financeira],X!$E$3,Saidas[Centro de Custos],X!$E$4) -> 0 | O16: =SUM(C16:N16) -> 8123
B17: =X!V8 -> Despesas administrativas | C17: =SUMIFS(Saidas[Valores],Saidas[Data do Pagamento],">="&C$6,Saidas[Data do Pagamento],"<"&EDATE(C$6,1),Saidas[Categoria],$B17,Saidas[Status],X!$E$2,Saidas[Conta Financeira],X!$E$3,Saidas[Centro de Custos],X!$E$4) -> 0 | D17: =SUMIFS(Saidas[Valores],Saidas[Data do Pagamento],">="&D$6,Saidas[Data do Pagamento],"<"&EDATE(D$6,1),Saidas[Categoria],$B17,Saidas[Status],X!$E$2,Saidas[Conta Financeira],X!$E$3,Saidas[Centro de Custos],X!$E$4) -> 0 | E17: =SUMIFS(Saidas[Valores],Saidas[Data do Pagamento],">="&E$6,Saidas[Data do Pagamento],"<"&EDATE(E$6,1),Saidas[Categoria],$B17,Saidas[Status],X!$E$2,Saidas[Conta Financeira],X!$E$3,Saidas[Centro de Custos],X!$E$4) -> 0 | F17: =SUMIFS(Saidas[Valores],Saidas[Data do Pagamento],">="&F$6,Saidas[Data do Pagamento],"<"&EDATE(F$6,1),Saidas[Categoria],$B17,Saidas[Status],X!$E$2,Saidas[Conta Financeira],X!$E$3,Saidas[Centro de Custos],X!$E$4) -> 0 | G17: =SUMIFS(Saidas[Valores],Saidas[Data do Pagamento],">="&G$6,Saidas[Data do Pagamento],"<"&EDATE(G$6,1),Saidas[Categoria],$B17,Saidas[Status],X!$E$2,Saidas[Conta Financeira],X!$E$3,Saidas[Centro de Custos],X!$E$4) -> 0 | H17: =SUMIFS(Saidas[Valores],Saidas[Data do Pagamento],">="&H$6,Saidas[Data do Pagamento],"<"&EDATE(H$6,1),Saidas[Categoria],$B17,Saidas[Status],X!$E$2,Saidas[Conta Financeira],X!$E$3,Saidas[Centro de Custos],X!$E$4) -> 0 | I17: =SUMIFS(Saidas[Valores],Saidas[Data do Pagamento],">="&I$6,Saidas[Data do Pagamento],"<"&EDATE(I$6,1),Saidas[Categoria],$B17,Saidas[Status],X!$E$2,Saidas[Conta Financeira],X!$E$3,Saidas[Centro de Custos],X!$E$4) -> 0 | J17: =SUMIFS(Saidas[Valores],Saidas[Data do Pagamento],">="&J$6,Saidas[Data do Pagamento],"<"&EDATE(J$6,1),Saidas[Categoria],$B17,Saidas[Status],X!$E$2,Saidas[Conta Financeira],X!$E$3,Saidas[Centro de Custos],X!$E$4) -> 0 | ... N17: =SUMIFS(Saidas[Valores],Saidas[Data do Pagamento],">="&N$6,Saidas[Data do Pagamento],"<"&EDATE(N$6,1),Saidas[Categoria],$B17,Saidas[Status],X!$E$2,Saidas[Conta Financeira],X!$E$3,Saidas[Centro de Custos],X!$E$4) -> 0 | O17: =SUM(C17:N17) -> 4270
B18: =X!V9 -> Despesa com Pessoal | C18: =SUMIFS(Saidas[Valores],Saidas[Data do Pagamento],">="&C$6,Saidas[Data do Pagamento],"<"&EDATE(C$6,1),Saidas[Categoria],$B18,Saidas[Status],X!$E$2,Saidas[Conta Financeira],X!$E$3,Saidas[Centro de Custos],X!$E$4) -> 0 | D18: =SUMIFS(Saidas[Valores],Saidas[Data do Pagamento],">="&D$6,Saidas[Data do Pagamento],"<"&EDATE(D$6,1),Saidas[Categoria],$B18,Saidas[Status],X!$E$2,Saidas[Conta Financeira],X!$E$3,Saidas[Centro de Custos],X!$E$4) -> 0 | E18: =SUMIFS(Saidas[Valores],Saidas[Data do Pagamento],">="&E$6,Saidas[Data do Pagamento],"<"&EDATE(E$6,1),Saidas[Categoria],$B18,Saidas[Status],X!$E$2,Saidas[Conta Financeira],X!$E$3,Saidas[Centro de Custos],X!$E$4) -> 0 | F18: =SUMIFS(Saidas[Valores],Saidas[Data do Pagamento],">="&F$6,Saidas[Data do Pagamento],"<"&EDATE(F$6,1),Saidas[Categoria],$B18,Saidas[Status],X!$E$2,Saidas[Conta Financeira],X!$E$3,Saidas[Centro de Custos],X!$E$4) -> 0 | G18: =SUMIFS(Saidas[Valores],Saidas[Data do Pagamento],">="&G$6,Saidas[Data do Pagamento],"<"&EDATE(G$6,1),Saidas[Categoria],$B18,Saidas[Status],X!$E$2,Saidas[Conta Financeira],X!$E$3,Saidas[Centro de Custos],X!$E$4) -> 0 | H18: =SUMIFS(Saidas[Valores],Saidas[Data do Pagamento],">="&H$6,Saidas[Data do Pagamento],"<"&EDATE(H$6,1),Saidas[Categoria],$B18,Saidas[Status],X!$E$2,Saidas[Conta Financeira],X!$E$3,Saidas[Centro de Custos],X!$E$4) -> 0 | I18: =SUMIFS(Saidas[Valores],Saidas[Data do Pagamento],">="&I$6,Saidas[Data do Pagamento],"<"&EDATE(I$6,1),Saidas[Categoria],$B18,Saidas[Status],X!$E$2,Saidas[Conta Financeira],X!$E$3,Saidas[Centro de Custos],X!$E$4) -> 0 | J18: =SUMIFS(Saidas[Valores],Saidas[Data do Pagamento],">="&J$6,Saidas[Data do Pagamento],"<"&EDATE(J$6,1),Saidas[Categoria],$B18,Saidas[Status],X!$E$2,Saidas[Conta Financeira],X!$E$3,Saidas[Centro de Custos],X!$E$4) -> 0 | ... N18: =SUMIFS(Saidas[Valores],Saidas[Data do Pagamento],">="&N$6,Saidas[Data do Pagamento],"<"&EDATE(N$6,1),Saidas[Categoria],$B18,Saidas[Status],X!$E$2,Saidas[Conta Financeira],X!$E$3,Saidas[Centro de Custos],X!$E$4) -> 0 | O18: =SUM(C18:N18) -> 7920
B19: =X!V11 -> Despesa Financeira | C19: =SUMIFS(Saidas[Valores],Saidas[Data do Pagamento],">="&C$6,Saidas[Data do Pagamento],"<"&EDATE(C$6,1),Saidas[Categoria],$B19,Saidas[Status],X!$E$2,Saidas[Conta Financeira],X!$E$3,Saidas[Centro de Custos],X!$E$4) -> 0 | D19: =SUMIFS(Saidas[Valores],Saidas[Data do Pagamento],">="&D$6,Saidas[Data do Pagamento],"<"&EDATE(D$6,1),Saidas[Categoria],$B19,Saidas[Status],X!$E$2,Saidas[Conta Financeira],X!$E$3,Saidas[Centro de Custos],X!$E$4) -> 0 | E19: =SUMIFS(Saidas[Valores],Saidas[Data do Pagamento],">="&E$6,Saidas[Data do Pagamento],"<"&EDATE(E$6,1),Saidas[Categoria],$B19,Saidas[Status],X!$E$2,Saidas[Conta Financeira],X!$E$3,Saidas[Centro de Custos],X!$E$4) -> 0 | F19: =SUMIFS(Saidas[Valores],Saidas[Data do Pagamento],">="&F$6,Saidas[Data do Pagamento],"<"&EDATE(F$6,1),Saidas[Categoria],$B19,Saidas[Status],X!$E$2,Saidas[Conta Financeira],X!$E$3,Saidas[Centro de Custos],X!$E$4) -> 0 | G19: =SUMIFS(Saidas[Valores],Saidas[Data do Pagamento],">="&G$6,Saidas[Data do Pagamento],"<"&EDATE(G$6,1),Saidas[Categoria],$B19,Saidas[Status],X!$E$2,Saidas[Conta Financeira],X!$E$3,Saidas[Centro de Custos],X!$E$4) -> 0 | H19: =SUMIFS(Saidas[Valores],Saidas[Data do Pagamento],">="&H$6,Saidas[Data do Pagamento],"<"&EDATE(H$6,1),Saidas[Categoria],$B19,Saidas[Status],X!$E$2,Saidas[Conta Financeira],X!$E$3,Saidas[Centro de Custos],X!$E$4) -> 0 | I19: =SUMIFS(Saidas[Valores],Saidas[Data do Pagamento],">="&I$6,Saidas[Data do Pagamento],"<"&EDATE(I$6,1),Saidas[Categoria],$B19,Saidas[Status],X!$E$2,Saidas[Conta Financeira],X!$E$3,Saidas[Centro de Custos],X!$E$4) -> 0 | J19: =SUMIFS(Saidas[Valores],Saidas[Data do Pagamento],">="&J$6,Saidas[Data do Pagamento],"<"&EDATE(J$6,1),Saidas[Categoria],$B19,Saidas[Status],X!$E$2,Saidas[Conta Financeira],X!$E$3,Saidas[Centro de Custos],X!$E$4) -> 0 | ... N19: =SUMIFS(Saidas[Valores],Saidas[Data do Pagamento],">="&N$6,Saidas[Data do Pagamento],"<"&EDATE(N$6,1),Saidas[Categoria],$B19,Saidas[Status],X!$E$2,Saidas[Conta Financeira],X!$E$3,Saidas[Centro de Custos],X!$E$4) -> 0 | O19: =SUM(C19:N19) -> 0
B20: =X!V12 -> Despesas não operacionais | C20: =SUMIFS(Saidas[Valores],Saidas[Data do Pagamento],">="&C$6,Saidas[Data do Pagamento],"<"&EDATE(C$6,1),Saidas[Categoria],$B20,Saidas[Status],X!$E$2,Saidas[Conta Financeira],X!$E$3,Saidas[Centro de Custos],X!$E$4) -> 0 | D20: =SUMIFS(Saidas[Valores],Saidas[Data do Pagamento],">="&D$6,Saidas[Data do Pagamento],"<"&EDATE(D$6,1),Saidas[Categoria],$B20,Saidas[Status],X!$E$2,Saidas[Conta Financeira],X!$E$3,Saidas[Centro de Custos],X!$E$4) -> 0 | E20: =SUMIFS(Saidas[Valores],Saidas[Data do Pagamento],">="&E$6,Saidas[Data do Pagamento],"<"&EDATE(E$6,1),Saidas[Categoria],$B20,Saidas[Status],X!$E$2,Saidas[Conta Financeira],X!$E$3,Saidas[Centro de Custos],X!$E$4) -> 0 | F20: =SUMIFS(Saidas[Valores],Saidas[Data do Pagamento],">="&F$6,Saidas[Data do Pagamento],"<"&EDATE(F$6,1),Saidas[Categoria],$B20,Saidas[Status],X!$E$2,Saidas[Conta Financeira],X!$E$3,Saidas[Centro de Custos],X!$E$4) -> 0 | G20: =SUMIFS(Saidas[Valores],Saidas[Data do Pagamento],">="&G$6,Saidas[Data do Pagamento],"<"&EDATE(G$6,1),Saidas[Categoria],$B20,Saidas[Status],X!$E$2,Saidas[Conta Financeira],X!$E$3,Saidas[Centro de Custos],X!$E$4) -> 0 | H20: =SUMIFS(Saidas[Valores],Saidas[Data do Pagamento],">="&H$6,Saidas[Data do Pagamento],"<"&EDATE(H$6,1),Saidas[Categoria],$B20,Saidas[Status],X!$E$2,Saidas[Conta Financeira],X!$E$3,Saidas[Centro de Custos],X!$E$4) -> 0 | I20: =SUMIFS(Saidas[Valores],Saidas[Data do Pagamento],">="&I$6,Saidas[Data do Pagamento],"<"&EDATE(I$6,1),Saidas[Categoria],$B20,Saidas[Status],X!$E$2,Saidas[Conta Financeira],X!$E$3,Saidas[Centro de Custos],X!$E$4) -> 0 | J20: =SUMIFS(Saidas[Valores],Saidas[Data do Pagamento],">="&J$6,Saidas[Data do Pagamento],"<"&EDATE(J$6,1),Saidas[Categoria],$B20,Saidas[Status],X!$E$2,Saidas[Conta Financeira],X!$E$3,Saidas[Centro de Custos],X!$E$4) -> 0 | ... N20: =SUMIFS(Saidas[Valores],Saidas[Data do Pagamento],">="&N$6,Saidas[Data do Pagamento],"<"&EDATE(N$6,1),Saidas[Categoria],$B20,Saidas[Status],X!$E$2,Saidas[Conta Financeira],X!$E$3,Saidas[Centro de Custos],X!$E$4) -> 0 | O20: =SUM(C20:N20) -> 35000
B21: =X!V13 -> Impostos | C21: =SUMIFS(Saidas[Valores],Saidas[Data do Pagamento],">="&C$6,Saidas[Data do Pagamento],"<"&EDATE(C$6,1),Saidas[Categoria],$B21,Saidas[Status],X!$E$2,Saidas[Conta Financeira],X!$E$3,Saidas[Centro de Custos],X!$E$4) -> 0 | D21: =SUMIFS(Saidas[Valores],Saidas[Data do Pagamento],">="&D$6,Saidas[Data do Pagamento],"<"&EDATE(D$6,1),Saidas[Categoria],$B21,Saidas[Status],X!$E$2,Saidas[Conta Financeira],X!$E$3,Saidas[Centro de Custos],X!$E$4) -> 0 | E21: =SUMIFS(Saidas[Valores],Saidas[Data do Pagamento],">="&E$6,Saidas[Data do Pagamento],"<"&EDATE(E$6,1),Saidas[Categoria],$B21,Saidas[Status],X!$E$2,Saidas[Conta Financeira],X!$E$3,Saidas[Centro de Custos],X!$E$4) -> 0 | F21: =SUMIFS(Saidas[Valores],Saidas[Data do Pagamento],">="&F$6,Saidas[Data do Pagamento],"<"&EDATE(F$6,1),Saidas[Categoria],$B21,Saidas[Status],X!$E$2,Saidas[Conta Financeira],X!$E$3,Saidas[Centro de Custos],X!$E$4) -> 0 | G21: =SUMIFS(Saidas[Valores],Saidas[Data do Pagamento],">="&G$6,Saidas[Data do Pagamento],"<"&EDATE(G$6,1),Saidas[Categoria],$B21,Saidas[Status],X!$E$2,Saidas[Conta Financeira],X!$E$3,Saidas[Centro de Custos],X!$E$4) -> 0 | H21: =SUMIFS(Saidas[Valores],Saidas[Data do Pagamento],">="&H$6,Saidas[Data do Pagamento],"<"&EDATE(H$6,1),Saidas[Categoria],$B21,Saidas[Status],X!$E$2,Saidas[Conta Financeira],X!$E$3,Saidas[Centro de Custos],X!$E$4) -> 0 | I21: =SUMIFS(Saidas[Valores],Saidas[Data do Pagamento],">="&I$6,Saidas[Data do Pagamento],"<"&EDATE(I$6,1),Saidas[Categoria],$B21,Saidas[Status],X!$E$2,Saidas[Conta Financeira],X!$E$3,Saidas[Centro de Custos],X!$E$4) -> 0 | J21: =SUMIFS(Saidas[Valores],Saidas[Data do Pagamento],">="&J$6,Saidas[Data do Pagamento],"<"&EDATE(J$6,1),Saidas[Categoria],$B21,Saidas[Status],X!$E$2,Saidas[Conta Financeira],X!$E$3,Saidas[Centro de Custos],X!$E$4) -> 0 | ... N21: =SUMIFS(Saidas[Valores],Saidas[Data do Pagamento],">="&N$6,Saidas[Data do Pagamento],"<"&EDATE(N$6,1),Saidas[Categoria],$B21,Saidas[Status],X!$E$2,Saidas[Conta Financeira],X!$E$3,Saidas[Centro de Custos],X!$E$4) -> 0 | O21: =SUM(C21:N21) -> 0
B22: =X!V14 -> Participação e Dividendos | C22: =SUMIFS(Saidas[Valores],Saidas[Data do Pagamento],">="&C$6,Saidas[Data do Pagamento],"<"&EDATE(C$6,1),Saidas[Categoria],$B22,Saidas[Status],X!$E$2,Saidas[Conta Financeira],X!$E$3,Saidas[Centro de Custos],X!$E$4) -> 0 | D22: =SUMIFS(Saidas[Valores],Saidas[Data do Pagamento],">="&D$6,Saidas[Data do Pagamento],"<"&EDATE(D$6,1),Saidas[Categoria],$B22,Saidas[Status],X!$E$2,Saidas[Conta Financeira],X!$E$3,Saidas[Centro de Custos],X!$E$4) -> 0 | E22: =SUMIFS(Saidas[Valores],Saidas[Data do Pagamento],">="&E$6,Saidas[Data do Pagamento],"<"&EDATE(E$6,1),Saidas[Categoria],$B22,Saidas[Status],X!$E$2,Saidas[Conta Financeira],X!$E$3,Saidas[Centro de Custos],X!$E$4) -> 0 | F22: =SUMIFS(Saidas[Valores],Saidas[Data do Pagamento],">="&F$6,Saidas[Data do Pagamento],"<"&EDATE(F$6,1),Saidas[Categoria],$B22,Saidas[Status],X!$E$2,Saidas[Conta Financeira],X!$E$3,Saidas[Centro de Custos],X!$E$4) -> 0 | G22: =SUMIFS(Saidas[Valores],Saidas[Data do Pagamento],">="&G$6,Saidas[Data do Pagamento],"<"&EDATE(G$6,1),Saidas[Categoria],$B22,Saidas[Status],X!$E$2,Saidas[Conta Financeira],X!$E$3,Saidas[Centro de Custos],X!$E$4) -> 0 | H22: =SUMIFS(Saidas[Valores],Saidas[Data do Pagamento],">="&H$6,Saidas[Data do Pagamento],"<"&EDATE(H$6,1),Saidas[Categoria],$B22,Saidas[Status],X!$E$2,Saidas[Conta Financeira],X!$E$3,Saidas[Centro de Custos],X!$E$4) -> 0 | I22: =SUMIFS(Saidas[Valores],Saidas[Data do Pagamento],">="&I$6,Saidas[Data do Pagamento],"<"&EDATE(I$6,1),Saidas[Categoria],$B22,Saidas[Status],X!$E$2,Saidas[Conta Financeira],X!$E$3,Saidas[Centro de Custos],X!$E$4) -> 0 | J22: =SUMIFS(Saidas[Valores],Saidas[Data do Pagamento],">="&J$6,Saidas[Data do Pagamento],"<"&EDATE(J$6,1),Saidas[Categoria],$B22,Saidas[Status],X!$E$2,Saidas[Conta Financeira],X!$E$3,Saidas[Centro de Custos],X!$E$4) -> 0 | ... N22: =SUMIFS(Saidas[Valores],Saidas[Data do Pagamento],">="&N$6,Saidas[Data do Pagamento],"<"&EDATE(N$6,1),Saidas[Categoria],$B22,Saidas[Status],X!$E$2,Saidas[Conta Financeira],X!$E$3,Saidas[Centro de Custos],X!$E$4) -> 0 | O22: =SUM(C22:N22) -> 0
B23: =X!V15 | C23: =SUMIFS(Saidas[Valores],Saidas[Data do Pagamento],">="&C$6,Saidas[Data do Pagamento],"<"&EDATE(C$6,1),Saidas[Categoria],$B23,Saidas[Status],X!$E$2,Saidas[Conta Financeira],X!$E$3,Saidas[Centro de Custos],X!$E$4) -> 0 | D23: =SUMIFS(Saidas[Valores],Saidas[Data do Pagamento],">="&D$6,Saidas[Data do Pagamento],"<"&EDATE(D$6,1),Saidas[Categoria],$B23,Saidas[Status],X!$E$2,Saidas[Conta Financeira],X!$E$3,Saidas[Centro de Custos],X!$E$4) -> 0 | E23: =SUMIFS(Saidas[Valores],Saidas[Data do Pagamento],">="&E$6,Saidas[Data do Pagamento],"<"&EDATE(E$6,1),Saidas[Categoria],$B23,Saidas[Status],X!$E$2,Saidas[Conta Financeira],X!$E$3,Saidas[Centro de Custos],X!$E$4) -> 0 | F23: =SUMIFS(Saidas[Valores],Saidas[Data do Pagamento],">="&F$6,Saidas[Data do Pagamento],"<"&EDATE(F$6,1),Saidas[Categoria],$B23,Saidas[Status],X!$E$2,Saidas[Conta Financeira],X!$E$3,Saidas[Centro de Custos],X!$E$4) -> 0 | G23: =SUMIFS(Saidas[Valores],Saidas[Data do Pagamento],">="&G$6,Saidas[Data do Pagamento],"<"&EDATE(G$6,1),Saidas[Categoria],$B23,Saidas[Status],X!$E$2,Saidas[Conta Financeira],X!$E$3,Saidas[Centro de Custos],X!$E$4) -> 0 | H23: =SUMIFS(Saidas[Valores],Saidas[Data do Pagamento],">="&H$6,Saidas[Data do Pagamento],"<"&EDATE(H$6,1),Saidas[Categoria],$B23,Saidas[Status],X!$E$2,Saidas[Conta Financeira],X!$E$3,Saidas[Centro de Custos],X!$E$4) -> 0 | I23: =SUMIFS(Saidas[Valores],Saidas[Data do Pagamento],">="&I$6,Saidas[Data do Pagamento],"<"&EDATE(I$6,1),Saidas[Categoria],$B23,Saidas[Status],X!$E$2,Saidas[Conta Financeira],X!$E$3,Saidas[Centro de Custos],X!$E$4) -> 0 | J23: =SUMIFS(Saidas[Valores],Saidas[Data do Pagamento],">="&J$6,Saidas[Data do Pagamento],"<"&EDATE(J$6,1),Saidas[Categoria],$B23,Saidas[Status],X!$E$2,Saidas[Conta Financeira],X!$E$3,Saidas[Centro de Custos],X!$E$4) -> 0 | ... N23: =SUMIFS(Saidas[Valores],Saidas[Data do Pagamento],">="&N$6,Saidas[Data do Pagamento],"<"&EDATE(N$6,1),Saidas[Categoria],$B23,Saidas[Status],X!$E$2,Saidas[Conta Financeira],X!$E$3,Saidas[Centro de Custos],X!$E$4) -> 0 | O23: =SUM(C23:N23) -> 0
B24: =X!V16 | C24: =SUMIFS(Saidas[Valores],Saidas[Data do Pagamento],">="&C$6,Saidas[Data do Pagamento],"<"&EDATE(C$6,1),Saidas[Categoria],$B24,Saidas[Status],X!$E$2,Saidas[Conta Financeira],X!$E$3,Saidas[Centro de Custos],X!$E$4) -> 0 | D24: =SUMIFS(Saidas[Valores],Saidas[Data do Pagamento],">="&D$6,Saidas[Data do Pagamento],"<"&EDATE(D$6,1),Saidas[Categoria],$B24,Saidas[Status],X!$E$2,Saidas[Conta Financeira],X!$E$3,Saidas[Centro de Custos],X!$E$4) -> 0 | E24: =SUMIFS(Saidas[Valores],Saidas[Data do Pagamento],">="&E$6,Saidas[Data do Pagamento],"<"&EDATE(E$6,1),Saidas[Categoria],$B24,Saidas[Status],X!$E$2,Saidas[Conta Financeira],X!$E$3,Saidas[Centro de Custos],X!$E$4) -> 0 | F24: =SUMIFS(Saidas[Valores],Saidas[Data do Pagamento],">="&F$6,Saidas[Data do Pagamento],"<"&EDATE(F$6,1),Saidas[Categoria],$B24,Saidas[Status],X!$E$2,Saidas[Conta Financeira],X!$E$3,Saidas[Centro de Custos],X!$E$4) -> 0 | G24: =SUMIFS(Saidas[Valores],Saidas[Data do Pagamento],">="&G$6,Saidas[Data do Pagamento],"<"&EDATE(G$6,1),Saidas[Categoria],$B24,Saidas[Status],X!$E$2,Saidas[Conta Financeira],X!$E$3,Saidas[Centro de Custos],X!$E$4) -> 0 | H24: =SUMIFS(Saidas[Valores],Saidas[Data do Pagamento],">="&H$6,Saidas[Data do Pagamento],"<"&EDATE(H$6,1),Saidas[Categoria],$B24,Saidas[Status],X!$E$2,Saidas[Conta Financeira],X!$E$3,Saidas[Centro de Custos],X!$E$4) -> 0 | I24: =SUMIFS(Saidas[Valores],Saidas[Data do Pagamento],">="&I$6,Saidas[Data do Pagamento],"<"&EDATE(I$6,1),Saidas[Categoria],$B24,Saidas[Status],X!$E$2,Saidas[Conta Financeira],X!$E$3,Saidas[Centro de Custos],X!$E$4) -> 0 | J24: =SUMIFS(Saidas[Valores],Saidas[Data do Pagamento],">="&J$6,Saidas[Data do Pagamento],"<"&EDATE(J$6,1),Saidas[Categoria],$B24,Saidas[Status],X!$E$2,Saidas[Conta Financeira],X!$E$3,Saidas[Centro de Custos],X!$E$4) -> 0 | ... N24: =SUMIFS(Saidas[Valores],Saidas[Data do Pagamento],">="&N$6,Saidas[Data do Pagamento],"<"&EDATE(N$6,1),Saidas[Categoria],$B24,Saidas[Status],X!$E$2,Saidas[Conta Financeira],X!$E$3,Saidas[Centro de Custos],X!$E$4) -> 0 | O24: =SUM(C24:N24) -> 0
B26: Resultado do Mês | C26: =C9-C14 -> 0 | D26: =D9-D14 -> 0 | E26: =E9-E14 -> 0 | F26: =F9-F14 -> 0 | G26: =G9-G14 -> 0 | H26: =H9-H14 -> 0 | I26: =I9-I14 -> 0 | J26: =J9-J14 -> 0 | ... O26: =O9-O14 -> -38713
B28: Ajuste de Transferência interna | C28: =SUMIFS(Transferência_Interna[Valor],Transferência_Interna[Conta de Destino],X!$E$3,Transferência_Interna[Data],">="&C$6,Transferência_Interna[Data],"<"&EDATE(C$6,1))-SUMIFS(Transferência_Interna[Valor],Transferência_Interna[Conta de Origem],X!$E$3,Transferência_Interna[Data],">="&C$6,Transferência_Interna[Data],"<"&EDATE(C$6,1)) -> 0 | D28: =SUMIFS(Transferência_Interna[Valor],Transferência_Interna[Conta de Destino],X!$E$3,Transferência_Interna[Data],">="&D$6,Transferência_Interna[Data],"<"&EDATE(D$6,1))-SUMIFS(Transferência_Interna[Valor],Transferência_Interna[Conta de Origem],X!$E$3,Transferência_Interna[Data],">="&D$6,Transferência_Interna[Data],"<"&EDATE(D$6,1)) -> 0 | E28: =SUMIFS(Transferência_Interna[Valor],Transferência_Interna[Conta de Destino],X!$E$3,Transferência_Interna[Data],">="&E$6,Transferência_Interna[Data],"<"&EDATE(E$6,1))-SUMIFS(Transferência_Interna[Valor],Transferência_Interna[Conta de Origem],X!$E$3,Transferência_Interna[Data],">="&E$6,Transferência_Interna[Data],"<"&EDATE(E$6,1)) -> 0 | F28: =SUMIFS(Transferência_Interna[Valor],Transferência_Interna[Conta de Destino],X!$E$3,Transferência_Interna[Data],">="&F$6,Transferência_Interna[Data],"<"&EDATE(F$6,1))-SUMIFS(Transferência_Interna[Valor],Transferência_Interna[Conta de Origem],X!$E$3,Transferência_Interna[Data],">="&F$6,Transferência_Interna[Data],"<"&EDATE(F$6,1)) -> 0 | G28: =SUMIFS(Transferência_Interna[Valor],Transferência_Interna[Conta de Destino],X!$E$3,Transferência_Interna[Data],">="&G$6,Transferência_Interna[Data],"<"&EDATE(G$6,1))-SUMIFS(Transferência_Interna[Valor],Transferência_Interna[Conta de Origem],X!$E$3,Transferência_Interna[Data],">="&G$6,Transferência_Interna[Data],"<"&EDATE(G$6,1)) -> 0 | H28: =SUMIFS(Transferência_Interna[Valor],Transferência_Interna[Conta de Destino],X!$E$3,Transferência_Interna[Data],">="&H$6,Transferência_Interna[Data],"<"&EDATE(H$6,1))-SUMIFS(Transferência_Interna[Valor],Transferência_Interna[Conta de Origem],X!$E$3,Transferência_Interna[Data],">="&H$6,Transferência_Interna[Data],"<"&EDATE(H$6,1)) -> 0 | I28: =SUMIFS(Transferência_Interna[Valor],Transferência_Interna[Conta de Destino],X!$E$3,Transferência_Interna[Data],">="&I$6,Transferência_Interna[Data],"<"&EDATE(I$6,1))-SUMIFS(Transferência_Interna[Valor],Transferência_Interna[Conta de Origem],X!$E$3,Transferência_Interna[Data],">="&I$6,Transferência_Interna[Data],"<"&EDATE(I$6,1)) -> 0 | J28: =SUMIFS(Transferência_Interna[Valor],Transferência_Interna[Conta de Destino],X!$E$3,Transferência_Interna[Data],">="&J$6,Transferência_Interna[Data],"<"&EDATE(J$6,1))-SUMIFS(Transferência_Interna[Valor],Transferência_Interna[Conta de Origem],X!$E$3,Transferência_Interna[Data],">="&J$6,Transferência_Interna[Data],"<"&EDATE(J$6,1)) -> 0 | ... N28: =SUMIFS(Transferência_Interna[Valor],Transferência_Interna[Conta de Destino],X!$E$3,Transferência_Interna[Data],">="&N$6,Transferência_Interna[Data],"<"&EDATE(N$6,1))-SUMIFS(Transferência_Interna[Valor],Transferência_Interna[Conta de Origem],X!$E$3,Transferência_Interna[Data],">="&N$6,Transferência_Interna[Data],"<"&EDATE(N$6,1)) -> 0
B30: Disponível | C30: =C8+C26+C28 -> 7740 | D30: =D8+D26+D28 -> 7740 | E30: =E8+E26+E28 -> 7740 | F30: =F8+F26+F28 -> 7740 | G30: =G8+G26+G28 -> 7740 | H30: =H8+H26+H28 -> 7740 | I30: =I8+I26+I28 -> 7740 | J30: =J8+J26+J28 -> 7740 | ... N30: =N8+N26+N28 -> -30973 | O30: =N30 -> -30973

Sheet DRE
B2: DRE - Demonstrativo do Resultado do Exercício
E4: FILTROS PARA O DRE
E5: Ano: | F5: 2025 | G5: Status: | H5: Ambos | I5: Banco: | J5: Todos | L5: Centro de custos: | M5: Todos
C7: =DATE(F5,1,1) -> 45658 | D7: =EDATE(C7,1) -> 45689 | E7: =EDATE(D7,1) -> 45717 | F7: =EDATE(E7,1) -> 45748 | G7: =EDATE(F7,1) -> 45778 | H7: =EDATE(G7,1) -> 45809 | I7: =EDATE(H7,1) -> 45839 | J7: =EDATE(I7,1) -> 45870 | K7: =EDATE(J7,1) -> 45901 | ... N7: =EDATE(M7,1) -> 45992 | O7: Total
B9: DEMONSTRATIVO DO RESULTADO DO EXERCÍCIO
B10: =X!V2 -> Receitas Operacionais | C10: =SUMIFS(Entradas[Valores],Entradas[Data da Competência],">="&C$7,Entradas[Data da Competência],"<"&EDATE(C$7,1),Entradas[Categoria],$B10,Entradas[Status],X!$E$7,Entradas[Conta Financeira],X!$E$8,Entradas[Centro de Custos],X!$E$9) -> 0 | D10: =SUMIFS(Entradas[Valores],Entradas[Data da Competência],">="&D$7,Entradas[Data da Competência],"<"&EDATE(D$7,1),Entradas[Categoria],$B10,Entradas[Status],X!$E$7,Entradas[Conta Financeira],X!$E$8,Entradas[Centro de Custos],X!$E$9) -> 0 | E10: =SUMIFS(Entradas[Valores],Entradas[Data da Competência],">="&E$7,Entradas[Data da Competência],"<"&EDATE(E$7,1),Entradas[Categoria],$B10,Entradas[Status],X!$E$7,Entradas[Conta Financeira],X!$E$8,Entradas[Centro de Custos],X!$E$9) -> 0 | F10: =SUMIFS(Entradas[Valores],Entradas[Data da Competência],">="&F$7,Entradas[Data da Competência],"<"&EDATE(F$7,1),Entradas[Categoria],$B10,Entradas[Status],X!$E$7,Entradas[Conta Financeira],X!$E$8,Entradas[Centro de Custos],X!$E$9) -> 0 | G10: =SUMIFS(Entradas[Valores],Entradas[Data da Competência],">="&G$7,Entradas[Data da Competência],"<"&EDATE(G$7,1),Entradas[Categoria],$B10,Entradas[Status],X!$E$7,Entradas[Conta Financeira],X!$E$8,Entradas[Centro de Custos],X!$E$9) -> 0 | H10: =SUMIFS(Entradas[Valores],Entradas[Data da Competência],">="&H$7,Entradas[Data da Competência],"<"&EDATE(H$7,1),Entradas[Categoria],$B10,Entradas[Status],X!$E$7,Entradas[Conta Financeira],X!$E$8,Entradas[Centro de Custos],X!$E$9) -> 0 | I10: =SUMIFS(Entradas[Valores],Entradas[Data da Competência],">="&I$7,Entradas[Data da Competência],"<"&EDATE(I$7,1),Entradas[Categoria],$B10,Entradas[Status],X!$E$7,Entradas[Conta Financeira],X!$E$8,Entradas[Centro de Custos],X!$E$9) -> 0 | J10: =SUMIFS(Entradas[Valores],Entradas[Data da Competência],">="&J$7,Entradas[Data da Competência],"<"&EDATE(J$7,1),Entradas[Categoria],$B10,Entradas[Status],X!$E$7,Entradas[Conta Financeira],X!$E$8,Entradas[Centro de Custos],X!$E$9) -> 0 | ... N10: =SUMIFS(Entradas[Valores],Entradas[Data da Competência],">="&N$7,Entradas[Data da Competência],"<"&EDATE(N$7,1),Entradas[Categoria],$B10,Entradas[Status],X!$E$7,Entradas[Conta Financeira],X!$E$8,Entradas[Centro de Custos],X!$E$9) -> 5350 | O10: =SUM(C10:N10) -> 25250
B11: =X!V3 -> Outras Receitas Operacionais | C11: =SUMIFS(Entradas[Valores],Entradas[Data da Competência],">="&C$7,Entradas[Data da Competência],"<"&EDATE(C$7,1),Entradas[Categoria],$B11,Entradas[Status],X!$E$7,Entradas[Conta Financeira],X!$E$8,Entradas[Centro de Custos],X!$E$9) -> 0 | D11: =SUMIFS(Entradas[Valores],Entradas[Data da Competência],">="&D$7,Entradas[Data da Competência],"<"&EDATE(D$7,1),Entradas[Categoria],$B11,Entradas[Status],X!$E$7,Entradas[Conta Financeira],X!$E$8,Entradas[Centro de Custos],X!$E$9) -> 0 | E11: =SUMIFS(Entradas[Valores],Entradas[Data da Competência],">="&E$7,Entradas[Data da Competência],"<"&EDATE(E$7,1),Entradas[Categoria],$B11,Entradas[Status],X!$E$7,Entradas[Conta Financeira],X!$E$8,Entradas[Centro de Custos],X!$E$9) -> 0 | F11: =SUMIFS(Entradas[Valores],Entradas[Data da Competência],">="&F$7,Entradas[Data da Competência],"<"&EDATE(F$7,1),Entradas[Categoria],$B11,Entradas[Status],X!$E$7,Entradas[Conta Financeira],X!$E$8,Entradas[Centro de Custos],X!$E$9) -> 0 | G11: =SUMIFS(Entradas[Valores],Entradas[Data da Competência],">="&G$7,Entradas[Data da Competência],"<"&EDATE(G$7,1),Entradas[Categoria],$B11,Entradas[Status],X!$E$7,Entradas[Conta Financeira],X!$E$8,Entradas[Centro de Custos],X!$E$9) -> 0 | H11: =SUMIFS(Entradas[Valores],Entradas[Data da Competência],">="&H$7,Entradas[Data da Competência],"<"&EDATE(H$7,1),Entradas[Categoria],$B11,Entradas[Status],X!$E$7,Entradas[Conta Financeira],X!$E$8,Entradas[Centro de Custos],X!$E$9) -> 0 | I11: =SUMIFS(Entradas[Valores],Entradas[Data da Competência],">="&I$7,Entradas[Data da Competência],"<"&EDATE(I$7,1),Entradas[Categoria],$B11,Entradas[Status],X!$E$7,Entradas[Conta Financeira],X!$E$8,Entradas[Centro de Custos],X!$E$9) -> 0 | J11: =SUMIFS(Entradas[Valores],Entradas[Data da Competência],">="&J$7,Entradas[Data da Competência],"<"&EDATE(J$7,1),Entradas[Categoria],$B11,Entradas[Status],X!$E$7,Entradas[Conta Financeira],X!$E$8,Entradas[Centro de Custos],X!$E$9) -> 0 | ... N11: =SUMIFS(Entradas[Valores],Entradas[Data da Competência],">="&N$7,Entradas[Data da Competência],"<"&EDATE(N$7,1),Entradas[Categoria],$B11,Entradas[Status],X!$E$7,Entradas[Conta Financeira],X!$E$8,Entradas[Centro de Custos],X!$E$9) -> 0 | O11: =SUM(C11:N11) -> 0
B12: Receita Bruta | C12: =C10+C11 -> 0 | D12: =D10+D11 -> 0 | E12: =E10+E11 -> 0 | F12: =F10+F11 -> 0 | G12: =G10+G11 -> 0 | H12: =H10+H11 -> 0 | I12: =I10+I11 -> 0 | J12: =J10+J11 -> 0 | ... N12: =N10+N11 -> 5350 | O12: =SUM(C12:N12) -> 25250
B13: =X!V13 -> Impostos | C13: =SUMIFS(Saidas[Valores],Saidas[Data da Competência],">="&C$7,Saidas[Data da Competência],"<"&EDATE(C$7,1),Saidas[Categoria],$B13,Saidas[Status],X!$E$7,Saidas[Conta Financeira],X!$E$8,Saidas[Centro de Custos],X!$E$9) -> 0 | D13: =SUMIFS(Saidas[Valores],Saidas[Data da Competência],">="&D$7,Saidas[Data da Competência],"<"&EDATE(D$7,1),Saidas[Categoria],$B13,Saidas[Status],X!$E$7,Saidas[Conta Financeira],X!$E$8,Saidas[Centro de Custos],X!$E$9) -> 0 | E13: =SUMIFS(Saidas[Valores],Saidas[Data da Competência],">="&E$7,Saidas[Data da Competência],"<"&EDATE(E$7,1),Saidas[Categoria],$B13,Saidas[Status],X!$E$7,Saidas[Conta Financeira],X!$E$8,Saidas[Centro de Custos],X!$E$9) -> 0 | F13: =SUMIFS(Saidas[Valores],Saidas[Data da Competência],">="&F$7,Saidas[Data da Competência],"<"&EDATE(F$7,1),Saidas[Categoria],$B13,Saidas[Status],X!$E$7,Saidas[Conta Financeira],X!$E$8,Saidas[Centro de Custos],X!$E$9) -> 0 | G13: =SUMIFS(Saidas[Valores],Saidas[Data da Competência],">="&G$7,Saidas[Data da Competência],"<"&EDATE(G$7,1),Saidas[Categoria],$B13,Saidas[Status],X!$E$7,Saidas[Conta Financeira],X!$E$8,Saidas[Centro de Custos],X!$E$9) -> 0 | H13: =SUMIFS(Saidas[Valores],Saidas[Data da Competência],">="&H$7,Saidas[Data da Competência],"<"&EDATE(H$7,1),Saidas[Categoria],$B13,Saidas[Status],X!$E$7,Saidas[Conta Financeira],X!$E$8,Saidas[Centro de Custos],X!$E$9) -> 0 | I13: =SUMIFS(Saidas[Valores],Saidas[Data da Competência],">="&I$7,Saidas[Data da Competência],"<"&EDATE(I$7,1),Saidas[Categoria],$B13,Saidas[Status],X!$E$7,Saidas[Conta Financeira],X!$E$8,Saidas[Centro de Custos],X!$E$9) -> 0 | J13: =SUMIFS(Saidas[Valores],Saidas[Data da Competência],">="&J$7,Saidas[Data da Competência],"<"&EDATE(J$7,1),Saidas[Categoria],$B13,Saidas[Status],X!$E$7,Saidas[Conta Financeira],X!$E$8,Saidas[Centro de Custos],X!$E$9) -> 0 | ... N13: =SUMIFS(Saidas[Valores],Saidas[Data da Competência],">="&N$7,Saidas[Data da Competência],"<"&EDATE(N$7,1),Saidas[Categoria],$B13,Saidas[Status],X!$E$7,Saidas[Conta Financeira],X!$E$8,Saidas[Centro de Custos],X!$E$9) -> 0 | O13: =SUM(C13:N13) -> 650
B14: =X!V6 -> Deduções sobre vendas | C14: =SUMIFS(Saidas[Valores],Saidas[Data da Competência],">="&C$7,Saidas[Data da Competência],"<"&EDATE(C$7,1),Saidas[Categoria],$B14,Saidas[Status],X!$E$7,Saidas[Conta Financeira],X!$E$8,Saidas[Centro de Custos],X!$E$9) -> 0 | D14: =SUMIFS(Saidas[Valores],Saidas[Data da Competência],">="&D$7,Saidas[Data da Competência],"<"&EDATE(D$7,1),Saidas[Categoria],$B14,Saidas[Status],X!$E$7,Saidas[Conta Financeira],X!$E$8,Saidas[Centro de Custos],X!$E$9) -> 0 | E14: =SUMIFS(Saidas[Valores],Saidas[Data da Competência],">="&E$7,Saidas[Data da Competência],"<"&EDATE(E$7,1),Saidas[Categoria],$B14,Saidas[Status],X!$E$7,Saidas[Conta Financeira],X!$E$8,Saidas[Centro de Custos],X!$E$9) -> 0 | F14: =SUMIFS(Saidas[Valores],Saidas[Data da Competência],">="&F$7,Saidas[Data da Competência],"<"&EDATE(F$7,1),Saidas[Categoria],$B14,Saidas[Status],X!$E$7,Saidas[Conta Financeira],X!$E$8,Saidas[Centro de Custos],X!$E$9) -> 0 | G14: =SUMIFS(Saidas[Valores],Saidas[Data da Competência],">="&G$7,Saidas[Data da Competência],"<"&EDATE(G$7,1),Saidas[Categoria],$B14,Saidas[Status],X!$E$7,Saidas[Conta Financeira],X!$E$8,Saidas[Centro de Custos],X!$E$9) -> 0 | H14: =SUMIFS(Saidas[Valores],Saidas[Data da Competência],">="&H$7,Saidas[Data da Competência],"<"&EDATE(H$7,1),Saidas[Categoria],$B14,Saidas[Status],X!$E$7,Saidas[Conta Financeira],X!$E$8,Saidas[Centro de Custos],X!$E$9) -> 0 | I14: =SUMIFS(Saidas[Valores],Saidas[Data da Competência],">="&I$7,Saidas[Data da Competência],"<"&EDATE(I$7,1),Saidas[Categoria],$B14,Saidas[Status],X!$E$7,Saidas[Conta Financeira],X!$E$8,Saidas[Centro de Custos],X!$E$9) -> 0 | J14: =SUMIFS(Saidas[Valores],Saidas[Data da Competência],">="&J$7,Saidas[Data da Competência],"<"&EDATE(J$7,1),Saidas[Categoria],$B14,Saidas[Status],X!$E$7,Saidas[Conta Financeira],X!$E$8,Saidas[Centro de Custos],X!$E$9) -> 0 | ... N14: =SUMIFS(Saidas[Valores],Saidas[Data da Competência],">="&N$7,Saidas[Data da Competência],"<"&EDATE(N$7,1),Saidas[Categoria],$B14,Saidas[Status],X!$E$7,Saidas[Conta Financeira],X!$E$8,Saidas[Centro de Custos],X!$E$9) -> 0 | O14: =SUM(C14:N14) -> 925
B15: Receita Liquida | C15: =C12-C13-C14 -> 0 | D15: =D12-D13-D14 -> 0 | E15: =E12-E13-E14 -> 0 | F15: =F12-F13-F14 -> 0 | G15: =G12-G13-G14 -> 0 | H15: =H12-H13-H14 -> 0 | I15: =I12-I13-I14 -> 0 | J15: =J12-J13-J14 -> 0 | ... N15: =N12-N13-N14 -> 5350 | O15: =SUM(C15:N15) -> 23675
B16: =X!V7 -> Custo das Vendas | C16: =SUMIFS(Saidas[Valores],Saidas[Data da Competência],">="&C$7,Saidas[Data da Competência],"<"&EDATE(C$7,1),Saidas[Categoria],$B16,Saidas[Status],X!$E$7,Saidas[Conta Financeira],X!$E$8,Saidas[Centro de Custos],X!$E$9) -> 0 | D16: =SUMIFS(Saidas[Valores],Saidas[Data da Competência],">="&D$7,Saidas[Data da Competência],"<"&EDATE(D$7,1),Saidas[Categoria],$B16,Saidas[Status],X!$E$7,Saidas[Conta Financeira],X!$E$8,Saidas[Centro de Custos],X!$E$9) -> 0 | E16: =SUMIFS(Saidas[Valores],Saidas[Data da Competência],">="&E$7,Saidas[Data da Competência],"<"&EDATE(E$7,1),Saidas[Categoria],$B16,Saidas[Status],X!$E$7,Saidas[Conta Financeira],X!$E$8,Saidas[Centro de Custos],X!$E$9) -> 0 | F16: =SUMIFS(Saidas[Valores],Saidas[Data da Competência],">="&F$7,Saidas[Data da Competência],"<"&EDATE(F$7,1),Saidas[Categoria],$B16,Saidas[Status],X!$E$7,Saidas[Conta Financeira],X!$E$8,Saidas[Centro de Custos],X!$E$9) -> 0 | G16: =SUMIFS(Saidas[Valores],Saidas[Data da Competência],">="&G$7,Saidas[Data da Competência],"<"&EDATE(G$7,1),Saidas[Categoria],$B16,Saidas[Status],X!$E$7,Saidas[Conta Financeira],X!$E$8,Saidas[Centro de Custos],X!$E$9) -> 0 | H16: =SUMIFS(Saidas[Valores],Saidas[Data da Competência],">="&H$7,Saidas[Data da Competência],"<"&EDATE(H$7,1),Saidas[Categoria],$B16,Saidas[Status],X!$E$7,Saidas[Conta Financeira],X!$E$8,Saidas[Centro de Custos],X!$E$9) -> 0 | I16: =SUMIFS(Saidas[Valores],Saidas[Data da Competência],">="&I$7,Saidas[Data da Competência],"<"&EDATE(I$7,1),Saidas[Categoria],$B16,Saidas[Status],X!$E$7,Saidas[Conta Financeira],X!$E$8,Saidas[Centro de Custos],X!$E$9) -> 0 | J16: =SUMIFS(Saidas[Valores],Saidas[Data da Competência],">="&J$7,Saidas[Data da Competência],"<"&EDATE(J$7,1),Saidas[Categoria],$B16,Saidas[Status],X!$E$7,Saidas[Conta Financeira],X!$E$8,Saidas[Centro de Custos],X!$E$9) -> 0 | ... N16: =SUMIFS(Saidas[Valores],Saidas[Data da Competência],">="&N$7,Saidas[Data da Competência],"<"&EDATE(N$7,1),Saidas[Categoria],$B16,Saidas[Status],X!$E$7,Saidas[Conta Financeira],X!$E$8,Saidas[Centro de Custos],X!$E$9) -> 0 | O16: =SUM(C16:N16) -> 8823
B17: Resultado Operacional Bruto | C17: =C15-C16 -> 0 | D17: =D15-D16 -> 0 | E17: =E15-E16 -> 0 | F17: =F15-F16 -> 0 | G17: =G15-G16 -> 0 | H17: =H15-H16 -> 0 | I17: =I15-I16 -> 0 | J17: =J15-J16 -> 0 | ... N17: =N15-N16 -> 5350 | O17: =SUM(C17:N17) -> 14852
B18: =X!V8 -> Despesas administrativas | C18: =SUMIFS(Saidas[Valores],Saidas[Data da Competência],">="&C$7,Saidas[Data da Competência],"<"&EDATE(C$7,1),Saidas[Categoria],$B18,Saidas[Status],X!$E$7,Saidas[Conta Financeira],X!$E$8,Saidas[Centro de Custos],X!$E$9) -> 0 | D18: =SUMIFS(Saidas[Valores],Saidas[Data da Competência],">="&D$7,Saidas[Data da Competência],"<"&EDATE(D$7,1),Saidas[Categoria],$B18,Saidas[Status],X!$E$7,Saidas[Conta Financeira],X!$E$8,Saidas[Centro de Custos],X!$E$9) -> 0 | E18: =SUMIFS(Saidas[Valores],Saidas[Data da Competência],">="&E$7,Saidas[Data da Competência],"<"&EDATE(E$7,1),Saidas[Categoria],$B18,Saidas[Status],X!$E$7,Saidas[Conta Financeira],X!$E$8,Saidas[Centro de Custos],X!$E$9) -> 0 | F18: =SUMIFS(Saidas[Valores],Saidas[Data da Competência],">="&F$7,Saidas[Data da Competência],"<"&EDATE(F$7,1),Saidas[Categoria],$B18,Saidas[Status],X!$E$7,Saidas[Conta Financeira],X!$E$8,Saidas[Centro de Custos],X!$E$9) -> 0 | G18: =SUMIFS(Saidas[Valores],Saidas[Data da Competência],">="&G$7,Saidas[Data da Competência],"<"&EDATE(G$7,1),Saidas[Categoria],$B18,Saidas[Status],X!$E$7,Saidas[Conta Financeira],X!$E$8,Saidas[Centro de Custos],X!$E$9) -> 0 | H18: =SUMIFS(Saidas[Valores],Saidas[Data da Competência],">="&H$7,Saidas[Data da Competência],"<"&EDATE(H$7,1),Saidas[Categoria],$B18,Saidas[Status],X!$E$7,Saidas[Conta Financeira],X!$E$8,Saidas[Centro de Custos],X!$E$9) -> 0 | I18: =SUMIFS(Saidas[Valores],Saidas[Data da Competência],">="&I$7,Saidas[Data da Competência],"<"&EDATE(I$7,1),Saidas[Categoria],$B18,Saidas[Status],X!$E$7,Saidas[Conta Financeira],X!$E$8,Saidas[Centro de Custos],X!$E$9) -> 0 | J18: =SUMIFS(Saidas[Valores],Saidas[Data da Competência],">="&J$7,Saidas[Data da Competência],"<"&EDATE(J$7,1),Saidas[Categoria],$B18,Saidas[Status],X!$E$7,Saidas[Conta Financeira],X!$E$8,Saidas[Centro de Custos],X!$E$9) -> 0 | ... N18: =SUMIFS(Saidas[Valores],Saidas[Data da Competência],">="&N$7,Saidas[Data da Competência],"<"&EDATE(N$7,1),Saidas[Categoria],$B18,Saidas[Status],X!$E$7,Saidas[Conta Financeira],X!$E$8,Saidas[Centro de Custos],X!$E$9) -> 0 | O18: =SUM(C18:N18) -> 4270
B19: =X!V9 -> Despesa com Pessoal | C19: =SUMIFS(Saidas[Valores],Saidas[Data da Competência],">="&C$7,Saidas[Data da Competência],"<"&EDATE(C$7,1),Saidas[Categoria],$B19,Saidas[Status],X!$E$7,Saidas[Conta Financeira],X!$E$8,Saidas[Centro de Custos],X!$E$9) -> 0 | D19: =SUMIFS(Saidas[Valores],Saidas[Data da Competência],">="&D$7,Saidas[Data da Competência],"<"&EDATE(D$7,1),Saidas[Categoria],$B19,Saidas[Status],X!$E$7,Saidas[Conta Financeira],X!$E$8,Saidas[Centro de Custos],X!$E$9) -> 0 | E19: =SUMIFS(Saidas[Valores],Saidas[Data da Competência],">="&E$7,Saidas[Data da Competência],"<"&EDATE(E$7,1),Saidas[Categoria],$B19,Saidas[Status],X!$E$7,Saidas[Conta Financeira],X!$E$8,Saidas[Centro de Custos],X!$E$9) -> 0 | F19: =SUMIFS(Saidas[Valores],Saidas[Data da Competência],">="&F$7,Saidas[Data da Competência],"<"&EDATE(F$7,1),Saidas[Categoria],$B19,Saidas[Status],X!$E$7,Saidas[Conta Financeira],X!$E$8,Saidas[Centro de Custos],X!$E$9) -> 0 | G19: =SUMIFS(Saidas[Valores],Saidas[Data da Competência],">="&G$7,Saidas[Data da Competência],"<"&EDATE(G$7,1),Saidas[Categoria],$B19,Saidas[Status],X!$E$7,Saidas[Conta Financeira],X!$E$8,Saidas[Centro de Custos],X!$E$9) -> 0 | H19: =SUMIFS(Saidas[Valores],Saidas[Data da Competência],">="&H$7,Saidas[Data da Competência],"<"&EDATE(H$7,1),Saidas[Categoria],$B19,Saidas[Status],X!$E$7,Saidas[Conta Financeira],X!$E$8,Saidas[Centro de Custos],X!$E$9) -> 0 | I19: =SUMIFS(Saidas[Valores],Saidas[Data da Competência],">="&I$7,Saidas[Data da Competência],"<"&EDATE(I$7,1),Saidas[Categoria],$B19,Saidas[Status],X!$E$7,Saidas[Conta Financeira],X!$E$8,Saidas[Centro de Custos],X!$E$9) -> 0 | J19: =SUMIFS(Saidas[Valores],Saidas[Data da Competência],">="&J$7,Saidas[Data da Competência],"<"&EDATE(J$7,1),Saidas[Categoria],$B19,Saidas[Status],X!$E$7,Saidas[Conta Financeira],X!$E$8,Saidas[Centro de Custos],X!$E$9) -> 0 | ... N19: =SUMIFS(Saidas[Valores],Saidas[Data da Competência],">="&N$7,Saidas[Data da Competência],"<"&EDATE(N$7,1),Saidas[Categoria],$B19,Saidas[Status],X!$E$7,Saidas[Conta Financeira],X!$E$8,Saidas[Centro de Custos],X!$E$9) -> 0 | O19: =SUM(C19:N19) -> 7920
B20: =X!V10 -> Despesa Comercial | C20: =SUMIFS(Saidas[Valores],Saidas[Data da Competência],">="&C$7,Saidas[Data da Competência],"<"&EDATE(C$7,1),Saidas[Categoria],$B20,Saidas[Status],X!$E$7,Saidas[Conta Financeira],X!$E$8,Saidas[Centro de Custos],X!$E$9) -> 0 | D20: =SUMIFS(Saidas[Valores],Saidas[Data da Competência],">="&D$7,Saidas[Data da Competência],"<"&EDATE(D$7,1),Saidas[Categoria],$B20,Saidas[Status],X!$E$7,Saidas[Conta Financeira],X!$E$8,Saidas[Centro de Custos],X!$E$9) -> 0 | E20: =SUMIFS(Saidas[Valores],Saidas[Data da Competência],">="&E$7,Saidas[Data da Competência],"<"&EDATE(E$7,1),Saidas[Categoria],$B20,Saidas[Status],X!$E$7,Saidas[Conta Financeira],X!$E$8,Saidas[Centro de Custos],X!$E$9) -> 0 | F20: =SUMIFS(Saidas[Valores],Saidas[Data da Competência],">="&F$7,Saidas[Data da Competência],"<"&EDATE(F$7,1),Saidas[Categoria],$B20,Saidas[Status],X!$E$7,Saidas[Conta Financeira],X!$E$8,Saidas[Centro de Custos],X!$E$9) -> 0 | G20: =SUMIFS(Saidas[Valores],Saidas[Data da Competência],">="&G$7,Saidas[Data da Competência],"<"&EDATE(G$7,1),Saidas[Categoria],$B20,Saidas[Status],X!$E$7,Saidas[Conta Financeira],X!$E$8,Saidas[Centro de Custos],X!$E$9) -> 0 | H20: =SUMIFS(Saidas[Valores],Saidas[Data da Competência],">="&H$7,Saidas[Data da Competência],"<"&EDATE(H$7,1),Saidas[Categoria],$B20,Saidas[Status],X!$E$7,Saidas[Conta Financeira],X!$E$8,Saidas[Centro de Custos],X!$E$9) -> 0 | I20: =SUMIFS(Saidas[Valores],Saidas[Data da Competência],">="&I$7,Saidas[Data da Competência],"<"&EDATE(I$7,1),Saidas[Categoria],$B20,Saidas[Status],X!$E$7,Saidas[Conta Financeira],X!$E$8,Saidas[Centro de Custos],X!$E$9) -> 0 | J20: =SUMIFS(Saidas[Valores],Saidas[Data da Competência],">="&J$7,Saidas[Data da Competência],"<"&EDATE(J$7,1),Saidas[Categoria],$B20,Saidas[Status],X!$E$7,Saidas[Conta Financeira],X!$E$8,Saidas[Centro de Custos],X!$E$9) -> 0 | ... N20: =SUMIFS(Saidas[Valores],Saidas[Data da Competência],">="&N$7,Saidas[Data da Competência],"<"&EDATE(N$7,1),Saidas[Categoria],$B20,Saidas[Status],X!$E$7,Saidas[Conta Financeira],X!$E$8,Saidas[Centro de Custos],X!$E$9) -> 0 | O20: =SUM(C20:N20) -> 0
B21: Resultado Operacional Líquido | C21: =C17-C20-C18-C19 -> 0 | D21: =D17-D20-D18-D19 -> 0 | E21: =E17-E20-E18-E19 -> 0 | F21: =F17-F20-F18-F19 -> 0 | G21: =G17-G20-G18-G19 -> 0 | H21: =H17-H20-H18-H19 -> 0 | I21: =I17-I20-I18-I19 -> 0 | J21: =J17-J20-J18-J19 -> 0 | ... N21: =N17-N20-N18-N19 -> 5350 | O21: =SUM(C21:N21) -> 2662
B22: =X!V4 -> Receitas Financeiras | C22: =SUMIFS(Entradas[Valores],Entradas[Data da Competência],">="&C$7,Entradas[Data da Competência],"<"&EDATE(C$7,1),Entradas[Categoria],$B22,Entradas[Status],X!$E$7,Entradas[Conta Financeira],X!$E$8,Entradas[Centro de Custos],X!$E$9) -> 0 | D22: =SUMIFS(Entradas[Valores],Entradas[Data da Competência],">="&D$7,Entradas[Data da Competência],"<"&EDATE(D$7,1),Entradas[Categoria],$B22,Entradas[Status],X!$E$7,Entradas[Conta Financeira],X!$E$8,Entradas[Centro de Custos],X!$E$9) -> 0 | E22: =SUMIFS(Entradas[Valores],Entradas[Data da Competência],">="&E$7,Entradas[Data da Competência],"<"&EDATE(E$7,1),Entradas[Categoria],$B22,Entradas[Status],X!$E$7,Entradas[Conta Financeira],X!$E$8,Entradas[Centro de Custos],X!$E$9) -> 0 | F22: =SUMIFS(Entradas[Valores],Entradas[Data da Competência],">="&F$7,Entradas[Data da Competência],"<"&EDATE(F$7,1),Entradas[Categoria],$B22,Entradas[Status],X!$E$7,Entradas[Conta Financeira],X!$E$8,Entradas[Centro de Custos],X!$E$9) -> 0 | G22: =SUMIFS(Entradas[Valores],Entradas[Data da Competência],">="&G$7,Entradas[Data da Competência],"<"&EDATE(G$7,1),Entradas[Categoria],$B22,Entradas[Status],X!$E$7,Entradas[Conta Financeira],X!$E$8,Entradas[Centro de Custos],X!$E$9) -> 0 | H22: =SUMIFS(Entradas[Valores],Entradas[Data da Competência],">="&H$7,Entradas[Data da Competência],"<"&EDATE(H$7,1),Entradas[Categoria],$B22,Entradas[Status],X!$E$7,Entradas[Conta Financeira],X!$E$8,Entradas[Centro de Custos],X!$E$9) -> 0 | I22: =SUMIFS(Entradas[Valores],Entradas[Data da Competência],">="&I$7,Entradas[Data da Competência],"<"&EDATE(I$7,1),Entradas[Categoria],$B22,Entradas[Status],X!$E$7,Entradas[Conta Financeira],X!$E$8,Entradas[Centro de Custos],X!$E$9) -> 0 | J22: =SUMIFS(Entradas[Valores],Entradas[Data da Competência],">="&J$7,Entradas[Data da Competência],"<"&EDATE(J$7,1),Entradas[Categoria],$B22,Entradas[Status],X!$E$7,Entradas[Conta Financeira],X!$E$8,Entradas[Centro de Custos],X!$E$9) -> 0 | ... N22: =SUMIFS(Entradas[Valores],Entradas[Data da Competência],">="&N$7,Entradas[Data da Competência],"<"&EDATE(N$7,1),Entradas[Categoria],$B22,Entradas[Status],X!$E$7,Entradas[Conta Financeira],X!$E$8,Entradas[Centro de Custos],X!$E$9) -> 0 | O22: =SUM(C22:N22) -> 0
B23: =X!V11 -> Despesa Financeira | C23: =SUMIFS(Saidas[Valores],Saidas[Data da Competência],">="&C$7,Saidas[Data da Competência],"<"&EDATE(C$7,1),Saidas[Categoria],$B23,Saidas[Status],X!$E$7,Saidas[Conta Financeira],X!$E$8,Saidas[Centro de Custos],X!$E$9) -> 0 | D23: =SUMIFS(Saidas[Valores],Saidas[Data da Competência],">="&D$7,Saidas[Data da Competência],"<"&EDATE(D$7,1),Saidas[Categoria],$B23,Saidas[Status],X!$E$7,Saidas[Conta Financeira],X!$E$8,Saidas[Centro de Custos],X!$E$9) -> 0 | E23: =SUMIFS(Saidas[Valores],Saidas[Data da Competência],">="&E$7,Saidas[Data da Competência],"<"&EDATE(E$7,1),Saidas[Categoria],$B23,Saidas[Status],X!$E$7,Saidas[Conta Financeira],X!$E$8,Saidas[Centro de Custos],X!$E$9) -> 0 | F23: =SUMIFS(Saidas[Valores],Saidas[Data da Competência],">="&F$7,Saidas[Data da Competência],"<"&EDATE(F$7,1),Saidas[Categoria],$B23,Saidas[Status],X!$E$7,Saidas[Conta Financeira],X!$E$8,Saidas[Centro de Custos],X!$E$9) -> 0 | G23: =SUMIFS(Saidas[Valores],Saidas[Data da Competência],">="&G$7,Saidas[Data da Competência],"<"&EDATE(G$7,1),Saidas[Categoria],$B23,Saidas[Status],X!$E$7,Saidas[Conta Financeira],X!$E$8,Saidas[Centro de Custos],X!$E$9) -> 0 | H23: =SUMIFS(Saidas[Valores],Saidas[Data da Competência],">="&H$7,Saidas[Data da Competência],"<"&EDATE(H$7,1),Saidas[Categoria],$B23,Saidas[Status],X!$E$7,Saidas[Conta Financeira],X!$E$8,Saidas[Centro de Custos],X!$E$9) -> 0 | I23: =SUMIFS(Saidas[Valores],Saidas[Data da Competência],">="&I$7,Saidas[Data da Competência],"<"&EDATE(I$7,1),Saidas[Categoria],$B23,Saidas[Status],X!$E$7,Saidas[Conta Financeira],X!$E$8,Saidas[Centro de Custos],X!$E$9) -> 0 | J23: =SUMIFS(Saidas[Valores],Saidas[Data da Competência],">="&J$7,Saidas[Data da Competência],"<"&EDATE(J$7,1),Saidas[Categoria],$B23,Saidas[Status],X!$E$7,Saidas[Conta Financeira],X!$E$8,Saidas[Centro de Custos],X!$E$9) -> 0 | ... N23: =SUMIFS(Saidas[Valores],Saidas[Data da Competência],">="&N$7,Saidas[Data da Competência],"<"&EDATE(N$7,1),Saidas[Categoria],$B23,Saidas[Status],X!$E$7,Saidas[Conta Financeira],X!$E$8,Saidas[Centro de Custos],X!$E$9) -> 0 | O23: =SUM(C23:N23) -> 0
B24: =X!V5 -> Receitas não operacionais | C24: =SUMIFS(Entradas[Valores],Entradas[Data da Competência],">="&C$7,Entradas[Data da Competência],"<"&EDATE(C$7,1),Entradas[Categoria],$B24,Entradas[Status],X!$E$7,Entradas[Conta Financeira],X!$E$8,Entradas[Centro de Custos],X!$E$9) -> 0 | D24: =SUMIFS(Entradas[Valores],Entradas[Data da Competência],">="&D$7,Entradas[Data da Competência],"<"&EDATE(D$7,1),Entradas[Categoria],$B24,Entradas[Status],X!$E$7,Entradas[Conta Financeira],X!$E$8,Entradas[Centro de Custos],X!$E$9) -> 0 | E24: =SUMIFS(Entradas[Valores],Entradas[Data da Competência],">="&E$7,Entradas[Data da Competência],"<"&EDATE(E$7,1),Entradas[Categoria],$B24,Entradas[Status],X!$E$7,Entradas[Conta Financeira],X!$E$8,Entradas[Centro de Custos],X!$E$9) -> 0 | F24: =SUMIFS(Entradas[Valores],Entradas[Data da Competência],">="&F$7,Entradas[Data da Competência],"<"&EDATE(F$7,1),Entradas[Categoria],$B24,Entradas[Status],X!$E$7,Entradas[Conta Financeira],X!$E$8,Entradas[Centro de Custos],X!$E$9) -> 0 | G24: =SUMIFS(Entradas[Valores],Entradas[Data da Competência],">="&G$7,Entradas[Data da Competência],"<"&EDATE(G$7,1),Entradas[Categoria],$B24,Entradas[Status],X!$E$7,Entradas[Conta Financeira],X!$E$8,Entradas[Centro de Custos],X!$E$9) -> 0 | H24: =SUMIFS(Entradas[Valores],Entradas[Data da Competência],">="&H$7,Entradas[Data da Competência],"<"&EDATE(H$7,1),Entradas[Categoria],$B24,Entradas[Status],X!$E$7,Entradas[Conta Financeira],X!$E$8,Entradas[Centro de Custos],X!$E$9) -> 0 | I24: =SUMIFS(Entradas[Valores],Entradas[Data da Competência],">="&I$7,Entradas[Data da Competência],"<"&EDATE(I$7,1),Entradas[Categoria],$B24,Entradas[Status],X!$E$7,Entradas[Conta Financeira],X!$E$8,Entradas[Centro de Custos],X!$E$9) -> 0 | J24: =SUMIFS(Entradas[Valores],Entradas[Data da Competência],">="&J$7,Entradas[Data da Competência],"<"&EDATE(J$7,1),Entradas[Categoria],$B24,Entradas[Status],X!$E$7,Entradas[Conta Financeira],X!$E$8,Entradas[Centro de Custos],X!$E$9) -> 0 | ... N24: =SUMIFS(Entradas[Valores],Entradas[Data da Competência],">="&N$7,Entradas[Data da Competência],"<"&EDATE(N$7,1),Entradas[Categoria],$B24,Entradas[Status],X!$E$7,Entradas[Conta Financeira],X!$E$8,Entradas[Centro de Custos],X!$E$9) -> 0 | O24: =SUM(C24:N24) -> 10500
B25: =X!V12 -> Despesas não operacionais | C25: =SUMIFS(Saidas[Valores],Saidas[Data da Competência],">="&C$7,Saidas[Data da Competência],"<"&EDATE(C$7,1),Saidas[Categoria],$B25,Saidas[Status],X!$E$7,Saidas[Conta Financeira],X!$E$8,Saidas[Centro de Custos],X!$E$9) -> 0 | D25: =SUMIFS(Saidas[Valores],Saidas[Data da Competência],">="&D$7,Saidas[Data da Competência],"<"&EDATE(D$7,1),Saidas[Categoria],$B25,Saidas[Status],X!$E$7,Saidas[Conta Financeira],X!$E$8,Saidas[Centro de Custos],X!$E$9) -> 0 | E25: =SUMIFS(Saidas[Valores],Saidas[Data da Competência],">="&E$7,Saidas[Data da Competência],"<"&EDATE(E$7,1),Saidas[Categoria],$B25,Saidas[Status],X!$E$7,Saidas[Conta Financeira],X!$E$8,Saidas[Centro de Custos],X!$E$9) -> 0 | F25: =SUMIFS(Saidas[Valores],Saidas[Data da Competência],">="&F$7,Saidas[Data da Competência],"<"&EDATE(F$7,1),Saidas[Categoria],$B25,Saidas[Status],X!$E$7,Saidas[Conta Financeira],X!$E$8,Saidas[Centro de Custos],X!$E$9) -> 0 | G25: =SUMIFS(Saidas[Valores],Saidas[Data da Competência],">="&G$7,Saidas[Data da Competência],"<"&EDATE(G$7,1),Saidas[Categoria],$B25,Saidas[Status],X!$E$7,Saidas[Conta Financeira],X!$E$8,Saidas[Centro de Custos],X!$E$9) -> 0 | H25: =SUMIFS(Saidas[Valores],Saidas[Data da Competência],">="&H$7,Saidas[Data da Competência],"<"&EDATE(H$7,1),Saidas[Categoria],$B25,Saidas[Status],X!$E$7,Saidas[Conta Financeira],X!$E$8,Saidas[Centro de Custos],X!$E$9) -> 0 | I25: =SUMIFS(Saidas[Valores],Saidas[Data da Competência],">="&I$7,Saidas[Data da Competência],"<"&EDATE(I$7,1),Saidas[Categoria],$B25,Saidas[Status],X!$E$7,Saidas[Conta Financeira],X!$E$8,Saidas[Centro de Custos],X!$E$9) -> 0 | J25: =SUMIFS(Saidas[Valores],Saidas[Data da Competência],">="&J$7,Saidas[Data da Competência],"<"&EDATE(J$7,1),Saidas[Categoria],$B25,Saidas[Status],X!$E$7,Saidas[Conta Financeira],X!$E$8,Saidas[Centro de Custos],X!$E$9) -> 0 | ... N25: =SUMIFS(Saidas[Valores],Saidas[Data da Competência],">="&N$7,Saidas[Data da Competência],"<"&EDATE(N$7,1),Saidas[Categoria],$B25,Saidas[Status],X!$E$7,Saidas[Conta Financeira],X!$E$8,Saidas[Centro de Custos],X!$E$9) -> 0 | O25: =SUM(C25:N25) -> 35000
B26: Resultado Liquido | C26: =C21+C22-C23+C24-C25 -> 0 | D26: =D21+D22-D23+D24-D25 -> 0 | E26: =E21+E22-E23+E24-E25 -> 0 | F26: =F21+F22-F23+F24-F25 -> 0 | G26: =G21+G22-G23+G24-G25 -> 0 | H26: =H21+H22-H23+H24-H25 -> 0 | I26: =I21+I22-I23+I24-I25 -> 0 | J26: =J21+J22-J23+J24-J25 -> 0 | ... N26: =N21+N22-N23+N24-N25 -> 5350 | O26: =SUM(C26:N26) -> -21838
B27: =X!V14 -> Participação e Dividendos | C27: =SUMIFS(Saidas[Valores],Saidas[Data da Competência],">="&C$7,Saidas[Data da Competência],"<"&EDATE(C$7,1),Saidas[Categoria],$B27,Saidas[Status],X!$E$7,Saidas[Conta Financeira],X!$E$8,Saidas[Centro de Custos],X!$E$9) -> 0 | D27: =SUMIFS(Saidas[Valores],Saidas[Data da Competência],">="&D$7,Saidas[Data da Competência],"<"&EDATE(D$7,1),Saidas[Categoria],$B27,Saidas[Status],X!$E$7,Saidas[Conta Financeira],X!$E$8,Saidas[Centro de Custos],X!$E$9) -> 0 | E27: =SUMIFS(Saidas[Valores],Saidas[Data da Competência],">="&E$7,Saidas[Data da Competência],"<"&EDATE(E$7,1),Saidas[Categoria],$B27,Saidas[Status],X!$E$7,Saidas[Conta Financeira],X!$E$8,Saidas[Centro de Custos],X!$E$9) -> 0 | F27: =SUMIFS(Saidas[Valores],Saidas[Data da Competência],">="&F$7,Saidas[Data da Competência],"<"&EDATE(F$7,1),Saidas[Categoria],$B27,Saidas[Status],X!$E$7,Saidas[Conta Financeira],X!$E$8,Saidas[Centro de Custos],X!$E$9) -> 0 | G27: =SUMIFS(Saidas[Valores],Saidas[Data da Competência],">="&G$7,Saidas[Data da Competência],"<"&EDATE(G$7,1),Saidas[Categoria],$B27,Saidas[Status],X!$E$7,Saidas[Conta Financeira],X!$E$8,Saidas[Centro de Custos],X!$E$9) -> 0 | H27: =SUMIFS(Saidas[Valores],Saidas[Data da Competência],">="&H$7,Saidas[Data da Competência],"<"&EDATE(H$7,1),Saidas[Categoria],$B27,Saidas[Status],X!$E$7,Saidas[Conta Financeira],X!$E$8,Saidas[Centro de Custos],X!$E$9) -> 0 | I27: =SUMIFS(Saidas[Valores],Saidas[Data da Competência],">="&I$7,Saidas[Data da Competência],"<"&EDATE(I$7,1),Saidas[Categoria],$B27,Saidas[Status],X!$E$7,Saidas[Conta Financeira],X!$E$8,Saidas[Centro de Custos],X!$E$9) -> 0 | J27: =SUMIFS(Saidas[Valores],Saidas[Data da Competência],">="&J$7,Saidas[Data da Competência],"<"&EDATE(J$7,1),Saidas[Categoria],$B27,Saidas[Status],X!$E$7,Saidas[Conta Financeira],X!$E$8,Saidas[Centro de Custos],X!$E$9) -> 0 | ... N27: =SUMIFS(Saidas[Valores],Saidas[Data da Competência],">="&N$7,Saidas[Data da Competência],"<"&EDATE(N$7,1),Saidas[Categoria],$B27,Saidas[Status],X!$E$7,Saidas[Conta Financeira],X!$E$8,Saidas[Centro de Custos],X!$E$9) -> 0 | O27: =SUM(C27:N27) -> 0
B28: Resultado Líquido do Exercício | C28: =C26-C27 -> 0 | D28: =D26-D27 -> 0 | E28: =E26-E27 -> 0 | F28: =F26-F27 -> 0 | G28: =G26-G27 -> 0 | H28: =H26-H27 -> 0 | I28: =I26-I27 -> 0 | J28: =J26-J27 -> 0 | ... N28: =N26-N27 -> 5350 | O28: =SUM(C28:N28) -> -21838
B31: Despesas não operacionais
B32: TOTAL | C32: =SUM(C33:C500) -> 0 | D32: =SUM(D33:D500) -> 0 | E32: =SUM(E33:E500) -> 0 | F32: =SUM(F33:F500) -> 0 | G32: =SUM(G33:G500) -> 0 | H32: =SUM(H33:H500) -> 0 | I32: =SUM(I33:I500) -> 0 | J32: =SUM(J33:J500) -> 0 | ... O32: =SUM(O33:O500) -> 35000
B33: =IFERROR(__xludf.DUMMYFUNCTION("IF($B$31="""","""", FILTER( INDEX('Plano de Contas'!$A$5:$Z$200,, MATCH($B$31,'Plano de Contas'!$A$4:$Z$4,0)), INDEX('Plano de Contas'!$A$5:$Z$200,, MATCH($B$31,'Plano de Contas'!$A$4:$Z$4,0))<>"""" ) )"),"Financiamento") -> Financiamento | C33: =SUMIFS(Saidas[Valores],Saidas[Data da Competência],">="&C$7,Saidas[Data da Competência],"<"&EDATE(C$7,1),Saidas[Classificação],$B33,Saidas[Status],X!$E$7,Saidas[Conta Financeira],X!$E$8,Saidas[Centro de Custos],X!$E$9) -> 0 | D33: =SUMIFS(Saidas[Valores],Saidas[Data da Competência],">="&D$7,Saidas[Data da Competência],"<"&EDATE(D$7,1),Saidas[Classificação],$B33,Saidas[Status],X!$E$7,Saidas[Conta Financeira],X!$E$8,Saidas[Centro de Custos],X!$E$9) -> 0 | E33: =SUMIFS(Saidas[Valores],Saidas[Data da Competência],">="&E$7,Saidas[Data da Competência],"<"&EDATE(E$7,1),Saidas[Classificação],$B33,Saidas[Status],X!$E$7,Saidas[Conta Financeira],X!$E$8,Saidas[Centro de Custos],X!$E$9) -> 0 | F33: =SUMIFS(Saidas[Valores],Saidas[Data da Competência],">="&F$7,Saidas[Data da Competência],"<"&EDATE(F$7,1),Saidas[Classificação],$B33,Saidas[Status],X!$E$7,Saidas[Conta Financeira],X!$E$8,Saidas[Centro de Custos],X!$E$9) -> 0 | G33: =SUMIFS(Saidas[Valores],Saidas[Data da Competência],">="&G$7,Saidas[Data da Competência],"<"&EDATE(G$7,1),Saidas[Classificação],$B33,Saidas[Status],X!$E$7,Saidas[Conta Financeira],X!$E$8,Saidas[Centro de Custos],X!$E$9) -> 0 | H33: =SUMIFS(Saidas[Valores],Saidas[Data da Competência],">="&H$7,Saidas[Data da Competência],"<"&EDATE(H$7,1),Saidas[Classificação],$B33,Saidas[Status],X!$E$7,Saidas[Conta Financeira],X!$E$8,Saidas[Centro de Custos],X!$E$9) -> 0 | I33: =SUMIFS(Saidas[Valores],Saidas[Data da Competência],">="&I$7,Saidas[Data da Competência],"<"&EDATE(I$7,1),Saidas[Classificação],$B33,Saidas[Status],X!$E$7,Saidas[Conta Financeira],X!$E$8,Saidas[Centro de Custos],X!$E$9) -> 0 | J33: =SUMIFS(Saidas[Valores],Saidas[Data da Competência],">="&J$7,Saidas[Data da Competência],"<"&EDATE(J$7,1),Saidas[Classificação],$B33,Saidas[Status],X!$E$7,Saidas[Conta Financeira],X!$E$8,Saidas[Centro de Custos],X!$E$9) -> 0 | ... N33: =SUMIFS(Saidas[Valores],Saidas[Data da Competência],">="&N$7,Saidas[Data da Competência],"<"&EDATE(N$7,1),Saidas[Classificação],$B33,Saidas[Status],X!$E$7,Saidas[Conta Financeira],X!$E$8,Saidas[Centro de Custos],X!$E$9) -> 0 | O33: =SUM(C33:N33) -> 0
B34: =IFERROR(__xludf.DUMMYFUNCTION("""COMPUTED_VALUE"""),"Gastos Não Identificados") -> Gastos Não Identificados | C34: =SUMIFS(Saidas[Valores],Saidas[Data da Competência],">="&C$7,Saidas[Data da Competência],"<"&EDATE(C$7,1),Saidas[Classificação],$B34,Saidas[Status],X!$E$7,Saidas[Conta Financeira],X!$E$8,Saidas[Centro de Custos],X!$E$9) -> 0 | D34: =SUMIFS(Saidas[Valores],Saidas[Data da Competência],">="&D$7,Saidas[Data da Competência],"<"&EDATE(D$7,1),Saidas[Classificação],$B34,Saidas[Status],X!$E$7,Saidas[Conta Financeira],X!$E$8,Saidas[Centro de Custos],X!$E$9) -> 0 | E34: =SUMIFS(Saidas[Valores],Saidas[Data da Competência],">="&E$7,Saidas[Data da Competência],"<"&EDATE(E$7,1),Saidas[Classificação],$B34,Saidas[Status],X!$E$7,Saidas[Conta Financeira],X!$E$8,Saidas[Centro de Custos],X!$E$9) -> 0 | F34: =SUMIFS(Saidas[Valores],Saidas[Data da Competência],">="&F$7,Saidas[Data da Competência],"<"&EDATE(F$7,1),Saidas[Classificação],$B34,Saidas[Status],X!$E$7,Saidas[Conta Financeira],X!$E$8,Saidas[Centro de Custos],X!$E$9) -> 0 | G34: =SUMIFS(Saidas[Valores],Saidas[Data da Competência],">="&G$7,Saidas[Data da Competência],"<"&EDATE(G$7,1),Saidas[Classificação],$B34,Saidas[Status],X!$E$7,Saidas[Conta Financeira],X!$E$8,Saidas[Centro de Custos],X!$E$9) -> 0 | H34: =SUMIFS(Saidas[Valores],Saidas[Data da Competência],">="&H$7,Saidas[Data da Competência],"<"&EDATE(H$7,1),Saidas[Classificação],$B34,Saidas[Status],X!$E$7,Saidas[Conta Financeira],X!$E$8,Saidas[Centro de Custos],X!$E$9) -> 0 | I34: =SUMIFS(Saidas[Valores],Saidas[Data da Competência],">="&I$7,Saidas[Data da Competência],"<"&EDATE(I$7,1),Saidas[Classificação],$B34,Saidas[Status],X!$E$7,Saidas[Conta Financeira],X!$E$8,Saidas[Centro de Custos],X!$E$9) -> 0 | J34: =SUMIFS(Saidas[Valores],Saidas[Data da Competência],">="&J$7,Saidas[Data da Competência],"<"&EDATE(J$7,1),Saidas[Classificação],$B34,Saidas[Status],X!$E$7,Saidas[Conta Financeira],X!$E$8,Saidas[Centro de Custos],X!$E$9) -> 0 | ... N34: =SUMIFS(Saidas[Valores],Saidas[Data da Competência],">="&N$7,Saidas[Data da Competência],"<"&EDATE(N$7,1),Saidas[Classificação],$B34,Saidas[Status],X!$E$7,Saidas[Conta Financeira],X!$E$8,Saidas[Centro de Custos],X!$E$9) -> 0 | O34: =SUM(C34:N34) -> 0
B35: =IFERROR(__xludf.DUMMYFUNCTION("""COMPUTED_VALUE"""),"Investimento em Patrimonio") -> Investimento em Patrimonio | C35: =SUMIFS(Saidas[Valores],Saidas[Data da Competência],">="&C$7,Saidas[Data da Competência],"<"&EDATE(C$7,1),Saidas[Classificação],$B35,Saidas[Status],X!$E$7,Saidas[Conta Financeira],X!$E$8,Saidas[Centro de Custos],X!$E$9) -> 0 | D35: =SUMIFS(Saidas[Valores],Saidas[Data da Competência],">="&D$7,Saidas[Data da Competência],"<"&EDATE(D$7,1),Saidas[Classificação],$B35,Saidas[Status],X!$E$7,Saidas[Conta Financeira],X!$E$8,Saidas[Centro de Custos],X!$E$9) -> 0 | E35: =SUMIFS(Saidas[Valores],Saidas[Data da Competência],">="&E$7,Saidas[Data da Competência],"<"&EDATE(E$7,1),Saidas[Classificação],$B35,Saidas[Status],X!$E$7,Saidas[Conta Financeira],X!$E$8,Saidas[Centro de Custos],X!$E$9) -> 0 | F35: =SUMIFS(Saidas[Valores],Saidas[Data da Competência],">="&F$7,Saidas[Data da Competência],"<"&EDATE(F$7,1),Saidas[Classificação],$B35,Saidas[Status],X!$E$7,Saidas[Conta Financeira],X!$E$8,Saidas[Centro de Custos],X!$E$9) -> 0 | G35: =SUMIFS(Saidas[Valores],Saidas[Data da Competência],">="&G$7,Saidas[Data da Competência],"<"&EDATE(G$7,1),Saidas[Classificação],$B35,Saidas[Status],X!$E$7,Saidas[Conta Financeira],X!$E$8,Saidas[Centro de Custos],X!$E$9) -> 0 | H35: =SUMIFS(Saidas[Valores],Saidas[Data da Competência],">="&H$7,Saidas[Data da Competência],"<"&EDATE(H$7,1),Saidas[Classificação],$B35,Saidas[Status],X!$E$7,Saidas[Conta Financeira],X!$E$8,Saidas[Centro de Custos],X!$E$9) -> 0 | I35: =SUMIFS(Saidas[Valores],Saidas[Data da Competência],">="&I$7,Saidas[Data da Competência],"<"&EDATE(I$7,1),Saidas[Classificação],$B35,Saidas[Status],X!$E$7,Saidas[Conta Financeira],X!$E$8,Saidas[Centro de Custos],X!$E$9) -> 0 | J35: =SUMIFS(Saidas[Valores],Saidas[Data da Competência],">="&J$7,Saidas[Data da Competência],"<"&EDATE(J$7,1),Saidas[Classificação],$B35,Saidas[Status],X!$E$7,Saidas[Conta Financeira],X!$E$8,Saidas[Centro de Custos],X!$E$9) -> 0 | ... N35: =SUMIFS(Saidas[Valores],Saidas[Data da Competência],">="&N$7,Saidas[Data da Competência],"<"&EDATE(N$7,1),Saidas[Classificação],$B35,Saidas[Status],X!$E$7,Saidas[Conta Financeira],X!$E$8,Saidas[Centro de Custos],X!$E$9) -> 0 | O35: =SUM(C35:N35) -> 35000
B36: =IFERROR(__xludf.DUMMYFUNCTION("""COMPUTED_VALUE"""),"Combustível") -> Combustível | C36: =SUMIFS(Saidas[Valores],Saidas[Data da Competência],">="&C$7,Saidas[Data da Competência],"<"&EDATE(C$7,1),Saidas[Classificação],$B36,Saidas[Status],X!$E$7,Saidas[Conta Financeira],X!$E$8,Saidas[Centro de Custos],X!$E$9) -> 0 | D36: =SUMIFS(Saidas[Valores],Saidas[Data da Competência],">="&D$7,Saidas[Data da Competência],"<"&EDATE(D$7,1),Saidas[Classificação],$B36,Saidas[Status],X!$E$7,Saidas[Conta Financeira],X!$E$8,Saidas[Centro de Custos],X!$E$9) -> 0 | E36: =SUMIFS(Saidas[Valores],Saidas[Data da Competência],">="&E$7,Saidas[Data da Competência],"<"&EDATE(E$7,1),Saidas[Classificação],$B36,Saidas[Status],X!$E$7,Saidas[Conta Financeira],X!$E$8,Saidas[Centro de Custos],X!$E$9) -> 0 | F36: =SUMIFS(Saidas[Valores],Saidas[Data da Competência],">="&F$7,Saidas[Data da Competência],"<"&EDATE(F$7,1),Saidas[Classificação],$B36,Saidas[Status],X!$E$7,Saidas[Conta Financeira],X!$E$8,Saidas[Centro de Custos],X!$E$9) -> 0 | G36: =SUMIFS(Saidas[Valores],Saidas[Data da Competência],">="&G$7,Saidas[Data da Competência],"<"&EDATE(G$7,1),Saidas[Classificação],$B36,Saidas[Status],X!$E$7,Saidas[Conta Financeira],X!$E$8,Saidas[Centro de Custos],X!$E$9) -> 0 | H36: =SUMIFS(Saidas[Valores],Saidas[Data da Competência],">="&H$7,Saidas[Data da Competência],"<"&EDATE(H$7,1),Saidas[Classificação],$B36,Saidas[Status],X!$E$7,Saidas[Conta Financeira],X!$E$8,Saidas[Centro de Custos],X!$E$9) -> 0 | I36: =SUMIFS(Saidas[Valores],Saidas[Data da Competência],">="&I$7,Saidas[Data da Competência],"<"&EDATE(I$7,1),Saidas[Classificação],$B36,Saidas[Status],X!$E$7,Saidas[Conta Financeira],X!$E$8,Saidas[Centro de Custos],X!$E$9) -> 0 | J36: =SUMIFS(Saidas[Valores],Saidas[Data da Competência],">="&J$7,Saidas[Data da Competência],"<"&EDATE(J$7,1),Saidas[Classificação],$B36,Saidas[Status],X!$E$7,Saidas[Conta Financeira],X!$E$8,Saidas[Centro de Custos],X!$E$9) -> 0 | ... N36: =SUMIFS(Saidas[Valores],Saidas[Data da Competência],">="&N$7,Saidas[Data da Competência],"<"&EDATE(N$7,1),Saidas[Classificação],$B36,Saidas[Status],X!$E$7,Saidas[Conta Financeira],X!$E$8,Saidas[Centro de Custos],X!$E$9) -> 0 | O36: =SUM(C36:N36) -> 0
B37: =IFERROR(__xludf.DUMMYFUNCTION("""COMPUTED_VALUE"""),"Doblô") -> Doblô | C37: =SUMIFS(Saidas[Valores],Saidas[Data da Competência],">="&C$7,Saidas[Data da Competência],"<"&EDATE(C$7,1),Saidas[Classificação],$B37,Saidas[Status],X!$E$7,Saidas[Conta Financeira],X!$E$8,Saidas[Centro de Custos],X!$E$9) -> 0 | D37: =SUMIFS(Saidas[Valores],Saidas[Data da Competência],">="&D$7,Saidas[Data da Competência],"<"&EDATE(D$7,1),Saidas[Classificação],$B37,Saidas[Status],X!$E$7,Saidas[Conta Financeira],X!$E$8,Saidas[Centro de Custos],X!$E$9) -> 0 | E37: =SUMIFS(Saidas[Valores],Saidas[Data da Competência],">="&E$7,Saidas[Data da Competência],"<"&EDATE(E$7,1),Saidas[Classificação],$B37,Saidas[Status],X!$E$7,Saidas[Conta Financeira],X!$E$8,Saidas[Centro de Custos],X!$E$9) -> 0 | F37: =SUMIFS(Saidas[Valores],Saidas[Data da Competência],">="&F$7,Saidas[Data da Competência],"<"&EDATE(F$7,1),Saidas[Classificação],$B37,Saidas[Status],X!$E$7,Saidas[Conta Financeira],X!$E$8,Saidas[Centro de Custos],X!$E$9) -> 0 | G37: =SUMIFS(Saidas[Valores],Saidas[Data da Competência],">="&G$7,Saidas[Data da Competência],"<"&EDATE(G$7,1),Saidas[Classificação],$B37,Saidas[Status],X!$E$7,Saidas[Conta Financeira],X!$E$8,Saidas[Centro de Custos],X!$E$9) -> 0 | H37: =SUMIFS(Saidas[Valores],Saidas[Data da Competência],">="&H$7,Saidas[Data da Competência],"<"&EDATE(H$7,1),Saidas[Classificação],$B37,Saidas[Status],X!$E$7,Saidas[Conta Financeira],X!$E$8,Saidas[Centro de Custos],X!$E$9) -> 0 | I37: =SUMIFS(Saidas[Valores],Saidas[Data da Competência],">="&I$7,Saidas[Data da Competência],"<"&EDATE(I$7,1),Saidas[Classificação],$B37,Saidas[Status],X!$E$7,Saidas[Conta Financeira],X!$E$8,Saidas[Centro de Custos],X!$E$9) -> 0 | J37: =SUMIFS(Saidas[Valores],Saidas[Data da Competência],">="&J$7,Saidas[Data da Competência],"<"&EDATE(J$7,1),Saidas[Classificação],$B37,Saidas[Status],X!$E$7,Saidas[Conta Financeira],X!$E$8,Saidas[Centro de Custos],X!$E$9) -> 0 | ... N37: =SUMIFS(Saidas[Valores],Saidas[Data da Competência],">="&N$7,Saidas[Data da Competência],"<"&EDATE(N$7,1),Saidas[Classificação],$B37,Saidas[Status],X!$E$7,Saidas[Conta Financeira],X!$E$8,Saidas[Centro de Custos],X!$E$9) -> 0 | O37: =SUM(C37:N37) -> 0
B38: =IFERROR(__xludf.DUMMYFUNCTION("""COMPUTED_VALUE"""),"Obras e Manutenção") -> Obras e Manutenção | C38: =SUMIFS(Saidas[Valores],Saidas[Data da Competência],">="&C$7,Saidas[Data da Competência],"<"&EDATE(C$7,1),Saidas[Classificação],$B38,Saidas[Status],X!$E$7,Saidas[Conta Financeira],X!$E$8,Saidas[Centro de Custos],X!$E$9) -> 0 | D38: =SUMIFS(Saidas[Valores],Saidas[Data da Competência],">="&D$7,Saidas[Data da Competência],"<"&EDATE(D$7,1),Saidas[Classificação],$B38,Saidas[Status],X!$E$7,Saidas[Conta Financeira],X!$E$8,Saidas[Centro de Custos],X!$E$9) -> 0 | E38: =SUMIFS(Saidas[Valores],Saidas[Data da Competência],">="&E$7,Saidas[Data da Competência],"<"&EDATE(E$7,1),Saidas[Classificação],$B38,Saidas[Status],X!$E$7,Saidas[Conta Financeira],X!$E$8,Saidas[Centro de Custos],X!$E$9) -> 0 | F38: =SUMIFS(Saidas[Valores],Saidas[Data da Competência],">="&F$7,Saidas[Data da Competência],"<"&EDATE(F$7,1),Saidas[Classificação],$B38,Saidas[Status],X!$E$7,Saidas[Conta Financeira],X!$E$8,Saidas[Centro de Custos],X!$E$9) -> 0 | G38: =SUMIFS(Saidas[Valores],Saidas[Data da Competência],">="&G$7,Saidas[Data da Competência],"<"&EDATE(G$7,1),Saidas[Classificação],$B38,Saidas[Status],X!$E$7,Saidas[Conta Financeira],X!$E$8,Saidas[Centro de Custos],X!$E$9) -> 0 | H38: =SUMIFS(Saidas[Valores],Saidas[Data da Competência],">="&H$7,Saidas[Data da Competência],"<"&EDATE(H$7,1),Saidas[Classificação],$B38,Saidas[Status],X!$E$7,Saidas[Conta Financeira],X!$E$8,Saidas[Centro de Custos],X!$E$9) -> 0 | I38: =SUMIFS(Saidas[Valores],Saidas[Data da Competência],">="&I$7,Saidas[Data da Competência],"<"&EDATE(I$7,1),Saidas[Classificação],$B38,Saidas[Status],X!$E$7,Saidas[Conta Financeira],X!$E$8,Saidas[Centro de Custos],X!$E$9) -> 0 | J38: =SUMIFS(Saidas[Valores],Saidas[Data da Competência],">="&J$7,Saidas[Data da Competência],"<"&EDATE(J$7,1),Saidas[Classificação],$B38,Saidas[Status],X!$E$7,Saidas[Conta Financeira],X!$E$8,Saidas[Centro de Custos],X!$E$9) -> 0 | ... N38: =SUMIFS(Saidas[Valores],Saidas[Data da Competência],">="&N$7,Saidas[Data da Competência],"<"&EDATE(N$7,1),Saidas[Classificação],$B38,Saidas[Status],X!$E$7,Saidas[Conta Financeira],X!$E$8,Saidas[Centro de Custos],X!$E$9) -> 0 | O38: =SUM(C38:N38) -> 0
B39: =IFERROR(__xludf.DUMMYFUNCTION("""COMPUTED_VALUE"""),"Empréstimos Luiz") -> Empréstimos Luiz | C39: =SUMIFS(Saidas[Valores],Saidas[Data da Competência],">="&C$7,Saidas[Data da Competência],"<"&EDATE(C$7,1),Saidas[Classificação],$B39,Saidas[Status],X!$E$7,Saidas[Conta Financeira],X!$E$8,Saidas[Centro de Custos],X!$E$9) -> 0 | D39: =SUMIFS(Saidas[Valores],Saidas[Data da Competência],">="&D$7,Saidas[Data da Competência],"<"&EDATE(D$7,1),Saidas[Classificação],$B39,Saidas[Status],X!$E$7,Saidas[Conta Financeira],X!$E$8,Saidas[Centro de Custos],X!$E$9) -> 0 | E39: =SUMIFS(Saidas[Valores],Saidas[Data da Competência],">="&E$7,Saidas[Data da Competência],"<"&EDATE(E$7,1),Saidas[Classificação],$B39,Saidas[Status],X!$E$7,Saidas[Conta Financeira],X!$E$8,Saidas[Centro de Custos],X!$E$9) -> 0 | F39: =SUMIFS(Saidas[Valores],Saidas[Data da Competência],">="&F$7,Saidas[Data da Competência],"<"&EDATE(F$7,1),Saidas[Classificação],$B39,Saidas[Status],X!$E$7,Saidas[Conta Financeira],X!$E$8,Saidas[Centro de Custos],X!$E$9) -> 0 | G39: =SUMIFS(Saidas[Valores],Saidas[Data da Competência],">="&G$7,Saidas[Data da Competência],"<"&EDATE(G$7,1),Saidas[Classificação],$B39,Saidas[Status],X!$E$7,Saidas[Conta Financeira],X!$E$8,Saidas[Centro de Custos],X!$E$9) -> 0 | H39: =SUMIFS(Saidas[Valores],Saidas[Data da Competência],">="&H$7,Saidas[Data da Competência],"<"&EDATE(H$7,1),Saidas[Classificação],$B39,Saidas[Status],X!$E$7,Saidas[Conta Financeira],X!$E$8,Saidas[Centro de Custos],X!$E$9) -> 0 | I39: =SUMIFS(Saidas[Valores],Saidas[Data da Competência],">="&I$7,Saidas[Data da Competência],"<"&EDATE(I$7,1),Saidas[Classificação],$B39,Saidas[Status],X!$E$7,Saidas[Conta Financeira],X!$E$8,Saidas[Centro de Custos],X!$E$9) -> 0 | J39: =SUMIFS(Saidas[Valores],Saidas[Data da Competência],">="&J$7,Saidas[Data da Competência],"<"&EDATE(J$7,1),Saidas[Classificação],$B39,Saidas[Status],X!$E$7,Saidas[Conta Financeira],X!$E$8,Saidas[Centro de Custos],X!$E$9) -> 0 | ... N39: =SUMIFS(Saidas[Valores],Saidas[Data da Competência],">="&N$7,Saidas[Data da Competência],"<"&EDATE(N$7,1),Saidas[Classificação],$B39,Saidas[Status],X!$E$7,Saidas[Conta Financeira],X!$E$8,Saidas[Centro de Custos],X!$E$9) -> 0 | O39: =SUM(C39:N39) -> 0
B40: =IFERROR(__xludf.DUMMYFUNCTION("""COMPUTED_VALUE"""),"Empréstimos Diogo") -> Empréstimos Diogo | C40: =SUMIFS(Saidas[Valores],Saidas[Data da Competência],">="&C$7,Saidas[Data da Competência],"<"&EDATE(C$7,1),Saidas[Classificação],$B40,Saidas[Status],X!$E$7,Saidas[Conta Financeira],X!$E$8,Saidas[Centro de Custos],X!$E$9) -> 0 | D40: =SUMIFS(Saidas[Valores],Saidas[Data da Competência],">="&D$7,Saidas[Data da Competência],"<"&EDATE(D$7,1),Saidas[Classificação],$B40,Saidas[Status],X!$E$7,Saidas[Conta Financeira],X!$E$8,Saidas[Centro de Custos],X!$E$9) -> 0 | E40: =SUMIFS(Saidas[Valores],Saidas[Data da Competência],">="&E$7,Saidas[Data da Competência],"<"&EDATE(E$7,1),Saidas[Classificação],$B40,Saidas[Status],X!$E$7,Saidas[Conta Financeira],X!$E$8,Saidas[Centro de Custos],X!$E$9) -> 0 | F40: =SUMIFS(Saidas[Valores],Saidas[Data da Competência],">="&F$7,Saidas[Data da Competência],"<"&EDATE(F$7,1),Saidas[Classificação],$B40,Saidas[Status],X!$E$7,Saidas[Conta Financeira],X!$E$8,Saidas[Centro de Custos],X!$E$9) -> 0 | G40: =SUMIFS(Saidas[Valores],Saidas[Data da Competência],">="&G$7,Saidas[Data da Competência],"<"&EDATE(G$7,1),Saidas[Classificação],$B40,Saidas[Status],X!$E$7,Saidas[Conta Financeira],X!$E$8,Saidas[Centro de Custos],X!$E$9) -> 0 | H40: =SUMIFS(Saidas[Valores],Saidas[Data da Competência],">="&H$7,Saidas[Data da Competência],"<"&EDATE(H$7,1),Saidas[Classificação],$B40,Saidas[Status],X!$E$7,Saidas[Conta Financeira],X!$E$8,Saidas[Centro de Custos],X!$E$9) -> 0 | I40: =SUMIFS(Saidas[Valores],Saidas[Data da Competência],">="&I$7,Saidas[Data da Competência],"<"&EDATE(I$7,1),Saidas[Classificação],$B40,Saidas[Status],X!$E$7,Saidas[Conta Financeira],X!$E$8,Saidas[Centro de Custos],X!$E$9) -> 0 | J40: =SUMIFS(Saidas[Valores],Saidas[Data da Competência],">="&J$7,Saidas[Data da Competência],"<"&EDATE(J$7,1),Saidas[Classificação],$B40,Saidas[Status],X!$E$7,Saidas[Conta Financeira],X!$E$8,Saidas[Centro de Custos],X!$E$9) -> 0 | ... N40: =SUMIFS(Saidas[Valores],Saidas[Data da Competência],">="&N$7,Saidas[Data da Competência],"<"&EDATE(N$7,1),Saidas[Classificação],$B40,Saidas[Status],X!$E$7,Saidas[Conta Financeira],X!$E$8,Saidas[Centro de Custos],X!$E$9) -> 0 | O40: =SUM(C40:N40) -> 0
B41: =IFERROR(__xludf.DUMMYFUNCTION("""COMPUTED_VALUE"""),"Tarifas") -> Tarifas | C41: =SUMIFS(Saidas[Valores],Saidas[Data da Competência],">="&C$7,Saidas[Data da Competência],"<"&EDATE(C$7,1),Saidas[Classificação],$B41,Saidas[Status],X!$E$7,Saidas[Conta Financeira],X!$E$8,Saidas[Centro de Custos],X!$E$9) -> 0 | D41: =SUMIFS(Saidas[Valores],Saidas[Data da Competência],">="&D$7,Saidas[Data da Competência],"<"&EDATE(D$7,1),Saidas[Classificação],$B41,Saidas[Status],X!$E$7,Saidas[Conta Financeira],X!$E$8,Saidas[Centro de Custos],X!$E$9) -> 0 | E41: =SUMIFS(Saidas[Valores],Saidas[Data da Competência],">="&E$7,Saidas[Data da Competência],"<"&EDATE(E$7,1),Saidas[Classificação],$B41,Saidas[Status],X!$E$7,Saidas[Conta Financeira],X!$E$8,Saidas[Centro de Custos],X!$E$9) -> 0 | F41: =SUMIFS(Saidas[Valores],Saidas[Data da Competência],">="&F$7,Saidas[Data da Competência],"<"&EDATE(F$7,1),Saidas[Classificação],$B41,Saidas[Status],X!$E$7,Saidas[Conta Financeira],X!$E$8,Saidas[Centro de Custos],X!$E$9) -> 0 | G41: =SUMIFS(Saidas[Valores],Saidas[Data da Competência],">="&G$7,Saidas[Data da Competência],"<"&EDATE(G$7,1),Saidas[Classificação],$B41,Saidas[Status],X!$E$7,Saidas[Conta Financeira],X!$E$8,Saidas[Centro de Custos],X!$E$9) -> 0 | H41: =SUMIFS(Saidas[Valores],Saidas[Data da Competência],">="&H$7,Saidas[Data da Competência],"<"&EDATE(H$7,1),Saidas[Classificação],$B41,Saidas[Status],X!$E$7,Saidas[Conta Financeira],X!$E$8,Saidas[Centro de Custos],X!$E$9) -> 0 | I41: =SUMIFS(Saidas[Valores],Saidas[Data da Competência],">="&I$7,Saidas[Data da Competência],"<"&EDATE(I$7,1),Saidas[Classificação],$B41,Saidas[Status],X!$E$7,Saidas[Conta Financeira],X!$E$8,Saidas[Centro de Custos],X!$E$9) -> 0 | J41: =SUMIFS(Saidas[Valores],Saidas[Data da Competência],">="&J$7,Saidas[Data da Competência],"<"&EDATE(J$7,1),Saidas[Classificação],$B41,Saidas[Status],X!$E$7,Saidas[Conta Financeira],X!$E$8,Saidas[Centro de Custos],X!$E$9) -> 0 | ... N41: =SUMIFS(Saidas[Valores],Saidas[Data da Competência],">="&N$7,Saidas[Data da Competência],"<"&EDATE(N$7,1),Saidas[Classificação],$B41,Saidas[Status],X!$E$7,Saidas[Conta Financeira],X!$E$8,Saidas[Centro de Custos],X!$E$9) -> 0 | O41: =SUM(C41:N41) -> 0
B42: =IFERROR(__xludf.DUMMYFUNCTION("""COMPUTED_VALUE"""),"Diferença de Caixa") -> Diferença de Caixa | C42: =SUMIFS(Saidas[Valores],Saidas[Data da Competência],">="&C$7,Saidas[Data da Competência],"<"&EDATE(C$7,1),Saidas[Classificação],$B42,Saidas[Status],X!$E$7,Saidas[Conta Financeira],X!$E$8,Saidas[Centro de Custos],X!$E$9) -> 0 | D42: =SUMIFS(Saidas[Valores],Saidas[Data da Competência],">="&D$7,Saidas[Data da Competência],"<"&EDATE(D$7,1),Saidas[Classificação],$B42,Saidas[Status],X!$E$7,Saidas[Conta Financeira],X!$E$8,Saidas[Centro de Custos],X!$E$9) -> 0 | E42: =SUMIFS(Saidas[Valores],Saidas[Data da Competência],">="&E$7,Saidas[Data da Competência],"<"&EDATE(E$7,1),Saidas[Classificação],$B42,Saidas[Status],X!$E$7,Saidas[Conta Financeira],X!$E$8,Saidas[Centro de Custos],X!$E$9) -> 0 | F42: =SUMIFS(Saidas[Valores],Saidas[Data da Competência],">="&F$7,Saidas[Data da Competência],"<"&EDATE(F$7,1),Saidas[Classificação],$B42,Saidas[Status],X!$E$7,Saidas[Conta Financeira],X!$E$8,Saidas[Centro de Custos],X!$E$9) -> 0 | G42: =SUMIFS(Saidas[Valores],Saidas[Data da Competência],">="&G$7,Saidas[Data da Competência],"<"&EDATE(G$7,1),Saidas[Classificação],$B42,Saidas[Status],X!$E$7,Saidas[Conta Financeira],X!$E$8,Saidas[Centro de Custos],X!$E$9) -> 0 | H42: =SUMIFS(Saidas[Valores],Saidas[Data da Competência],">="&H$7,Saidas[Data da Competência],"<"&EDATE(H$7,1),Saidas[Classificação],$B42,Saidas[Status],X!$E$7,Saidas[Conta Financeira],X!$E$8,Saidas[Centro de Custos],X!$E$9) -> 0 | I42: =SUMIFS(Saidas[Valores],Saidas[Data da Competência],">="&I$7,Saidas[Data da Competência],"<"&EDATE(I$7,1),Saidas[Classificação],$B42,Saidas[Status],X!$E$7,Saidas[Conta Financeira],X!$E$8,Saidas[Centro de Custos],X!$E$9) -> 0 | J42: =SUMIFS(Saidas[Valores],Saidas[Data da Competência],">="&J$7,Saidas[Data da Competência],"<"&EDATE(J$7,1),Saidas[Classificação],$B42,Saidas[Status],X!$E$7,Saidas[Conta Financeira],X!$E$8,Saidas[Centro de Custos],X!$E$9) -> 0 | ... N42: =SUMIFS(Saidas[Valores],Saidas[Data da Competência],">="&N$7,Saidas[Data da Competência],"<"&EDATE(N$7,1),Saidas[Classificação],$B42,Saidas[Status],X!$E$7,Saidas[Conta Financeira],X!$E$8,Saidas[Centro de Custos],X!$E$9) -> 0 | O42: =SUM(C42:N42) -> 0
B43: =IFERROR(__xludf.DUMMYFUNCTION("""COMPUTED_VALUE"""),"Multas e Juros") -> Multas e Juros | C43: =SUMIFS(Saidas[Valores],Saidas[Data da Competência],">="&C$7,Saidas[Data da Competência],"<"&EDATE(C$7,1),Saidas[Classificação],$B43,Saidas[Status],X!$E$7,Saidas[Conta Financeira],X!$E$8,Saidas[Centro de Custos],X!$E$9) -> 0 | D43: =SUMIFS(Saidas[Valores],Saidas[Data da Competência],">="&D$7,Saidas[Data da Competência],"<"&EDATE(D$7,1),Saidas[Classificação],$B43,Saidas[Status],X!$E$7,Saidas[Conta Financeira],X!$E$8,Saidas[Centro de Custos],X!$E$9) -> 0 | E43: =SUMIFS(Saidas[Valores],Saidas[Data da Competência],">="&E$7,Saidas[Data da Competência],"<"&EDATE(E$7,1),Saidas[Classificação],$B43,Saidas[Status],X!$E$7,Saidas[Conta Financeira],X!$E$8,Saidas[Centro de Custos],X!$E$9) -> 0 | F43: =SUMIFS(Saidas[Valores],Saidas[Data da Competência],">="&F$7,Saidas[Data da Competência],"<"&EDATE(F$7,1),Saidas[Classificação],$B43,Saidas[Status],X!$E$7,Saidas[Conta Financeira],X!$E$8,Saidas[Centro de Custos],X!$E$9) -> 0 | G43: =SUMIFS(Saidas[Valores],Saidas[Data da Competência],">="&G$7,Saidas[Data da Competência],"<"&EDATE(G$7,1),Saidas[Classificação],$B43,Saidas[Status],X!$E$7,Saidas[Conta Financeira],X!$E$8,Saidas[Centro de Custos],X!$E$9) -> 0 | H43: =SUMIFS(Saidas[Valores],Saidas[Data da Competência],">="&H$7,Saidas[Data da Competência],"<"&EDATE(H$7,1),Saidas[Classificação],$B43,Saidas[Status],X!$E$7,Saidas[Conta Financeira],X!$E$8,Saidas[Centro de Custos],X!$E$9) -> 0 | I43: =SUMIFS(Saidas[Valores],Saidas[Data da Competência],">="&I$7,Saidas[Data da Competência],"<"&EDATE(I$7,1),Saidas[Classificação],$B43,Saidas[Status],X!$E$7,Saidas[Conta Financeira],X!$E$8,Saidas[Centro de Custos],X!$E$9) -> 0 | J43: =SUMIFS(Saidas[Valores],Saidas[Data da Competência],">="&J$7,Saidas[Data da Competência],"<"&EDATE(J$7,1),Saidas[Classificação],$B43,Saidas[Status],X!$E$7,Saidas[Conta Financeira],X!$E$8,Saidas[Centro de Custos],X!$E$9) -> 0 | ... N43: =SUMIFS(Saidas[Valores],Saidas[Data da Competência],">="&N$7,Saidas[Data da Competência],"<"&EDATE(N$7,1),Saidas[Classificação],$B43,Saidas[Status],X!$E$7,Saidas[Conta Financeira],X!$E$8,Saidas[Centro de Custos],X!$E$9) -> 0 | O43: =SUM(C43:N43) -> 0
B44: =IFERROR(__xludf.DUMMYFUNCTION("""COMPUTED_VALUE"""),"Outros") -> Outros | C44: =SUMIFS(Saidas[Valores],Saidas[Data da Competência],">="&C$7,Saidas[Data da Competência],"<"&EDATE(C$7,1),Saidas[Classificação],$B44,Saidas[Status],X!$E$7,Saidas[Conta Financeira],X!$E$8,Saidas[Centro de Custos],X!$E$9) -> 0 | D44: =SUMIFS(Saidas[Valores],Saidas[Data da Competência],">="&D$7,Saidas[Data da Competência],"<"&EDATE(D$7,1),Saidas[Classificação],$B44,Saidas[Status],X!$E$7,Saidas[Conta Financeira],X!$E$8,Saidas[Centro de Custos],X!$E$9) -> 0 | E44: =SUMIFS(Saidas[Valores],Saidas[Data da Competência],">="&E$7,Saidas[Data da Competência],"<"&EDATE(E$7,1),Saidas[Classificação],$B44,Saidas[Status],X!$E$7,Saidas[Conta Financeira],X!$E$8,Saidas[Centro de Custos],X!$E$9) -> 0 | F44: =SUMIFS(Saidas[Valores],Saidas[Data da Competência],">="&F$7,Saidas[Data da Competência],"<"&EDATE(F$7,1),Saidas[Classificação],$B44,Saidas[Status],X!$E$7,Saidas[Conta Financeira],X!$E$8,Saidas[Centro de Custos],X!$E$9) -> 0 | G44: =SUMIFS(Saidas[Valores],Saidas[Data da Competência],">="&G$7,Saidas[Data da Competência],"<"&EDATE(G$7,1),Saidas[Classificação],$B44,Saidas[Status],X!$E$7,Saidas[Conta Financeira],X!$E$8,Saidas[Centro de Custos],X!$E$9) -> 0 | H44: =SUMIFS(Saidas[Valores],Saidas[Data da Competência],">="&H$7,Saidas[Data da Competência],"<"&EDATE(H$7,1),Saidas[Classificação],$B44,Saidas[Status],X!$E$7,Saidas[Conta Financeira],X!$E$8,Saidas[Centro de Custos],X!$E$9) -> 0 | I44: =SUMIFS(Saidas[Valores],Saidas[Data da Competência],">="&I$7,Saidas[Data da Competência],"<"&EDATE(I$7,1),Saidas[Classificação],$B44,Saidas[Status],X!$E$7,Saidas[Conta Financeira],X!$E$8,Saidas[Centro de Custos],X!$E$9) -> 0 | J44: =SUMIFS(Saidas[Valores],Saidas[Data da Competência],">="&J$7,Saidas[Data da Competência],"<"&EDATE(J$7,1),Saidas[Classificação],$B44,Saidas[Status],X!$E$7,Saidas[Conta Financeira],X!$E$8,Saidas[Centro de Custos],X!$E$9) -> 0 | ... N44: =SUMIFS(Saidas[Valores],Saidas[Data da Competência],">="&N$7,Saidas[Data da Competência],"<"&EDATE(N$7,1),Saidas[Classificação],$B44,Saidas[Status],X!$E$7,Saidas[Conta Financeira],X!$E$8,Saidas[Centro de Custos],X!$E$9) -> 0 | O44: =SUM(C44:N44) -> 0
C45: =SUMIFS(Saidas[Valores],Saidas[Data da Competência],">="&C$7,Saidas[Data da Competência],"<"&EDATE(C$7,1),Saidas[Classificação],$B45,Saidas[Status],X!$E$7,Saidas[Conta Financeira],X!$E$8,Saidas[Centro de Custos],X!$E$9) -> 0 | D45: =SUMIFS(Saidas[Valores],Saidas[Data da Competência],">="&D$7,Saidas[Data da Competência],"<"&EDATE(D$7,1),Saidas[Classificação],$B45,Saidas[Status],X!$E$7,Saidas[Conta Financeira],X!$E$8,Saidas[Centro de Custos],X!$E$9) -> 0 | E45: =SUMIFS(Saidas[Valores],Saidas[Data da Competência],">="&E$7,Saidas[Data da Competência],"<"&EDATE(E$7,1),Saidas[Classificação],$B45,Saidas[Status],X!$E$7,Saidas[Conta Financeira],X!$E$8,Saidas[Centro de Custos],X!$E$9) -> 0 | F45: =SUMIFS(Saidas[Valores],Saidas[Data da Competência],">="&F$7,Saidas[Data da Competência],"<"&EDATE(F$7,1),Saidas[Classificação],$B45,Saidas[Status],X!$E$7,Saidas[Conta Financeira],X!$E$8,Saidas[Centro de Custos],X!$E$9) -> 0 | G45: =SUMIFS(Saidas[Valores],Saidas[Data da Competência],">="&G$7,Saidas[Data da Competência],"<"&EDATE(G$7,1),Saidas[Classificação],$B45,Saidas[Status],X!$E$7,Saidas[Conta Financeira],X!$E$8,Saidas[Centro de Custos],X!$E$9) -> 0 | H45: =SUMIFS(Saidas[Valores],Saidas[Data da Competência],">="&H$7,Saidas[Data da Competência],"<"&EDATE(H$7,1),Saidas[Classificação],$B45,Saidas[Status],X!$E$7,Saidas[Conta Financeira],X!$E$8,Saidas[Centro de Custos],X!$E$9) -> 0 | I45: =SUMIFS(Saidas[Valores],Saidas[Data da Competência],">="&I$7,Saidas[Data da Competência],"<"&EDATE(I$7,1),Saidas[Classificação],$B45,Saidas[Status],X!$E$7,Saidas[Conta Financeira],X!$E$8,Saidas[Centro de Custos],X!$E$9) -> 0 | J45: =SUMIFS(Saidas[Valores],Saidas[Data da Competência],">="&J$7,Saidas[Data da Competência],"<"&EDATE(J$7,1),Saidas[Classificação],$B45,Saidas[Status],X!$E$7,Saidas[Conta Financeira],X!$E$8,Saidas[Centro de Custos],X!$E$9) -> 0 | ... N45: =SUMIFS(Saidas[Valores],Saidas[Data da Competência],">="&N$7,Saidas[Data da Competência],"<"&EDATE(N$7,1),Saidas[Classificação],$B45,Saidas[Status],X!$E$7,Saidas[Conta Financeira],X!$E$8,Saidas[Centro de Custos],X!$E$9) -> 0 | O45: =SUM(C45:N45) -> 0
C46: =SUMIFS(Saidas[Valores],Saidas[Data da Competência],">="&C$7,Saidas[Data da Competência],"<"&EDATE(C$7,1),Saidas[Classificação],$B46,Saidas[Status],X!$E$7,Saidas[Conta Financeira],X!$E$8,Saidas[Centro de Custos],X!$E$9) -> 0 | D46: =SUMIFS(Saidas[Valores],Saidas[Data da Competência],">="&D$7,Saidas[Data da Competência],"<"&EDATE(D$7,1),Saidas[Classificação],$B46,Saidas[Status],X!$E$7,Saidas[Conta Financeira],X!$E$8,Saidas[Centro de Custos],X!$E$9) -> 0 | E46: =SUMIFS(Saidas[Valores],Saidas[Data da Competência],">="&E$7,Saidas[Data da Competência],"<"&EDATE(E$7,1),Saidas[Classificação],$B46,Saidas[Status],X!$E$7,Saidas[Conta Financeira],X!$E$8,Saidas[Centro de Custos],X!$E$9) -> 0 | F46: =SUMIFS(Saidas[Valores],Saidas[Data da Competência],">="&F$7,Saidas[Data da Competência],"<"&EDATE(F$7,1),Saidas[Classificação],$B46,Saidas[Status],X!$E$7,Saidas[Conta Financeira],X!$E$8,Saidas[Centro de Custos],X!$E$9) -> 0 | G46: =SUMIFS(Saidas[Valores],Saidas[Data da Competência],">="&G$7,Saidas[Data da Competência],"<"&EDATE(G$7,1),Saidas[Classificação],$B46,Saidas[Status],X!$E$7,Saidas[Conta Financeira],X!$E$8,Saidas[Centro de Custos],X!$E$9) -> 0 | H46: =SUMIFS(Saidas[Valores],Saidas[Data da Competência],">="&H$7,Saidas[Data da Competência],"<"&EDATE(H$7,1),Saidas[Classificação],$B46,Saidas[Status],X!$E$7,Saidas[Conta Financeira],X!$E$8,Saidas[Centro de Custos],X!$E$9) -> 0 | I46: =SUMIFS(Saidas[Valores],Saidas[Data da Competência],">="&I$7,Saidas[Data da Competência],"<"&EDATE(I$7,1),Saidas[Classificação],$B46,Saidas[Status],X!$E$7,Saidas[Conta Financeira],X!$E$8,Saidas[Centro de Custos],X!$E$9) -> 0 | J46: =SUMIFS(Saidas[Valores],Saidas[Data da Competência],">="&J$7,Saidas[Data da Competência],"<"&EDATE(J$7,1),Saidas[Classificação],$B46,Saidas[Status],X!$E$7,Saidas[Conta Financeira],X!$E$8,Saidas[Centro de Custos],X!$E$9) -> 0 | ... N46: =SUMIFS(Saidas[Valores],Saidas[Data da Competência],">="&N$7,Saidas[Data da Competência],"<"&EDATE(N$7,1),Saidas[Classificação],$B46,Saidas[Status],X!$E$7,Saidas[Conta Financeira],X!$E$8,Saidas[Centro de Custos],X!$E$9) -> 0 | O46: =SUM(C46:N46) -> 0
C47: =SUMIFS(Saidas[Valores],Saidas[Data da Competência],">="&C$7,Saidas[Data da Competência],"<"&EDATE(C$7,1),Saidas[Classificação],$B47,Saidas[Status],X!$E$7,Saidas[Conta Financeira],X!$E$8,Saidas[Centro de Custos],X!$E$9) -> 0 | D47: =SUMIFS(Saidas[Valores],Saidas[Data da Competência],">="&D$7,Saidas[Data da Competência],"<"&EDATE(D$7,1),Saidas[Classificação],$B47,Saidas[Status],X!$E$7,Saidas[Conta Financeira],X!$E$8,Saidas[Centro de Custos],X!$E$9) -> 0 | E47: =SUMIFS(Saidas[Valores],Saidas[Data da Competência],">="&E$7,Saidas[Data da Competência],"<"&EDATE(E$7,1),Saidas[Classificação],$B47,Saidas[Status],X!$E$7,Saidas[Conta Financeira],X!$E$8,Saidas[Centro de Custos],X!$E$9) -> 0 | F47: =SUMIFS(Saidas[Valores],Saidas[Data da Competência],">="&F$7,Saidas[Data da Competência],"<"&EDATE(F$7,1),Saidas[Classificação],$B47,Saidas[Status],X!$E$7,Saidas[Conta Financeira],X!$E$8,Saidas[Centro de Custos],X!$E$9) -> 0 | G47: =SUMIFS(Saidas[Valores],Saidas[Data da Competência],">="&G$7,Saidas[Data da Competência],"<"&EDATE(G$7,1),Saidas[Classificação],$B47,Saidas[Status],X!$E$7,Saidas[Conta Financeira],X!$E$8,Saidas[Centro de Custos],X!$E$9) -> 0 | H47: =SUMIFS(Saidas[Valores],Saidas[Data da Competência],">="&H$7,Saidas[Data da Competência],"<"&EDATE(H$7,1),Saidas[Classificação],$B47,Saidas[Status],X!$E$7,Saidas[Conta Financeira],X!$E$8,Saidas[Centro de Custos],X!$E$9) -> 0 | I47: =SUMIFS(Saidas[Valores],Saidas[Data da Competência],">="&I$7,Saidas[Data da Competência],"<"&EDATE(I$7,1),Saidas[Classificação],$B47,Saidas[Status],X!$E$7,Saidas[Conta Financeira],X!$E$8,Saidas[Centro de Custos],X!$E$9) -> 0 | J47: =SUMIFS(Saidas[Valores],Saidas[Data da Competência],">="&J$7,Saidas[Data da Competência],"<"&EDATE(J$7,1),Saidas[Classificação],$B47,Saidas[Status],X!$E$7,Saidas[Conta Financeira],X!$E$8,Saidas[Centro de Custos],X!$E$9) -> 0 | ... N47: =SUMIFS(Saidas[Valores],Saidas[Data da Competência],">="&N$7,Saidas[Data da Competência],"<"&EDATE(N$7,1),Saidas[Classificação],$B47,Saidas[Status],X!$E$7,Saidas[Conta Financeira],X!$E$8,Saidas[Centro de Custos],X!$E$9) -> 0 | O47: =SUM(C47:N47) -> 0
C48: =SUMIFS(Saidas[Valores],Saidas[Data da Competência],">="&C$7,Saidas[Data da Competência],"<"&EDATE(C$7,1),Saidas[Classificação],$B48,Saidas[Status],X!$E$7,Saidas[Conta Financeira],X!$E$8,Saidas[Centro de Custos],X!$E$9) -> 0 | D48: =SUMIFS(Saidas[Valores],Saidas[Data da Competência],">="&D$7,Saidas[Data da Competência],"<"&EDATE(D$7,1),Saidas[Classificação],$B48,Saidas[Status],X!$E$7,Saidas[Conta Financeira],X!$E$8,Saidas[Centro de Custos],X!$E$9) -> 0 | E48: =SUMIFS(Saidas[Valores],Saidas[Data da Competência],">="&E$7,Saidas[Data da Competência],"<"&EDATE(E$7,1),Saidas[Classificação],$B48,Saidas[Status],X!$E$7,Saidas[Conta Financeira],X!$E$8,Saidas[Centro de Custos],X!$E$9) -> 0 | F48: =SUMIFS(Saidas[Valores],Saidas[Data da Competência],">="&F$7,Saidas[Data da Competência],"<"&EDATE(F$7,1),Saidas[Classificação],$B48,Saidas[Status],X!$E$7,Saidas[Conta Financeira],X!$E$8,Saidas[Centro de Custos],X!$E$9) -> 0 | G48: =SUMIFS(Saidas[Valores],Saidas[Data da Competência],">="&G$7,Saidas[Data da Competência],"<"&EDATE(G$7,1),Saidas[Classificação],$B48,Saidas[Status],X!$E$7,Saidas[Conta Financeira],X!$E$8,Saidas[Centro de Custos],X!$E$9) -> 0 | H48: =SUMIFS(Saidas[Valores],Saidas[Data da Competência],">="&H$7,Saidas[Data da Competência],"<"&EDATE(H$7,1),Saidas[Classificação],$B48,Saidas[Status],X!$E$7,Saidas[Conta Financeira],X!$E$8,Saidas[Centro de Custos],X!$E$9) -> 0 | I48: =SUMIFS(Saidas[Valores],Saidas[Data da Competência],">="&I$7,Saidas[Data da Competência],"<"&EDATE(I$7,1),Saidas[Classificação],$B48,Saidas[Status],X!$E$7,Saidas[Conta Financeira],X!$E$8,Saidas[Centro de Custos],X!$E$9) -> 0 | J48: =SUMIFS(Saidas[Valores],Saidas[Data da Competência],">="&J$7,Saidas[Data da Competência],"<"&EDATE(J$7,1),Saidas[Classificação],$B48,Saidas[Status],X!$E$7,Saidas[Conta Financeira],X!$E$8,Saidas[Centro de Custos],X!$E$9) -> 0 | ... N48: =SUMIFS(Saidas[Valores],Saidas[Data da Competência],">="&N$7,Saidas[Data da Competência],"<"&EDATE(N$7,1),Saidas[Classificação],$B48,Saidas[Status],X!$E$7,Saidas[Conta Financeira],X!$E$8,Saidas[Centro de Custos],X!$E$9) -> 0 | O48: =SUM(C48:N48) -> 0
C49: =SUMIFS(Saidas[Valores],Saidas[Data da Competência],">="&C$7,Saidas[Data da Competência],"<"&EDATE(C$7,1),Saidas[Classificação],$B49,Saidas[Status],X!$E$7,Saidas[Conta Financeira],X!$E$8,Saidas[Centro de Custos],X!$E$9) -> 0 | D49: =SUMIFS(Saidas[Valores],Saidas[Data da Competência],">="&D$7,Saidas[Data da Competência],"<"&EDATE(D$7,1),Saidas[Classificação],$B49,Saidas[Status],X!$E$7,Saidas[Conta Financeira],X!$E$8,Saidas[Centro de Custos],X!$E$9) -> 0 | E49: =SUMIFS(Saidas[Valores],Saidas[Data da Competência],">="&E$7,Saidas[Data da Competência],"<"&EDATE(E$7,1),Saidas[Classificação],$B49,Saidas[Status],X!$E$7,Saidas[Conta Financeira],X!$E$8,Saidas[Centro de Custos],X!$E$9) -> 0 | F49: =SUMIFS(Saidas[Valores],Saidas[Data da Competência],">="&F$7,Saidas[Data da Competência],"<"&EDATE(F$7,1),Saidas[Classificação],$B49,Saidas[Status],X!$E$7,Saidas[Conta Financeira],X!$E$8,Saidas[Centro de Custos],X!$E$9) -> 0 | G49: =SUMIFS(Saidas[Valores],Saidas[Data da Competência],">="&G$7,Saidas[Data da Competência],"<"&EDATE(G$7,1),Saidas[Classificação],$B49,Saidas[Status],X!$E$7,Saidas[Conta Financeira],X!$E$8,Saidas[Centro de Custos],X!$E$9) -> 0 | H49: =SUMIFS(Saidas[Valores],Saidas[Data da Competência],">="&H$7,Saidas[Data da Competência],"<"&EDATE(H$7,1),Saidas[Classificação],$B49,Saidas[Status],X!$E$7,Saidas[Conta Financeira],X!$E$8,Saidas[Centro de Custos],X!$E$9) -> 0 | I49: =SUMIFS(Saidas[Valores],Saidas[Data da Competência],">="&I$7,Saidas[Data da Competência],"<"&EDATE(I$7,1),Saidas[Classificação],$B49,Saidas[Status],X!$E$7,Saidas[Conta Financeira],X!$E$8,Saidas[Centro de Custos],X!$E$9) -> 0 | J49: =SUMIFS(Saidas[Valores],Saidas[Data da Competência],">="&J$7,Saidas[Data da Competência],"<"&EDATE(J$7,1),Saidas[Classificação],$B49,Saidas[Status],X!$E$7,Saidas[Conta Financeira],X!$E$8,Saidas[Centro de Custos],X!$E$9) -> 0 | ... N49: =SUMIFS(Saidas[Valores],Saidas[Data da Competência],">="&N$7,Saidas[Data da Competência],"<"&EDATE(N$7,1),Saidas[Classificação],$B49,Saidas[Status],X!$E$7,Saidas[Conta Financeira],X!$E$8,Saidas[Centro de Custos],X!$E$9) -> 0 | O49: =SUM(C49:N49) -> 0
C50: =SUMIFS(Saidas[Valores],Saidas[Data da Competência],">="&C$7,Saidas[Data da Competência],"<"&EDATE(C$7,1),Saidas[Classificação],$B50,Saidas[Status],X!$E$7,Saidas[Conta Financeira],X!$E$8,Saidas[Centro de Custos],X!$E$9) -> 0 | D50: =SUMIFS(Saidas[Valores],Saidas[Data da Competência],">="&D$7,Saidas[Data da Competência],"<"&EDATE(D$7,1),Saidas[Classificação],$B50,Saidas[Status],X!$E$7,Saidas[Conta Financeira],X!$E$8,Saidas[Centro de Custos],X!$E$9) -> 0 | E50: =SUMIFS(Saidas[Valores],Saidas[Data da Competência],">="&E$7,Saidas[Data da Competência],"<"&EDATE(E$7,1),Saidas[Classificação],$B50,Saidas[Status],X!$E$7,Saidas[Conta Financeira],X!$E$8,Saidas[Centro de Custos],X!$E$9) -> 0 | F50: =SUMIFS(Saidas[Valores],Saidas[Data da Competência],">="&F$7,Saidas[Data da Competência],"<"&EDATE(F$7,1),Saidas[Classificação],$B50,Saidas[Status],X!$E$7,Saidas[Conta Financeira],X!$E$8,Saidas[Centro de Custos],X!$E$9) -> 0 | G50: =SUMIFS(Saidas[Valores],Saidas[Data da Competência],">="&G$7,Saidas[Data da Competência],"<"&EDATE(G$7,1),Saidas[Classificação],$B50,Saidas[Status],X!$E$7,Saidas[Conta Financeira],X!$E$8,Saidas[Centro de Custos],X!$E$9) -> 0 | H50: =SUMIFS(Saidas[Valores],Saidas[Data da Competência],">="&H$7,Saidas[Data da Competência],"<"&EDATE(H$7,1),Saidas[Classificação],$B50,Saidas[Status],X!$E$7,Saidas[Conta Financeira],X!$E$8,Saidas[Centro de Custos],X!$E$9) -> 0 | I50: =SUMIFS(Saidas[Valores],Saidas[Data da Competência],">="&I$7,Saidas[Data da Competência],"<"&EDATE(I$7,1),Saidas[Classificação],$B50,Saidas[Status],X!$E$7,Saidas[Conta Financeira],X!$E$8,Saidas[Centro de Custos],X!$E$9) -> 0 | J50: =SUMIFS(Saidas[Valores],Saidas[Data da Competência],">="&J$7,Saidas[Data da Competência],"<"&EDATE(J$7,1),Saidas[Classificação],$B50,Saidas[Status],X!$E$7,Saidas[Conta Financeira],X!$E$8,Saidas[Centro de Custos],X!$E$9) -> 0 | ... N50: =SUMIFS(Saidas[Valores],Saidas[Data da Competência],">="&N$7,Saidas[Data da Competência],"<"&EDATE(N$7,1),Saidas[Classificação],$B50,Saidas[Status],X!$E$7,Saidas[Conta Financeira],X!$E$8,Saidas[Centro de Custos],X!$E$9) -> 0 | O50: =SUM(C50:N50) -> 0
C51: =SUMIFS(Saidas[Valores],Saidas[Data da Competência],">="&C$7,Saidas[Data da Competência],"<"&EDATE(C$7,1),Saidas[Classificação],$B51,Saidas[Status],X!$E$7,Saidas[Conta Financeira],X!$E$8,Saidas[Centro de Custos],X!$E$9) -> 0 | D51: =SUMIFS(Saidas[Valores],Saidas[Data da Competência],">="&D$7,Saidas[Data da Competência],"<"&EDATE(D$7,1),Saidas[Classificação],$B51,Saidas[Status],X!$E$7,Saidas[Conta Financeira],X!$E$8,Saidas[Centro de Custos],X!$E$9) -> 0 | E51: =SUMIFS(Saidas[Valores],Saidas[Data da Competência],">="&E$7,Saidas[Data da Competência],"<"&EDATE(E$7,1),Saidas[Classificação],$B51,Saidas[Status],X!$E$7,Saidas[Conta Financeira],X!$E$8,Saidas[Centro de Custos],X!$E$9) -> 0 | F51: =SUMIFS(Saidas[Valores],Saidas[Data da Competência],">="&F$7,Saidas[Data da Competência],"<"&EDATE(F$7,1),Saidas[Classificação],$B51,Saidas[Status],X!$E$7,Saidas[Conta Financeira],X!$E$8,Saidas[Centro de Custos],X!$E$9) -> 0 | G51: =SUMIFS(Saidas[Valores],Saidas[Data da Competência],">="&G$7,Saidas[Data da Competência],"<"&EDATE(G$7,1),Saidas[Classificação],$B51,Saidas[Status],X!$E$7,Saidas[Conta Financeira],X!$E$8,Saidas[Centro de Custos],X!$E$9) -> 0 | H51: =SUMIFS(Saidas[Valores],Saidas[Data da Competência],">="&H$7,Saidas[Data da Competência],"<"&EDATE(H$7,1),Saidas[Classificação],$B51,Saidas[Status],X!$E$7,Saidas[Conta Financeira],X!$E$8,Saidas[Centro de Custos],X!$E$9) -> 0 | I51: =SUMIFS(Saidas[Valores],Saidas[Data da Competência],">="&I$7,Saidas[Data da Competência],"<"&EDATE(I$7,1),Saidas[Classificação],$B51,Saidas[Status],X!$E$7,Saidas[Conta Financeira],X!$E$8,Saidas[Centro de Custos],X!$E$9) -> 0 | J51: =SUMIFS(Saidas[Valores],Saidas[Data da Competência],">="&J$7,Saidas[Data da Competência],"<"&EDATE(J$7,1),Saidas[Classificação],$B51,Saidas[Status],X!$E$7,Saidas[Conta Financeira],X!$E$8,Saidas[Centro de Custos],X!$E$9) -> 0 | ... N51: =SUMIFS(Saidas[Valores],Saidas[Data da Competência],">="&N$7,Saidas[Data da Competência],"<"&EDATE(N$7,1),Saidas[Classificação],$B51,Saidas[Status],X!$E$7,Saidas[Conta Financeira],X!$E$8,Saidas[Centro de Custos],X!$E$9) -> 0 | O51: =SUM(C51:N51) -> 0
C52: =SUMIFS(Saidas[Valores],Saidas[Data da Competência],">="&C$7,Saidas[Data da Competência],"<"&EDATE(C$7,1),Saidas[Classificação],$B52,Saidas[Status],X!$E$7,Saidas[Conta Financeira],X!$E$8,Saidas[Centro de Custos],X!$E$9) -> 0 | D52: =SUMIFS(Saidas[Valores],Saidas[Data da Competência],">="&D$7,Saidas[Data da Competência],"<"&EDATE(D$7,1),Saidas[Classificação],$B52,Saidas[Status],X!$E$7,Saidas[Conta Financeira],X!$E$8,Saidas[Centro de Custos],X!$E$9) -> 0 | E52: =SUMIFS(Saidas[Valores],Saidas[Data da Competência],">="&E$7,Saidas[Data da Competência],"<"&EDATE(E$7,1),Saidas[Classificação],$B52,Saidas[Status],X!$E$7,Saidas[Conta Financeira],X!$E$8,Saidas[Centro de Custos],X!$E$9) -> 0 | F52: =SUMIFS(Saidas[Valores],Saidas[Data da Competência],">="&F$7,Saidas[Data da Competência],"<"&EDATE(F$7,1),Saidas[Classificação],$B52,Saidas[Status],X!$E$7,Saidas[Conta Financeira],X!$E$8,Saidas[Centro de Custos],X!$E$9) -> 0 | G52: =SUMIFS(Saidas[Valores],Saidas[Data da Competência],">="&G$7,Saidas[Data da Competência],"<"&EDATE(G$7,1),Saidas[Classificação],$B52,Saidas[Status],X!$E$7,Saidas[Conta Financeira],X!$E$8,Saidas[Centro de Custos],X!$E$9) -> 0 | H52: =SUMIFS(Saidas[Valores],Saidas[Data da Competência],">="&H$7,Saidas[Data da Competência],"<"&EDATE(H$7,1),Saidas[Classificação],$B52,Saidas[Status],X!$E$7,Saidas[Conta Financeira],X!$E$8,Saidas[Centro de Custos],X!$E$9) -> 0 | I52: =SUMIFS(Saidas[Valores],Saidas[Data da Competência],">="&I$7,Saidas[Data da Competência],"<"&EDATE(I$7,1),Saidas[Classificação],$B52,Saidas[Status],X!$E$7,Saidas[Conta Financeira],X!$E$8,Saidas[Centro de Custos],X!$E$9) -> 0 | J52: =SUMIFS(Saidas[Valores],Saidas[Data da Competência],">="&J$7,Saidas[Data da Competência],"<"&EDATE(J$7,1),Saidas[Classificação],$B52,Saidas[Status],X!$E$7,Saidas[Conta Financeira],X!$E$8,Saidas[Centro de Custos],X!$E$9) -> 0 | ... N52: =SUMIFS(Saidas[Valores],Saidas[Data da Competência],">="&N$7,Saidas[Data da Competência],"<"&EDATE(N$7,1),Saidas[Classificação],$B52,Saidas[Status],X!$E$7,Saidas[Conta Financeira],X!$E$8,Saidas[Centro de Custos],X!$E$9) -> 0 | O52: =SUM(C52:N52) -> 0
C53: =SUMIFS(Saidas[Valores],Saidas[Data da Competência],">="&C$7,Saidas[Data da Competência],"<"&EDATE(C$7,1),Saidas[Classificação],$B53,Saidas[Status],X!$E$7,Saidas[Conta Financeira],X!$E$8,Saidas[Centro de Custos],X!$E$9) -> 0 | D53: =SUMIFS(Saidas[Valores],Saidas[Data da Competência],">="&D$7,Saidas[Data da Competência],"<"&EDATE(D$7,1),Saidas[Classificação],$B53,Saidas[Status],X!$E$7,Saidas[Conta Financeira],X!$E$8,Saidas[Centro de Custos],X!$E$9) -> 0 | E53: =SUMIFS(Saidas[Valores],Saidas[Data da Competência],">="&E$7,Saidas[Data da Competência],"<"&EDATE(E$7,1),Saidas[Classificação],$B53,Saidas[Status],X!$E$7,Saidas[Conta Financeira],X!$E$8,Saidas[Centro de Custos],X!$E$9) -> 0 | F53: =SUMIFS(Saidas[Valores],Saidas[Data da Competência],">="&F$7,Saidas[Data da Competência],"<"&EDATE(F$7,1),Saidas[Classificação],$B53,Saidas[Status],X!$E$7,Saidas[Conta Financeira],X!$E$8,Saidas[Centro de Custos],X!$E$9) -> 0 | G53: =SUMIFS(Saidas[Valores],Saidas[Data da Competência],">="&G$7,Saidas[Data da Competência],"<"&EDATE(G$7,1),Saidas[Classificação],$B53,Saidas[Status],X!$E$7,Saidas[Conta Financeira],X!$E$8,Saidas[Centro de Custos],X!$E$9) -> 0 | H53: =SUMIFS(Saidas[Valores],Saidas[Data da Competência],">="&H$7,Saidas[Data da Competência],"<"&EDATE(H$7,1),Saidas[Classificação],$B53,Saidas[Status],X!$E$7,Saidas[Conta Financeira],X!$E$8,Saidas[Centro de Custos],X!$E$9) -> 0 | I53: =SUMIFS(Saidas[Valores],Saidas[Data da Competência],">="&I$7,Saidas[Data da Competência],"<"&EDATE(I$7,1),Saidas[Classificação],$B53,Saidas[Status],X!$E$7,Saidas[Conta Financeira],X!$E$8,Saidas[Centro de Custos],X!$E$9) -> 0 | J53: =SUMIFS(Saidas[Valores],Saidas[Data da Competência],">="&J$7,Saidas[Data da Competência],"<"&EDATE(J$7,1),Saidas[Classificação],$B53,Saidas[Status],X!$E$7,Saidas[Conta Financeira],X!$E$8,Saidas[Centro de Custos],X!$E$9) -> 0 | ... N53: =SUMIFS(Saidas[Valores],Saidas[Data da Competência],">="&N$7,Saidas[Data da Competência],"<"&EDATE(N$7,1),Saidas[Classificação],$B53,Saidas[Status],X!$E$7,Saidas[Conta Financeira],X!$E$8,Saidas[Centro de Custos],X!$E$9) -> 0 | O53: =SUM(C53:N53) -> 0
C54: =SUMIFS(Saidas[Valores],Saidas[Data da Competência],">="&C$7,Saidas[Data da Competência],"<"&EDATE(C$7,1),Saidas[Classificação],$B54,Saidas[Status],X!$E$7,Saidas[Conta Financeira],X!$E$8,Saidas[Centro de Custos],X!$E$9) -> 0 | D54: =SUMIFS(Saidas[Valores],Saidas[Data da Competência],">="&D$7,Saidas[Data da Competência],"<"&EDATE(D$7,1),Saidas[Classificação],$B54,Saidas[Status],X!$E$7,Saidas[Conta Financeira],X!$E$8,Saidas[Centro de Custos],X!$E$9) -> 0 | E54: =SUMIFS(Saidas[Valores],Saidas[Data da Competência],">="&E$7,Saidas[Data da Competência],"<"&EDATE(E$7,1),Saidas[Classificação],$B54,Saidas[Status],X!$E$7,Saidas[Conta Financeira],X!$E$8,Saidas[Centro de Custos],X!$E$9) -> 0 | F54: =SUMIFS(Saidas[Valores],Saidas[Data da Competência],">="&F$7,Saidas[Data da Competência],"<"&EDATE(F$7,1),Saidas[Classificação],$B54,Saidas[Status],X!$E$7,Saidas[Conta Financeira],X!$E$8,Saidas[Centro de Custos],X!$E$9) -> 0 | G54: =SUMIFS(Saidas[Valores],Saidas[Data da Competência],">="&G$7,Saidas[Data da Competência],"<"&EDATE(G$7,1),Saidas[Classificação],$B54,Saidas[Status],X!$E$7,Saidas[Conta Financeira],X!$E$8,Saidas[Centro de Custos],X!$E$9) -> 0 | H54: =SUMIFS(Saidas[Valores],Saidas[Data da Competência],">="&H$7,Saidas[Data da Competência],"<"&EDATE(H$7,1),Saidas[Classificação],$B54,Saidas[Status],X!$E$7,Saidas[Conta Financeira],X!$E$8,Saidas[Centro de Custos],X!$E$9) -> 0 | I54: =SUMIFS(Saidas[Valores],Saidas[Data da Competência],">="&I$7,Saidas[Data da Competência],"<"&EDATE(I$7,1),Saidas[Classificação],$B54,Saidas[Status],X!$E$7,Saidas[Conta Financeira],X!$E$8,Saidas[Centro de Custos],X!$E$9) -> 0 | J54: =SUMIFS(Saidas[Valores],Saidas[Data da Competência],">="&J$7,Saidas[Data da Competência],"<"&EDATE(J$7,1),Saidas[Classificação],$B54,Saidas[Status],X!$E$7,Saidas[Conta Financeira],X!$E$8,Saidas[Centro de Custos],X!$E$9) -> 0 | ... N54: =SUMIFS(Saidas[Valores],Saidas[Data da Competência],">="&N$7,Saidas[Data da Competência],"<"&EDATE(N$7,1),Saidas[Classificação],$B54,Saidas[Status],X!$E$7,Saidas[Conta Financeira],X!$E$8,Saidas[Centro de Custos],X!$E$9) -> 0 | O54: =SUM(C54:N54) -> 0
C55: =SUMIFS(Saidas[Valores],Saidas[Data da Competência],">="&C$7,Saidas[Data da Competência],"<"&EDATE(C$7,1),Saidas[Classificação],$B55,Saidas[Status],X!$E$7,Saidas[Conta Financeira],X!$E$8,Saidas[Centro de Custos],X!$E$9) -> 0 | D55: =SUMIFS(Saidas[Valores],Saidas[Data da Competência],">="&D$7,Saidas[Data da Competência],"<"&EDATE(D$7,1),Saidas[Classificação],$B55,Saidas[Status],X!$E$7,Saidas[Conta Financeira],X!$E$8,Saidas[Centro de Custos],X!$E$9) -> 0 | E55: =SUMIFS(Saidas[Valores],Saidas[Data da Competência],">="&E$7,Saidas[Data da Competência],"<"&EDATE(E$7,1),Saidas[Classificação],$B55,Saidas[Status],X!$E$7,Saidas[Conta Financeira],X!$E$8,Saidas[Centro de Custos],X!$E$9) -> 0 | F55: =SUMIFS(Saidas[Valores],Saidas[Data da Competência],">="&F$7,Saidas[Data da Competência],"<"&EDATE(F$7,1),Saidas[Classificação],$B55,Saidas[Status],X!$E$7,Saidas[Conta Financeira],X!$E$8,Saidas[Centro de Custos],X!$E$9) -> 0 | G55: =SUMIFS(Saidas[Valores],Saidas[Data da Competência],">="&G$7,Saidas[Data da Competência],"<"&EDATE(G$7,1),Saidas[Classificação],$B55,Saidas[Status],X!$E$7,Saidas[Conta Financeira],X!$E$8,Saidas[Centro de Custos],X!$E$9) -> 0 | H55: =SUMIFS(Saidas[Valores],Saidas[Data da Competência],">="&H$7,Saidas[Data da Competência],"<"&EDATE(H$7,1),Saidas[Classificação],$B55,Saidas[Status],X!$E$7,Saidas[Conta Financeira],X!$E$8,Saidas[Centro de Custos],X!$E$9) -> 0 | I55: =SUMIFS(Saidas[Valores],Saidas[Data da Competência],">="&I$7,Saidas[Data da Competência],"<"&EDATE(I$7,1),Saidas[Classificação],$B55,Saidas[Status],X!$E$7,Saidas[Conta Financeira],X!$E$8,Saidas[Centro de Custos],X!$E$9) -> 0 | J55: =SUMIFS(Saidas[Valores],Saidas[Data da Competência],">="&J$7,Saidas[Data da Competência],"<"&EDATE(J$7,1),Saidas[Classificação],$B55,Saidas[Status],X!$E$7,Saidas[Conta Financeira],X!$E$8,Saidas[Centro de Custos],X!$E$9) -> 0 | ... N55: =SUMIFS(Saidas[Valores],Saidas[Data da Competência],">="&N$7,Saidas[Data da Competência],"<"&EDATE(N$7,1),Saidas[Classificação],$B55,Saidas[Status],X!$E$7,Saidas[Conta Financeira],X!$E$8,Saidas[Centro de Custos],X!$E$9) -> 0 | O55: =SUM(C55:N55) -> 0

Sheet RESUMO
B2: APLICAR FILTROS AO RESUMO | E2: DEMONSTRATIVO DO RESULTADO DO EXERCÍCIO
E3: =X!$V$2 -> Receitas Operacionais | F3: =SUMIFS(Entradas[Valores],Entradas[Data da Competência],">="&$C$4,Entradas[Data da Competência],"<"&$D$5,Entradas[Categoria],$E3,Entradas[Status],X!$E$13,Entradas[Centro de Custos],X!$E$14) -> 25250 | G3: =F3/F5 -> 1 | I3: LUCRO LIQUIDO | J3: =G22 -> -0.86487129
B4: Data Inicial | C4: 45901 | E4: =X!$V$3 -> Outras Receitas Operacionais | F4: =SUMIFS(Entradas[Valores],Entradas[Data da Competência],">="&$C$4,Entradas[Data da Competência],"<"&$D$5,Entradas[Categoria],$E4,Entradas[Status],X!$E$13,Entradas[Centro de Custos],X!$E$14) -> 0 | G4: =F4/F5 -> 0 | I4: =F22 -> -21838
B5: Data Final | C5: 46022 | D5: =C5+1 -> 46023 | E5: Receita Bruta | F5: =F3+F4 -> 25250 | G5: =F5/F5 -> 1
B6: Centro de custos: | C6: Todos | E6: =X!$V$13 -> Impostos | F6: =SUMIFS(Saidas[Valores],Saidas[Data da Competência],">="&$C$4,Saidas[Data da Competência],"<"&$D$5,Saidas[Categoria],$E6,Saidas[Status],X!$E$13,Saidas[Centro de Custos],X!$E$14) -> 650 | G6: =F6/$F$5 -> 0.025742574
B7: Status: | C7: Ambos | E7: =X!$V$6 -> Deduções sobre vendas | F7: =SUMIFS(Saidas[Valores],Saidas[Data da Competência],">="&$C$4,Saidas[Data da Competência],"<"&$D$5,Saidas[Categoria],$E7,Saidas[Status],X!$E$13,Saidas[Centro de Custos],X!$E$14) -> 925 | G7: =F7/$F$5 -> 0.036633663 | I7: LUCRO OPERACIONAL | J7: =G15 -> -1.2807129
E8: Receita Liquida | F8: =F5-F6-F7 -> 23675 | G8: =F8/$F$5 -> 0.93762376 | I8: =F15 -> -32338
B9: CUSTOS FIXOS | C9: =B10/F5 -> 1.8689109 | E9: =X!$V$7 -> Custo das Vendas | F9: =SUMIFS(Saidas[Valores],Saidas[Data da Competência],">="&$C$4,Saidas[Data da Competência],"<"&$D$5,Saidas[Categoria],$E9,Saidas[Status],X!$E$13,Saidas[Centro de Custos],X!$E$14) -> 8823 | G9: =F9/$F$5 -> 0.34942574
B10: =F11+F12+F13+F14 -> 47190 | E10: Resultado Operacional Bruto | F10: =F8-F9 -> 14852 | G10: =F10/$F$5 -> 0.58819802
E11: =X!$V$8 -> Despesas administrativas | F11: =SUMIFS(Saidas[Valores],Saidas[Data da Competência],">="&$C$4,Saidas[Data da Competência],"<"&$D$5,Saidas[Categoria],$E11,Saidas[Status],X!$E$13,Saidas[Centro de Custos],X!$E$14) -> 4270 | G11: =F11/$F$5 -> 0.16910891 | I11: MARGEM DE CONTRIBUIÇÃO | J11: =G10 -> 0.58819802
E12: =X!$V$9 -> Despesa com Pessoal | F12: =SUMIFS(Saidas[Valores],Saidas[Data da Competência],">="&$C$4,Saidas[Data da Competência],"<"&$D$5,Saidas[Categoria],$E12,Saidas[Status],X!$E$13,Saidas[Centro de Custos],X!$E$14) -> 7920 | G12: =F12/$F$5 -> 0.31366337 | I12: =F10 -> 14852
B13: CUSTOS VARIÁVEIS | C13: =B14/F5 -> 0.41180198 | E13: =X!$V$11 -> Despesa Financeira | F13: =SUMIFS(Saidas[Valores],Saidas[Data da Competência],">="&$C$4,Saidas[Data da Competência],"<"&$D$5,Saidas[Categoria],$E13,Saidas[Status],X!$E$13,Saidas[Centro de Custos],X!$E$14) -> 0 | G13: =F13/$F$5 -> 0
B14: =F6+F7+F9 -> 10398 | E14: =X!$V$12 -> Despesas não operacionais | F14: =SUMIFS(Saidas[Valores],Saidas[Data da Competência],">="&$C$4,Saidas[Data da Competência],"<"&$D$5,Saidas[Categoria],$E14,Saidas[Status],X!$E$13,Saidas[Centro de Custos],X!$E$14) -> 35000 | G14: =F14/$F$5 -> 1.3861386
E15: Resultado Operacional Líquido | F15: =F10-F13-F11-F12-F14 -> -32338 | G15: =F15/$F$5 -> -1.2807129 | I15: CUSTO DAS VENDAS | J15: =G9 -> 0.34942574
E16: =X!$V$4 -> Receitas Financeiras | F16: =SUMIFS(Entradas[Valores],Entradas[Data da Competência],">="&$C$4,Entradas[Data da Competência],"<"&$D$5,Entradas[Categoria],$E16,Entradas[Status],X!$E$13,Entradas[Centro de Custos],X!$E$14) -> 0 | G16: =F16/$F$5 -> 0 | I16: =F9 -> 8823
B17: PONTO DE EQUILÍBRIO OPERACIONAL | E17: =X!$V$11 -> Despesa Financeira | F17: =SUMIFS(Saidas[Valores],Saidas[Data da Competência],">="&$C$4,Saidas[Data da Competência],"<"&$D$5,Saidas[Categoria],$E17,Saidas[Status],X!$E$13,Saidas[Centro de Custos],X!$E$14) -> 0 | G17: =F17/$F$5 -> 0
B18: =IF(C13>1,"Esse projeto não tem como se pagar", B10/(1-C13)) -> 80228.084 | E18: =X!$V$5 -> Receitas não operacionais | F18: =SUMIFS(Entradas[Valores],Entradas[Data da Competência],">="&$C$4,Entradas[Data da Competência],"<"&$D$5,Entradas[Categoria],$E18,Entradas[Status],X!$E$13,Entradas[Centro de Custos],X!$E$14) -> 10500 | G18: =F18/$F$5 -> 0.41584158
E19: =X!$V$14 -> Participação e Dividendos | F19: =SUMIFS(Saidas[Valores],Saidas[Data da Competência],">="&$C$4,Saidas[Data da Competência],"<"&$D$5,Saidas[Categoria],$E19,Saidas[Status],X!$E$13,Saidas[Centro de Custos],X!$E$14) -> 0 | G19: =F19/$F$5 -> 0
E20: Resultado Liquido | F20: =F15+F16-F17+F18-F19 -> -21838 | G20: =F20/$F$5 -> -0.86487129
E21: =X!$V$15 | F21: =SUMIFS(Saidas[Valores],Saidas[Data da Competência],">="&$C$4,Saidas[Data da Competência],"<"&$D$5,Saidas[Categoria],$E21,Saidas[Status],X!$E$13,Saidas[Centro de Custos],X!$E$14) -> 0 | G21: =F21/$F$5 -> 0 | I21: =48/6 -> 8
E22: Resultado Líquido do Exercício | F22: =F20-F21 -> -21838 | G22: =F22/$F$5 -> -0.86487129
B25: MAIORES CLIENTES NO PERÍODO | E25: MAIORES FORNECEDORES | I25: RECEITAS NO PERÍODO
B26: =IFERROR(__xludf.DUMMYFUNCTION("IFERROR( QUERY( FILTER( {Entradas[Cliente],Entradas[Valores],Entradas[Data do Recebimento]}, Entradas[Cliente]<>""-"", Entradas[Data do Recebimento]>=RESUMO!$C$4, Entradas[Data do Recebimento]<=RESUMO!$C$5 ), ""select"&" Col1, sum(Col2) where Col1 is not null group by Col1 order by sum(Col2) desc limit 5000 label Col1 'Cliente', sum(Col2) 'Total'"", 0 ), ""Sem dados no período"" ) "),"Cliente") -> Cliente | C26: =IFERROR(__xludf.DUMMYFUNCTION("""COMPUTED_VALUE"""),"Total") -> Total | E26: =IFERROR(__xludf.DUMMYFUNCTION("IFERROR( QUERY( FILTER( {Saidas[Fornecedor],Saidas[Valores],Saidas[Data do Pagamento]}, Saidas[Fornecedor]<>""-"", Saidas[Data do Pagamento]>=RESUMO!$C$4, Saidas[Data do Pagamento]<=RESUMO!$C$5 ), ""select Col1, sum(C"&"ol2) where Col1 is not null group by Col1 order by sum(Col2) desc limit 100 label Col1 'Fornecedor', sum(Col2) 'Total'"", 0 ), ""Sem dados no período"" ) "),"Fornecedor") -> Fornecedor | F26: =IFERROR(__xludf.DUMMYFUNCTION("""COMPUTED_VALUE"""),"Total") -> Total | I26: =X!V2 -> Receitas Operacionais | J26: =SUMIFS(Entradas[Valores],Entradas[Categoria],I26,Entradas[Data da Competência],">="&$C$4,Entradas[Data da Competência],"<"&$D$5) -> 25250
B27: =IFERROR(__xludf.DUMMYFUNCTION("""COMPUTED_VALUE"""),"Luiz Castro") -> Luiz Castro | C27: =IFERROR(__xludf.DUMMYFUNCTION("""COMPUTED_VALUE"""),9500.0) -> 9500 | E27: =IFERROR(__xludf.DUMMYFUNCTION("""COMPUTED_VALUE"""),"Fornecedor 01") -> Fornecedor 01 | F27: =IFERROR(__xludf.DUMMYFUNCTION("""COMPUTED_VALUE"""),40713.0) -> 40713 | I27: =X!V3 -> Outras Receitas Operacionais | J27: =SUMIFS(Entradas[Valores],Entradas[Categoria],I27,Entradas[Data da Competência],">="&$C$4,Entradas[Data da Competência],"<"&$D$5) -> 0
B28: =IFERROR(__xludf.DUMMYFUNCTION("""COMPUTED_VALUE"""),"Rafael Paiva") -> Rafael Paiva | C28: =IFERROR(__xludf.DUMMYFUNCTION("""COMPUTED_VALUE"""),9400.0) -> 9400 | E28: =IFERROR(__xludf.DUMMYFUNCTION("""COMPUTED_VALUE"""),"Fornecedor 03") -> Fornecedor 03 | F28: =IFERROR(__xludf.DUMMYFUNCTION("""COMPUTED_VALUE"""),11740.0) -> 11740 | I28: =X!V4 -> Receitas Financeiras | J28: =SUMIFS(Entradas[Valores],Entradas[Categoria],I28,Entradas[Data da Competência],">="&$C$4,Entradas[Data da Competência],"<"&$D$5) -> 0
B29: =IFERROR(__xludf.DUMMYFUNCTION("""COMPUTED_VALUE"""),"Rogério Ceni") -> Rogério Ceni | C29: =IFERROR(__xludf.DUMMYFUNCTION("""COMPUTED_VALUE"""),9200.0) -> 9200 | E29: =IFERROR(__xludf.DUMMYFUNCTION("""COMPUTED_VALUE"""),"Fornecedor 02") -> Fornecedor 02 | F29: =IFERROR(__xludf.DUMMYFUNCTION("""COMPUTED_VALUE"""),5135.0) -> 5135 | I29: =X!V5 -> Receitas não operacionais | J29: =SUMIFS(Entradas[Valores],Entradas[Categoria],I29,Entradas[Data da Competência],">="&$C$4,Entradas[Data da Competência],"<"&$D$5) -> 10500
B30: =IFERROR(__xludf.DUMMYFUNCTION("""COMPUTED_VALUE"""),"Roger Machado") -> Roger Machado | C30: =IFERROR(__xludf.DUMMYFUNCTION("""COMPUTED_VALUE"""),7650.0) -> 7650
I32: DESPESAS NO PERÍODO
I33: =X!V6 -> Deduções sobre vendas | J33: =SUMIFS(Saidas[Valores],Saidas[Categoria],I33,Saidas[Data da Competência],">="&$C$4,Saidas[Data da Competência],"<"&$D$5) -> 925
I34: =X!V7 -> Custo das Vendas | J34: =SUMIFS(Saidas[Valores],Saidas[Categoria],I34,Saidas[Data da Competência],">="&$C$4,Saidas[Data da Competência],"<"&$D$5) -> 8823
I35: =X!V8 -> Despesas administrativas | J35: =SUMIFS(Saidas[Valores],Saidas[Categoria],I35,Saidas[Data da Competência],">="&$C$4,Saidas[Data da Competência],"<"&$D$5) -> 4270
I36: =X!V9 -> Despesa com Pessoal | J36: =SUMIFS(Saidas[Valores],Saidas[Categoria],I36,Saidas[Data da Competência],">="&$C$4,Saidas[Data da Competência],"<"&$D$5) -> 7920
I37: =X!V11 -> Despesa Financeira | J37: =SUMIFS(Saidas[Valores],Saidas[Categoria],I37,Saidas[Data da Competência],">="&$C$4,Saidas[Data da Competência],"<"&$D$5) -> 0
I38: =X!V12 -> Despesas não operacionais | J38: =SUMIFS(Saidas[Valores],Saidas[Categoria],I38,Saidas[Data da Competência],">="&$C$4,Saidas[Data da Competência],"<"&$D$5) -> 35000
I39: =X!V13 -> Impostos | J39: =SUMIFS(Saidas[Valores],Saidas[Categoria],I39,Saidas[Data da Competência],">="&$C$4,Saidas[Data da Competência],"<"&$D$5) -> 650
I40: =X!V14 -> Participação e Dividendos | J40: =SUMIFS(Saidas[Valores],Saidas[Categoria],I40,Saidas[Data da Competência],">="&$C$4,Saidas[Data da Competência],"<"&$D$5) -> 0
I41: =#REF! -> #REF! | J41: =SUMIFS(Saidas[Valores],Saidas[Categoria],I41,Saidas[Data da Competência],">="&$C$4,Saidas[Data da Competência],"<"&$D$5) -> 0
I42: =X!V15 | J42: =SUMIFS(Saidas[Valores],Saidas[Categoria],I42,Saidas[Data da Competência],">="&$C$4,Saidas[Data da Competência],"<"&$D$5) -> 0

Sheet Dashboard
C2: Centro de custos: | D2: Todos
B4: =DAY(TODAY()) -> 11 | C4: =PROPER(TEXT(MesAtual,"MMMM/yyyy")) -> Agosto/2026
C5: =VLOOKUP(WEEKDAY(TODAY(),1),X!S1:T7,2,FALSE) -> Terça-Feira
C6: Saldo em Contas
B7: Hoje | C7: =SUM(D38:D52) -> 24615
C10: RECEBER | D10: A RECEBER | F10: A RECEBER
C11: HOJE | D11: ESSE MÊS | F11: TOTAL EM ABERTO
C12: =SUMIFS(Entradas[Valores],Entradas[Status],"Previsto",Entradas[Data do Recebimento],"="&TODAY(),Entradas[Centro de Custos], IF($D$2="Todos", "<>-", $D$2)) -> 0 | D12: =SUMIFS(Entradas[Valores],Entradas[Status],"Previsto",Entradas[Data do Recebimento],">="&TODAY(),Entradas[Data do Recebimento],"<"&EDATE(MesAtual,1),Entradas[Centro de Custos], IF($D$2="Todos", "<>-", $D$2)) -> 0 | F12: =SUMIFS(Entradas[Valores],Entradas[Status],"Previsto",Entradas[Centro de Custos], IF($D$2="Todos", "<>-", $D$2)) -> 16600
C13: ="Recebimentos em Atraso"&" "&TEXT(SUMIFS(Entradas[Valores],Entradas[Status],"Previsto",Entradas[Data do Recebimento],"<"&TODAY(),Entradas[Centro de Custos], IF($D$2="Todos", "<>-", $D$2)),"R$ 0.0,0") -> Recebimentos em Atraso R$ 16.600,00
C15: PAGAR | D15: A PAGAR | F15: A PAGAR
C16: HOJE | D16: ESSE MÊS | F16: TOTAL EM ABERTO
C17: =SUMIFS(Saidas[Valores],Saidas[Status],"Previsto",Saidas[Data do Pagamento],"="&TODAY(),Saidas[Centro de Custos], IF($D$2="Todos", "<>-", $D$2)) -> 0 | D17: =SUMIFS(Saidas[Valores],Saidas[Status],"Previsto",Saidas[Data do Pagamento],">="&TODAY(),Saidas[Data do Pagamento],"<"&EDATE(MesAtual,1),Saidas[Centro de Custos], IF($D$2="Todos", "<>-", $D$2)) -> 0 | F17: =SUMIFS(Saidas[Valores],Saidas[Status],"Previsto",Saidas[Centro de Custos], IF($D$2="Todos", "<>-", $D$2)) -> 55313
C18: ="Pagamentos em Atraso"& " "&TEXT(SUMIFS(Saidas[Valores],Saidas[Status],"Previsto",Saidas[Data do Pagamento],"<"&TODAY(),Saidas[Centro de Custos], IF($D$2="Todos", "<>-", $D$2)),"R$ 0.0,0") -> Pagamentos em Atraso R$ 55.313,00
B37: CONTAS BANCÁRIAS | D37: SALDO ATUAL
B38: =IFERROR(__xludf.DUMMYFUNCTION("FILTER(Cadastros!B6:B19,IF(D2=""Todos"",Cadastros!C6:C19<>""-"",Cadastros!C6:C19=D2))"),"Banco Inter") -> Banco Inter | D38: =IFERROR( SUMIFS( Entradas[Valores], Entradas[Conta Financeira], B38, Entradas[Status], "Realizado", Entradas[Centro de Custos], IF($D$2="Todos", "<>-", $D$2) ) - SUMIFS( Saidas[Valores], Saidas[Conta Financeira], B38, Saidas[Status], "Realizado", Saidas[Centro de Custos], IF($D$2="Todos", "<>-", $D$2) ) + SUMIFS( Cadastros!$D$6:$D$19, Cadastros!$B$6:$B$19, B38, Cadastros!$C$6:$C$19, IF($D$2="Todos", "<>-", $D$2) ) + SUMIFS( Transferência_Interna[Valor], Transferência_Interna[Conta de Destino], B38 ) - SUMIFS( Transferência_Interna[Valor], Transferência_Interna[Conta de Origem], B38 ), 0 ) -> -44735
B39: =IFERROR(__xludf.DUMMYFUNCTION("""COMPUTED_VALUE"""),"Nubank") -> Nubank | D39: =IFERROR( SUMIFS( Entradas[Valores], Entradas[Conta Financeira], B39, Entradas[Status], "Realizado", Entradas[Centro de Custos], IF($D$2="Todos", "<>-", $D$2) ) - SUMIFS( Saidas[Valores], Saidas[Conta Financeira], B39, Saidas[Status], "Realizado", Saidas[Centro de Custos], IF($D$2="Todos", "<>-", $D$2) ) + SUMIFS( Cadastros!$D$6:$D$19, Cadastros!$B$6:$B$19, B39, Cadastros!$C$6:$C$19, IF($D$2="Todos", "<>-", $D$2) ) + SUMIFS( Transferência_Interna[Valor], Transferência_Interna[Conta de Destino], B39 ) - SUMIFS( Transferência_Interna[Valor], Transferência_Interna[Conta de Origem], B39 ), 0 ) -> 69350
D40: =IFERROR( SUMIFS( Entradas[Valores], Entradas[Conta Financeira], B40, Entradas[Status], "Realizado", Entradas[Centro de Custos], IF($D$2="Todos", "<>-", $D$2) ) - SUMIFS( Saidas[Valores], Saidas[Conta Financeira], B40, Saidas[Status], "Realizado", Saidas[Centro de Custos], IF($D$2="Todos", "<>-", $D$2) ) + SUMIFS( Cadastros!$D$6:$D$19, Cadastros!$B$6:$B$19, B40, Cadastros!$C$6:$C$19, IF($D$2="Todos", "<>-", $D$2) ) + SUMIFS( Transferência_Interna[Valor], Transferência_Interna[Conta de Destino], B40 ) - SUMIFS( Transferência_Interna[Valor], Transferência_Interna[Conta de Origem], B40 ), 0 ) -> 0
D41: =IFERROR( SUMIFS( Entradas[Valores], Entradas[Conta Financeira], B41, Entradas[Status], "Realizado", Entradas[Centro de Custos], IF($D$2="Todos", "<>-", $D$2) ) - SUMIFS( Saidas[Valores], Saidas[Conta Financeira], B41, Saidas[Status], "Realizado", Saidas[Centro de Custos], IF($D$2="Todos", "<>-", $D$2) ) + SUMIFS( Cadastros!$D$6:$D$19, Cadastros!$B$6:$B$19, B41, Cadastros!$C$6:$C$19, IF($D$2="Todos", "<>-", $D$2) ) + SUMIFS( Transferência_Interna[Valor], Transferência_Interna[Conta de Destino], B41 ) - SUMIFS( Transferência_Interna[Valor], Transferência_Interna[Conta de Origem], B41 ), 0 ) -> 0
D42: =IFERROR( SUMIFS( Entradas[Valores], Entradas[Conta Financeira], B42, Entradas[Status], "Realizado", Entradas[Centro de Custos], IF($D$2="Todos", "<>-", $D$2) ) - SUMIFS( Saidas[Valores], Saidas[Conta Financeira], B42, Saidas[Status], "Realizado", Saidas[Centro de Custos], IF($D$2="Todos", "<>-", $D$2) ) + SUMIFS( Cadastros!$D$6:$D$19, Cadastros!$B$6:$B$19, B42, Cadastros!$C$6:$C$19, IF($D$2="Todos", "<>-", $D$2) ) + SUMIFS( Transferência_Interna[Valor], Transferência_Interna[Conta de Destino], B42 ) - SUMIFS( Transferência_Interna[Valor], Transferência_Interna[Conta de Origem], B42 ), 0 ) -> 0
D43: =IFERROR( SUMIFS( Entradas[Valores], Entradas[Conta Financeira], B43, Entradas[Status], "Realizado", Entradas[Centro de Custos], IF($D$2="Todos", "<>-", $D$2) ) - SUMIFS( Saidas[Valores], Saidas[Conta Financeira], B43, Saidas[Status], "Realizado", Saidas[Centro de Custos], IF($D$2="Todos", "<>-", $D$2) ) + SUMIFS( Cadastros!$D$6:$D$19, Cadastros!$B$6:$B$19, B43, Cadastros!$C$6:$C$19, IF($D$2="Todos", "<>-", $D$2) ) + SUMIFS( Transferência_Interna[Valor], Transferência_Interna[Conta de Destino], B43 ) - SUMIFS( Transferência_Interna[Valor], Transferência_Interna[Conta de Origem], B43 ), 0 ) -> 0
D44: =IFERROR( SUMIFS( Entradas[Valores], Entradas[Conta Financeira], B44, Entradas[Status], "Realizado", Entradas[Centro de Custos], IF($D$2="Todos", "<>-", $D$2) ) - SUMIFS( Saidas[Valores], Saidas[Conta Financeira], B44, Saidas[Status], "Realizado", Saidas[Centro de Custos], IF($D$2="Todos", "<>-", $D$2) ) + SUMIFS( Cadastros!$D$6:$D$19, Cadastros!$B$6:$B$19, B44, Cadastros!$C$6:$C$19, IF($D$2="Todos", "<>-", $D$2) ) + SUMIFS( Transferência_Interna[Valor], Transferência_Interna[Conta de Destino], B44 ) - SUMIFS( Transferência_Interna[Valor], Transferência_Interna[Conta de Origem], B44 ), 0 ) -> 0
D45: =IFERROR( SUMIFS( Entradas[Valores], Entradas[Conta Financeira], B45, Entradas[Status], "Realizado", Entradas[Centro de Custos], IF($D$2="Todos", "<>-", $D$2) ) - SUMIFS( Saidas[Valores], Saidas[Conta Financeira], B45, Saidas[Status], "Realizado", Saidas[Centro de Custos], IF($D$2="Todos", "<>-", $D$2) ) + SUMIFS( Cadastros!$D$6:$D$19, Cadastros!$B$6:$B$19, B45, Cadastros!$C$6:$C$19, IF($D$2="Todos", "<>-", $D$2) ) + SUMIFS( Transferência_Interna[Valor], Transferência_Interna[Conta de Destino], B45 ) - SUMIFS( Transferência_Interna[Valor], Transferência_Interna[Conta de Origem], B45 ), 0 ) -> 0
D46: =IFERROR( SUMIFS( Entradas[Valores], Entradas[Conta Financeira], B46, Entradas[Status], "Realizado", Entradas[Centro de Custos], IF($D$2="Todos", "<>-", $D$2) ) - SUMIFS( Saidas[Valores], Saidas[Conta Financeira], B46, Saidas[Status], "Realizado", Saidas[Centro de Custos], IF($D$2="Todos", "<>-", $D$2) ) + SUMIFS( Cadastros!$D$6:$D$19, Cadastros!$B$6:$B$19, B46, Cadastros!$C$6:$C$19, IF($D$2="Todos", "<>-", $D$2) ) + SUMIFS( Transferência_Interna[Valor], Transferência_Interna[Conta de Destino], B46 ) - SUMIFS( Transferência_Interna[Valor], Transferência_Interna[Conta de Origem], B46 ), 0 ) -> 0
D47: =IFERROR( SUMIFS( Entradas[Valores], Entradas[Conta Financeira], B47, Entradas[Status], "Realizado", Entradas[Centro de Custos], IF($D$2="Todos", "<>-", $D$2) ) - SUMIFS( Saidas[Valores], Saidas[Conta Financeira], B47, Saidas[Status], "Realizado", Saidas[Centro de Custos], IF($D$2="Todos", "<>-", $D$2) ) + SUMIFS( Cadastros!$D$6:$D$19, Cadastros!$B$6:$B$19, B47, Cadastros!$C$6:$C$19, IF($D$2="Todos", "<>-", $D$2) ) + SUMIFS( Transferência_Interna[Valor], Transferência_Interna[Conta de Destino], B47 ) - SUMIFS( Transferência_Interna[Valor], Transferência_Interna[Conta de Origem], B47 ), 0 ) -> 0
D48: =IFERROR( SUMIFS( Entradas[Valores], Entradas[Conta Financeira], B48, Entradas[Status], "Realizado", Entradas[Centro de Custos], IF($D$2="Todos", "<>-", $D$2) ) - SUMIFS( Saidas[Valores], Saidas[Conta Financeira], B48, Saidas[Status], "Realizado", Saidas[Centro de Custos], IF($D$2="Todos", "<>-", $D$2) ) + SUMIFS( Cadastros!$D$6:$D$19, Cadastros!$B$6:$B$19, B48, Cadastros!$C$6:$C$19, IF($D$2="Todos", "<>-", $D$2) ) + SUMIFS( Transferência_Interna[Valor], Transferência_Interna[Conta de Destino], B48 ) - SUMIFS( Transferência_Interna[Valor], Transferência_Interna[Conta de Origem], B48 ), 0 ) -> 0
D49: =IFERROR( SUMIFS( Entradas[Valores], Entradas[Conta Financeira], B49, Entradas[Status], "Realizado", Entradas[Centro de Custos], IF($D$2="Todos", "<>-", $D$2) ) - SUMIFS( Saidas[Valores], Saidas[Conta Financeira], B49, Saidas[Status], "Realizado", Saidas[Centro de Custos], IF($D$2="Todos", "<>-", $D$2) ) + SUMIFS( Cadastros!$D$6:$D$19, Cadastros!$B$6:$B$19, B49, Cadastros!$C$6:$C$19, IF($D$2="Todos", "<>-", $D$2) ) + SUMIFS( Transferência_Interna[Valor], Transferência_Interna[Conta de Destino], B49 ) - SUMIFS( Transferência_Interna[Valor], Transferência_Interna[Conta de Origem], B49 ), 0 ) -> 0
D50: =IFERROR( SUMIFS( Entradas[Valores], Entradas[Conta Financeira], B50, Entradas[Status], "Realizado", Entradas[Centro de Custos], IF($D$2="Todos", "<>-", $D$2) ) - SUMIFS( Saidas[Valores], Saidas[Conta Financeira], B50, Saidas[Status], "Realizado", Saidas[Centro de Custos], IF($D$2="Todos", "<>-", $D$2) ) + SUMIFS( Cadastros!$D$6:$D$19, Cadastros!$B$6:$B$19, B50, Cadastros!$C$6:$C$19, IF($D$2="Todos", "<>-", $D$2) ) + SUMIFS( Transferência_Interna[Valor], Transferência_Interna[Conta de Destino], B50 ) - SUMIFS( Transferência_Interna[Valor], Transferência_Interna[Conta de Origem], B50 ), 0 ) -> 0
D51: =IFERROR( SUMIFS( Entradas[Valores], Entradas[Conta Financeira], B51, Entradas[Status], "Realizado", Entradas[Centro de Custos], IF($D$2="Todos", "<>-", $D$2) ) - SUMIFS( Saidas[Valores], Saidas[Conta Financeira], B51, Saidas[Status], "Realizado", Saidas[Centro de Custos], IF($D$2="Todos", "<>-", $D$2) ) + SUMIFS( Cadastros!$D$6:$D$19, Cadastros!$B$6:$B$19, B51, Cadastros!$C$6:$C$19, IF($D$2="Todos", "<>-", $D$2) ) + SUMIFS( Transferência_Interna[Valor], Transferência_Interna[Conta de Destino], B51 ) - SUMIFS( Transferência_Interna[Valor], Transferência_Interna[Conta de Origem], B51 ), 0 ) -> 0
D52: =IFERROR( SUMIFS( Entradas[Valores], Entradas[Conta Financeira], B52, Entradas[Status], "Realizado", Entradas[Centro de Custos], IF($D$2="Todos", "<>-", $D$2) ) - SUMIFS( Saidas[Valores], Saidas[Conta Financeira], B52, Saidas[Status], "Realizado", Saidas[Centro de Custos], IF($D$2="Todos", "<>-", $D$2) ) + SUMIFS( Cadastros!$D$6:$D$19, Cadastros!$B$6:$B$19, B52, Cadastros!$C$6:$C$19, IF($D$2="Todos", "<>-", $D$2) ) + SUMIFS( Transferência_Interna[Valor], Transferência_Interna[Conta de Destino], B52 ) - SUMIFS( Transferência_Interna[Valor], Transferência_Interna[Conta de Origem], B52 ), 0 ) -> 0

Sheet Dash-Cel
B2: =DAY(TODAY()) -> 11
C3: Saldo em Contas
B4: =PROPER(TEXT(MesAtual,"MMMM")) -> Agosto | C4: =SUM(D93:D106) -> 24615
B5: =PROPER(TEXT(MesAtual,"YYYY")) -> 2026
C7: RECEBER | D7: A RECEBER
C8: HOJE | D8: ESSE MÊS
C9: =SUMIFS(Entradas[Valores],Entradas[Status],"Previsto",Entradas[Data do Recebimento],"="&TODAY()) -> 0 | D9: =SUMIFS(Entradas[Valores],Entradas[Status],"Previsto",Entradas[Data do Recebimento],">="&TODAY(),Entradas[Data do Recebimento],"<"&EDATE(MesAtual,1)) -> 0
B10: ="Recebimentos em Atraso"&" "&TEXT(SUMIFS(Entradas[Valores],Entradas[Status],"Previsto",Entradas[Data do Recebimento],"<"&TODAY()),"R$ 0.0,0") -> Recebimentos em Atraso R$ 16.600,00
C12: PAGAR | D12: A PAGAR | G12: A PAGAR
C13: HOJE | D13: ESSE MÊS | G13: TOTAL EM ABERTO
C14: =SUMIFS(Saidas[Valores],Saidas[Status],"Previsto",Saidas[Data do Pagamento],"="&TODAY()) -> 0 | D14: =SUMIFS(Saidas[Valores],Saidas[Status],"Previsto",Saidas[Data do Pagamento],">="&TODAY(),Saidas[Data do Pagamento],"<"&EDATE(MesAtual,1)) -> 0 | G14: =SUMIFS(Saidas[Valores],Saidas[Status],"Previsto") -> 55313
B15: ="Pagamentos em Atraso"& " "&TEXT(SUMIFS(Saidas[Valores],Saidas[Status],"Previsto",Saidas[Data do Pagamento],"<"&TODAY()),"R$ 0.0,0") -> Pagamentos em Atraso R$ 55.313,00
B69: DEMONSTRATIVO DO RESULTADO DO MÊS
B70: =X!$V$2 -> Receitas Operacionais | D70: =SUMIFS(Entradas[Valores],Entradas[Data da Competência],">="&MesAtual,Entradas[Data da Competência],"<"&EDATE(MesAtual,1),Entradas[Categoria],$B70) -> 0
B71: =X!$V$3 -> Outras Receitas Operacionais | D71: =SUMIFS(Entradas[Valores],Entradas[Data da Competência],">="&MesAtual,Entradas[Data da Competência],"<"&EDATE(MesAtual,1),Entradas[Categoria],$B71) -> 0
B72: Receita Bruta | D72: =D70+D71 -> 0
B73: =#REF! -> #REF! | D73: =SUMIFS(Saidas[Valores],Saidas[Data da Competência],">="&MesAtual,Saidas[Data da Competência],"<"&EDATE(MesAtual,1),Saidas[Categoria],$B73) -> 0
B74: =X!$V$6 -> Deduções sobre vendas | D74: =SUMIFS(Saidas[Valores],Saidas[Data da Competência],">="&MesAtual,Saidas[Data da Competência],"<"&EDATE(MesAtual,1),Saidas[Categoria],$B74) -> 0
B75: Receita Liquida | D75: =D72-D73-D74 -> 0
B76: =X!$V$7 -> Custo das Vendas | D76: =SUMIFS(Saidas[Valores],Saidas[Data da Competência],">="&MesAtual,Saidas[Data da Competência],"<"&EDATE(MesAtual,1),Saidas[Categoria],$B76) -> 0
B77: Resultado Operacional Bruto | D77: =D75-D76 -> 0
B78: =X!$V$8 -> Despesas administrativas | D78: =SUMIFS(Saidas[Valores],Saidas[Data da Competência],">="&MesAtual,Saidas[Data da Competência],"<"&EDATE(MesAtual,1),Saidas[Categoria],$B78) -> 0
B79: =X!$V$9 -> Despesa com Pessoal | D79: =SUMIFS(Saidas[Valores],Saidas[Data da Competência],">="&MesAtual,Saidas[Data da Competência],"<"&EDATE(MesAtual,1),Saidas[Categoria],$B79) -> 0
B80: =X!$V$11 -> Despesa Financeira | D80: =SUMIFS(Saidas[Valores],Saidas[Data da Competência],">="&MesAtual,Saidas[Data da Competência],"<"&EDATE(MesAtual,1),Saidas[Categoria],$B80) -> 0
B81: =X!$V$12 -> Despesas não operacionais | D81: =SUMIFS(Saidas[Valores],Saidas[Data da Competência],">="&MesAtual,Saidas[Data da Competência],"<"&EDATE(MesAtual,1),Saidas[Categoria],$B81) -> 0
B82: Resultado Operacional Líquido | E82: =D77-D78-D79-D80-D81 -> 0
B83: =X!$V$4 -> Receitas Financeiras | D83: =SUMIFS(Entradas[Valores],Entradas[Data da Competência],">="&MesAtual,Entradas[Data da Competência],"<"&EDATE(MesAtual,1),Entradas[Categoria],$B83) -> 0
B84: =X!$V$13 -> Impostos | D84: =SUMIFS(Saidas[Valores],Saidas[Data da Competência],">="&MesAtual,Saidas[Data da Competência],"<"&EDATE(MesAtual,1),Saidas[Categoria],$B84) -> 0
B85: =X!$V$5 -> Receitas não operacionais | D85: =SUMIFS(Entradas[Valores],Entradas[Data da Competência],">="&MesAtual,Entradas[Data da Competência],"<"&EDATE(MesAtual,1),Entradas[Categoria],$B85) -> 0
B86: =X!$V$14 -> Participação e Dividendos | D86: =SUMIFS(Saidas[Valores],Saidas[Data da Competência],">="&MesAtual,Saidas[Data da Competência],"<"&EDATE(MesAtual,1),Saidas[Categoria],$B86) -> 0
B87: Resultado Liquido | D87: =E82+D83-D84+D85-D86 -> 0
B88: =X!$V$15 | D88: =SUMIFS(Saidas[Valores],Saidas[Data da Competência],">="&MesAtual,Saidas[Data da Competência],"<"&EDATE(MesAtual,1),Saidas[Categoria],$B88) -> 0
B89: Resultado Líquido do Exercício | D89: =D87-D88 -> 0
B92: CONTAS BANCÁRIAS | E92: SALDO ATUAL
B93: {=bancos} -> Banco Inter | D93: =SUMIFS(Entradas[Valores],Entradas[Conta Financeira],B93,Entradas[Status],"Realizado")-SUMIFS(Saidas[Valores],Saidas[Conta Financeira],B93,Saidas[Status],"Realizado")+SUMIFS(Cadastros!$D$6:$D$19,Cadastros!$B$6:$B$19,B93)+SUMIFS(Transferência_Interna[Valor],Transferência_Interna[Conta de Destino],B93)-SUMIFS(Transferência_Interna[Valor],Transferência_Interna[Conta de Origem],B93) -> -44735
B94: Nubank | D94: =SUMIFS(Entradas[Valores],Entradas[Conta Financeira],B94,Entradas[Status],"Realizado")-SUMIFS(Saidas[Valores],Saidas[Conta Financeira],B94,Saidas[Status],"Realizado")+SUMIFS(Cadastros!$D$6:$D$19,Cadastros!$B$6:$B$19,B94)+SUMIFS(Transferência_Interna[Valor],Transferência_Interna[Conta de Destino],B94)-SUMIFS(Transferência_Interna[Valor],Transferência_Interna[Conta de Origem],B94) -> 69350
D95: =SUMIFS(Entradas[Valores],Entradas[Conta Financeira],B95,Entradas[Status],"Realizado")-SUMIFS(Saidas[Valores],Saidas[Conta Financeira],B95,Saidas[Status],"Realizado")+SUMIFS(Cadastros!$D$6:$D$19,Cadastros!$B$6:$B$19,B95)+SUMIFS(Transferência_Interna[Valor],Transferência_Interna[Conta de Destino],B95)-SUMIFS(Transferência_Interna[Valor],Transferência_Interna[Conta de Origem],B95) -> 0
D96: =SUMIFS(Entradas[Valores],Entradas[Conta Financeira],B96,Entradas[Status],"Realizado")-SUMIFS(Saidas[Valores],Saidas[Conta Financeira],B96,Saidas[Status],"Realizado")+SUMIFS(Cadastros!$D$6:$D$19,Cadastros!$B$6:$B$19,B96)+SUMIFS(Transferência_Interna[Valor],Transferência_Interna[Conta de Destino],B96)-SUMIFS(Transferência_Interna[Valor],Transferência_Interna[Conta de Origem],B96) -> 0
D97: =SUMIFS(Entradas[Valores],Entradas[Conta Financeira],B97,Entradas[Status],"Realizado")-SUMIFS(Saidas[Valores],Saidas[Conta Financeira],B97,Saidas[Status],"Realizado")+SUMIFS(Cadastros!$D$6:$D$19,Cadastros!$B$6:$B$19,B97)+SUMIFS(Transferência_Interna[Valor],Transferência_Interna[Conta de Destino],B97)-SUMIFS(Transferência_Interna[Valor],Transferência_Interna[Conta de Origem],B97) -> 0
D98: =SUMIFS(Entradas[Valores],Entradas[Conta Financeira],B98,Entradas[Status],"Realizado")-SUMIFS(Saidas[Valores],Saidas[Conta Financeira],B98,Saidas[Status],"Realizado")+SUMIFS(Cadastros!$D$6:$D$19,Cadastros!$B$6:$B$19,B98)+SUMIFS(Transferência_Interna[Valor],Transferência_Interna[Conta de Destino],B98)-SUMIFS(Transferência_Interna[Valor],Transferência_Interna[Conta de Origem],B98) -> 0
D99: =SUMIFS(Entradas[Valores],Entradas[Conta Financeira],B99,Entradas[Status],"Realizado")-SUMIFS(Saidas[Valores],Saidas[Conta Financeira],B99,Saidas[Status],"Realizado")+SUMIFS(Cadastros!$D$6:$D$19,Cadastros!$B$6:$B$19,B99)+SUMIFS(Transferência_Interna[Valor],Transferência_Interna[Conta de Destino],B99)-SUMIFS(Transferência_Interna[Valor],Transferência_Interna[Conta de Origem],B99) -> 0
D100: =SUMIFS(Entradas[Valores],Entradas[Conta Financeira],B100,Entradas[Status],"Realizado")-SUMIFS(Saidas[Valores],Saidas[Conta Financeira],B100,Saidas[Status],"Realizado")+SUMIFS(Cadastros!$D$6:$D$19,Cadastros!$B$6:$B$19,B100)+SUMIFS(Transferência_Interna[Valor],Transferência_Interna[Conta de Destino],B100)-SUMIFS(Transferência_Interna[Valor],Transferência_Interna[Conta de Origem],B100) -> 0
D101: =SUMIFS(Entradas[Valores],Entradas[Conta Financeira],B101,Entradas[Status],"Realizado")-SUMIFS(Saidas[Valores],Saidas[Conta Financeira],B101,Saidas[Status],"Realizado")+SUMIFS(Cadastros!$D$6:$D$19,Cadastros!$B$6:$B$19,B101)+SUMIFS(Transferência_Interna[Valor],Transferência_Interna[Conta de Destino],B101)-SUMIFS(Transferência_Interna[Valor],Transferência_Interna[Conta de Origem],B101) -> 0
D102: =SUMIFS(Entradas[Valores],Entradas[Conta Financeira],B102,Entradas[Status],"Realizado")-SUMIFS(Saidas[Valores],Saidas[Conta Financeira],B102,Saidas[Status],"Realizado")+SUMIFS(Cadastros!$D$6:$D$19,Cadastros!$B$6:$B$19,B102)+SUMIFS(Transferência_Interna[Valor],Transferência_Interna[Conta de Destino],B102)-SUMIFS(Transferência_Interna[Valor],Transferência_Interna[Conta de Origem],B102) -> 0
D103: =SUMIFS(Entradas[Valores],Entradas[Conta Financeira],B103,Entradas[Status],"Realizado")-SUMIFS(Saidas[Valores],Saidas[Conta Financeira],B103,Saidas[Status],"Realizado")+SUMIFS(Cadastros!$D$6:$D$19,Cadastros!$B$6:$B$19,B103)+SUMIFS(Transferência_Interna[Valor],Transferência_Interna[Conta de Destino],B103)-SUMIFS(Transferência_Interna[Valor],Transferência_Interna[Conta de Origem],B103) -> 0
D104: =SUMIFS(Entradas[Valores],Entradas[Conta Financeira],B104,Entradas[Status],"Realizado")-SUMIFS(Saidas[Valores],Saidas[Conta Financeira],B104,Saidas[Status],"Realizado")+SUMIFS(Cadastros!$D$6:$D$19,Cadastros!$B$6:$B$19,B104)+SUMIFS(Transferência_Interna[Valor],Transferência_Interna[Conta de Destino],B104)-SUMIFS(Transferência_Interna[Valor],Transferência_Interna[Conta de Origem],B104) -> 0
D105: =SUMIFS(Entradas[Valores],Entradas[Conta Financeira],B105,Entradas[Status],"Realizado")-SUMIFS(Saidas[Valores],Saidas[Conta Financeira],B105,Saidas[Status],"Realizado")+SUMIFS(Cadastros!$D$6:$D$19,Cadastros!$B$6:$B$19,B105)+SUMIFS(Transferência_Interna[Valor],Transferência_Interna[Conta de Destino],B105)-SUMIFS(Transferência_Interna[Valor],Transferência_Interna[Conta de Origem],B105) -> 0
D106: =SUMIFS(Entradas[Valores],Entradas[Conta Financeira],B106,Entradas[Status],"Realizado")-SUMIFS(Saidas[Valores],Saidas[Conta Financeira],B106,Saidas[Status],"Realizado")+SUMIFS(Cadastros!$D$6:$D$19,Cadastros!$B$6:$B$19,B106)+SUMIFS(Transferência_Interna[Valor],Transferência_Interna[Conta de Destino],B106)-SUMIFS(Transferência_Interna[Valor],Transferência_Interna[Conta de Origem],B106) -> 0

Sheet dash-tab
B2: =DAY(TODAY()) -> 11
C3: Saldo em Contas
B4: =PROPER(TEXT(MesAtual,"MMMM")) -> Agosto | C4: =SUM(I33:I46) -> 24615
B5: =PROPER(TEXT(MesAtual,"YYYY")) -> 2026
C7: RECEBER | D7: A RECEBER
C8: HOJE | D8: ESSE MÊS
C9: =SUMIFS(Entradas[Valores],Entradas[Status],"Previsto",Entradas[Data do Recebimento],"="&TODAY()) -> 0 | D9: =SUMIFS(Entradas[Valores],Entradas[Status],"Previsto",Entradas[Data do Recebimento],">="&TODAY(),Entradas[Data do Recebimento],"<"&EDATE(MesAtual,1)) -> 0
B10: ="Recebimentos em Atraso"&" "&TEXT(SUMIFS(Entradas[Valores],Entradas[Status],"Previsto",Entradas[Data do Recebimento],"<"&TODAY()),"R$ 0.0,0") -> Recebimentos em Atraso R$ 16.600,00
C12: PAGAR | D12: A PAGAR | G12: A PAGAR
C13: HOJE | D13: ESSE MÊS | G13: TOTAL EM ABERTO
C14: =SUMIFS(Saidas[Valores],Saidas[Status],"Previsto",Saidas[Data do Pagamento],"="&TODAY()) -> 0 | D14: =SUMIFS(Saidas[Valores],Saidas[Status],"Previsto",Saidas[Data do Pagamento],">="&TODAY(),Saidas[Data do Pagamento],"<"&EDATE(MesAtual,1)) -> 0 | G14: =SUMIFS(Saidas[Valores],Saidas[Status],"Previsto") -> 55313
B15: ="Pagamentos em Atraso"& " "&TEXT(SUMIFS(Saidas[Valores],Saidas[Status],"Previsto",Saidas[Data do Pagamento],"<"&TODAY()),"R$ 0.0,0") -> Pagamentos em Atraso R$ 55.313,00
B32: DEMONSTRATIVO DO RESULTADO DO EXERCÍCIO | G32: CONTAS BANCÁRIAS | J32: SALDO ATUAL
B33: =X!$V$2 -> Receitas Operacionais | D33: =SUMIFS(Entradas[Valores],Entradas[Data da Competência],">="&MesAtual,Entradas[Data da Competência],"<"&EDATE(MesAtual,1),Entradas[Categoria],$B33) -> 0 | G33: {=bancos} -> Banco Inter | I33: =SUMIFS(Entradas[Valores],Entradas[Conta Financeira],G33,Entradas[Status],"Realizado")-SUMIFS(Saidas[Valores],Saidas[Conta Financeira],G33,Saidas[Status],"Realizado")+SUMIFS(Cadastros!$D$6:$D$19,Cadastros!$B$6:$B$19,G33)+SUMIFS(Transferência_Interna[Valor],Transferência_Interna[Conta de Destino],G33)-SUMIFS(Transferência_Interna[Valor],Transferência_Interna[Conta de Origem],G33) -> -44735
B34: =X!$V$3 -> Outras Receitas Operacionais | D34: =SUMIFS(Entradas[Valores],Entradas[Data da Competência],">="&MesAtual,Entradas[Data da Competência],"<"&EDATE(MesAtual,1),Entradas[Categoria],$B34) -> 0 | G34: Nubank | I34: =SUMIFS(Entradas[Valores],Entradas[Conta Financeira],G34,Entradas[Status],"Realizado")-SUMIFS(Saidas[Valores],Saidas[Conta Financeira],G34,Saidas[Status],"Realizado")+SUMIFS(Cadastros!$D$6:$D$19,Cadastros!$B$6:$B$19,G34)+SUMIFS(Transferência_Interna[Valor],Transferência_Interna[Conta de Destino],G34)-SUMIFS(Transferência_Interna[Valor],Transferência_Interna[Conta de Origem],G34) -> 69350
B35: Receita Bruta | D35: =D33+D34 -> 0 | I35: =SUMIFS(Entradas[Valores],Entradas[Conta Financeira],G35,Entradas[Status],"Realizado")-SUMIFS(Saidas[Valores],Saidas[Conta Financeira],G35,Saidas[Status],"Realizado")+SUMIFS(Cadastros!$D$6:$D$19,Cadastros!$B$6:$B$19,G35)+SUMIFS(Transferência_Interna[Valor],Transferência_Interna[Conta de Destino],G35)-SUMIFS(Transferência_Interna[Valor],Transferência_Interna[Conta de Origem],G35) -> 0
B36: =#REF! -> #REF! | D36: =SUMIFS(Saidas[Valores],Saidas[Data da Competência],">="&MesAtual,Saidas[Data da Competência],"<"&EDATE(MesAtual,1),Saidas[Categoria],$B36) -> 0 | I36: =SUMIFS(Entradas[Valores],Entradas[Conta Financeira],G36,Entradas[Status],"Realizado")-SUMIFS(Saidas[Valores],Saidas[Conta Financeira],G36,Saidas[Status],"Realizado")+SUMIFS(Cadastros!$D$6:$D$19,Cadastros!$B$6:$B$19,G36)+SUMIFS(Transferência_Interna[Valor],Transferência_Interna[Conta de Destino],G36)-SUMIFS(Transferência_Interna[Valor],Transferência_Interna[Conta de Origem],G36) -> 0
B37: =X!$V$6 -> Deduções sobre vendas | D37: =SUMIFS(Saidas[Valores],Saidas[Data da Competência],">="&MesAtual,Saidas[Data da Competência],"<"&EDATE(MesAtual,1),Saidas[Categoria],$B37) -> 0 | I37: =SUMIFS(Entradas[Valores],Entradas[Conta Financeira],G37,Entradas[Status],"Realizado")-SUMIFS(Saidas[Valores],Saidas[Conta Financeira],G37,Saidas[Status],"Realizado")+SUMIFS(Cadastros!$D$6:$D$19,Cadastros!$B$6:$B$19,G37)+SUMIFS(Transferência_Interna[Valor],Transferência_Interna[Conta de Destino],G37)-SUMIFS(Transferência_Interna[Valor],Transferência_Interna[Conta de Origem],G37) -> 0
B38: Receita Liquida | D38: =D35-D36-D37 -> 0 | I38: =SUMIFS(Entradas[Valores],Entradas[Conta Financeira],G38,Entradas[Status],"Realizado")-SUMIFS(Saidas[Valores],Saidas[Conta Financeira],G38,Saidas[Status],"Realizado")+SUMIFS(Cadastros!$D$6:$D$19,Cadastros!$B$6:$B$19,G38)+SUMIFS(Transferência_Interna[Valor],Transferência_Interna[Conta de Destino],G38)-SUMIFS(Transferência_Interna[Valor],Transferência_Interna[Conta de Origem],G38) -> 0
B39: =X!$V$7 -> Custo das Vendas | D39: =SUMIFS(Saidas[Valores],Saidas[Data da Competência],">="&MesAtual,Saidas[Data da Competência],"<"&EDATE(MesAtual,1),Saidas[Categoria],$B39) -> 0 | I39: =SUMIFS(Entradas[Valores],Entradas[Conta Financeira],G39,Entradas[Status],"Realizado")-SUMIFS(Saidas[Valores],Saidas[Conta Financeira],G39,Saidas[Status],"Realizado")+SUMIFS(Cadastros!$D$6:$D$19,Cadastros!$B$6:$B$19,G39)+SUMIFS(Transferência_Interna[Valor],Transferência_Interna[Conta de Destino],G39)-SUMIFS(Transferência_Interna[Valor],Transferência_Interna[Conta de Origem],G39) -> 0
B40: Resultado Operacional Bruto | D40: =D38-D39 -> 0 | I40: =SUMIFS(Entradas[Valores],Entradas[Conta Financeira],G40,Entradas[Status],"Realizado")-SUMIFS(Saidas[Valores],Saidas[Conta Financeira],G40,Saidas[Status],"Realizado")+SUMIFS(Cadastros!$D$6:$D$19,Cadastros!$B$6:$B$19,G40)+SUMIFS(Transferência_Interna[Valor],Transferência_Interna[Conta de Destino],G40)-SUMIFS(Transferência_Interna[Valor],Transferência_Interna[Conta de Origem],G40) -> 0
B41: =X!$V$8 -> Despesas administrativas | D41: =SUMIFS(Saidas[Valores],Saidas[Data da Competência],">="&MesAtual,Saidas[Data da Competência],"<"&EDATE(MesAtual,1),Saidas[Categoria],$B41) -> 0 | I41: =SUMIFS(Entradas[Valores],Entradas[Conta Financeira],G41,Entradas[Status],"Realizado")-SUMIFS(Saidas[Valores],Saidas[Conta Financeira],G41,Saidas[Status],"Realizado")+SUMIFS(Cadastros!$D$6:$D$19,Cadastros!$B$6:$B$19,G41)+SUMIFS(Transferência_Interna[Valor],Transferência_Interna[Conta de Destino],G41)-SUMIFS(Transferência_Interna[Valor],Transferência_Interna[Conta de Origem],G41) -> 0
B42: =X!$V$9 -> Despesa com Pessoal | D42: =SUMIFS(Saidas[Valores],Saidas[Data da Competência],">="&MesAtual,Saidas[Data da Competência],"<"&EDATE(MesAtual,1),Saidas[Categoria],$B42) -> 0 | I42: =SUMIFS(Entradas[Valores],Entradas[Conta Financeira],G42,Entradas[Status],"Realizado")-SUMIFS(Saidas[Valores],Saidas[Conta Financeira],G42,Saidas[Status],"Realizado")+SUMIFS(Cadastros!$D$6:$D$19,Cadastros!$B$6:$B$19,G42)+SUMIFS(Transferência_Interna[Valor],Transferência_Interna[Conta de Destino],G42)-SUMIFS(Transferência_Interna[Valor],Transferência_Interna[Conta de Origem],G42) -> 0
B43: =X!$V$11 -> Despesa Financeira | D43: =SUMIFS(Saidas[Valores],Saidas[Data da Competência],">="&MesAtual,Saidas[Data da Competência],"<"&EDATE(MesAtual,1),Saidas[Categoria],$B43) -> 0 | I43: =SUMIFS(Entradas[Valores],Entradas[Conta Financeira],G43,Entradas[Status],"Realizado")-SUMIFS(Saidas[Valores],Saidas[Conta Financeira],G43,Saidas[Status],"Realizado")+SUMIFS(Cadastros!$D$6:$D$19,Cadastros!$B$6:$B$19,G43)+SUMIFS(Transferência_Interna[Valor],Transferência_Interna[Conta de Destino],G43)-SUMIFS(Transferência_Interna[Valor],Transferência_Interna[Conta de Origem],G43) -> 0
B44: =X!$V$12 -> Despesas não operacionais | D44: =SUMIFS(Saidas[Valores],Saidas[Data da Competência],">="&MesAtual,Saidas[Data da Competência],"<"&EDATE(MesAtual,1),Saidas[Categoria],$B44) -> 0 | I44: =SUMIFS(Entradas[Valores],Entradas[Conta Financeira],G44,Entradas[Status],"Realizado")-SUMIFS(Saidas[Valores],Saidas[Conta Financeira],G44,Saidas[Status],"Realizado")+SUMIFS(Cadastros!$D$6:$D$19,Cadastros!$B$6:$B$19,G44)+SUMIFS(Transferência_Interna[Valor],Transferência_Interna[Conta de Destino],G44)-SUMIFS(Transferência_Interna[Valor],Transferência_Interna[Conta de Origem],G44) -> 0
B45: Resultado Operacional Líquido | E45: =D40-D41-D42-D43-D44 -> 0 | I45: =SUMIFS(Entradas[Valores],Entradas[Conta Financeira],G45,Entradas[Status],"Realizado")-SUMIFS(Saidas[Valores],Saidas[Conta Financeira],G45,Saidas[Status],"Realizado")+SUMIFS(Cadastros!$D$6:$D$19,Cadastros!$B$6:$B$19,G45)+SUMIFS(Transferência_Interna[Valor],Transferência_Interna[Conta de Destino],G45)-SUMIFS(Transferência_Interna[Valor],Transferência_Interna[Conta de Origem],G45) -> 0
B46: =X!$V$4 -> Receitas Financeiras | D46: =SUMIFS(Entradas[Valores],Entradas[Data da Competência],">="&MesAtual,Entradas[Data da Competência],"<"&EDATE(MesAtual,1),Entradas[Categoria],$B46) -> 0 | I46: =SUMIFS(Entradas[Valores],Entradas[Conta Financeira],G46,Entradas[Status],"Realizado")-SUMIFS(Saidas[Valores],Saidas[Conta Financeira],G46,Saidas[Status],"Realizado")+SUMIFS(Cadastros!$D$6:$D$19,Cadastros!$B$6:$B$19,G46)+SUMIFS(Transferência_Interna[Valor],Transferência_Interna[Conta de Destino],G46)-SUMIFS(Transferência_Interna[Valor],Transferência_Interna[Conta de Origem],G46) -> 0
B47: =X!$V$13 -> Impostos | D47: =SUMIFS(Saidas[Valores],Saidas[Data da Competência],">="&MesAtual,Saidas[Data da Competência],"<"&EDATE(MesAtual,1),Saidas[Categoria],$B47) -> 0
B48: =X!$V$5 -> Receitas não operacionais | D48: =SUMIFS(Entradas[Valores],Entradas[Data da Competência],">="&MesAtual,Entradas[Data da Competência],"<"&EDATE(MesAtual,1),Entradas[Categoria],$B48) -> 0
B49: =X!$V$14 -> Participação e Dividendos | D49: =SUMIFS(Saidas[Valores],Saidas[Data da Competência],">="&MesAtual,Saidas[Data da Competência],"<"&EDATE(MesAtual,1),Saidas[Categoria],$B49) -> 0
B50: Resultado Liquido | D50: =E45+D46-D47+D48-D49 -> 0
B51: =X!$V$15 | D51: =SUMIFS(Saidas[Valores],Saidas[Data da Competência],">="&MesAtual,Saidas[Data da Competência],"<"&EDATE(MesAtual,1),Saidas[Categoria],$B51) -> 0
B52: Resultado Líquido do Exercício | D52: =D50-D51 -> 0

Sheet XX
A1: PROJEÇÃO DO FLUXO DE CAIXA (15 DIAS) | F1: =Dashboard!D2 -> Todos | G1: RESULTADO DOS ULTIMOS 6 MESES | M1: MAIORES CLIENTES | N1: VALOR | P1: MAIORES FORNECEDORES | Q1: VALOR
A2: DATA | C2: ENTRADAS | D2: SAÍDAS | E2: SALDO | G2: DATA | H2: MÊS | I2: RECEITAS | J2: DESPESAS | K2: RESULTADO | M2: {=Clientes} -> Rogério Ceni | N2: =SUMIFS(Entradas[Valores],Entradas[Cliente],M2,Entradas[Data da Competência],">="&RESUMO!$C$4,Entradas[Data da Competência],"<"&RESUMO!$D$5,Entradas[Centro de Custos],X!$E$14,Entradas[Status],X!$E$13) -> 9200 | P2: {=Fornecedores} -> Fornecedor 01 | Q2: =SUMIFS(Saidas[Valores],Saidas[Fornecedor],P2,Saidas[Data da Competência],">="&RESUMO!$C$4,Saidas[Data da Competência],"<"&RESUMO!$D$5,Saidas[Centro de Custos],X!$E$14,Saidas[Status],X!$E$13) -> 40713 | U2: RECEITAS NO PERÍODO
A3: =TODAY() -> 46245 | B3: =DAY(A3) -> 11 | C3: =SUMIFS(Entradas[Valores],Entradas[Data do Recebimento],">="&A3,Entradas[Data do Recebimento],"<"&A3+1,Entradas[Centro de Custos], IF($F$1="Todos", "<>-", $F$1)) -> 0 | D3: =SUMIFS(Saidas[Valores],Saidas[Data do Pagamento],">="&A3,Saidas[Data do Pagamento],"<"&A3+1,Saidas[Centro de Custos], IF($F$1="Todos", "<>-", $F$1)) -> 0 | E3: =C3-D3+Dashboard!C7 -> 24615 | G3: =EDATE(MesAtual,-5) -> 46082 | H3: =TEXT(G3,"MMM-YYYY") -> mar.-2026 | I3: =SUMIFS(Entradas[Valores],Entradas[Data da Competência],">="&G3,Entradas[Data da Competência],"<"&EDATE(G3,1),Entradas[Centro de Custos], IF($F$1="Todos", "<>-", $F$1)) -> 0 | J3: =SUMIFS(Saidas[Valores],Saidas[Data da Competência],">="&G3,Saidas[Data da Competência],"<"&EDATE(G3,1),Saidas[Centro de Custos], IF($F$1="Todos", "<>-", $F$1)) -> 0 | K3: =I3-J3 -> 0 | M3: Roger Machado | N3: =SUMIFS(Entradas[Valores],Entradas[Cliente],M3,Entradas[Data da Competência],">="&RESUMO!$C$4,Entradas[Data da Competência],"<"&RESUMO!$D$5,Entradas[Centro de Custos],X!$E$14,Entradas[Status],X!$E$13) -> 7650 | P3: Fornecedor 02 | Q3: =SUMIFS(Saidas[Valores],Saidas[Fornecedor],P3,Saidas[Data da Competência],">="&RESUMO!$C$4,Saidas[Data da Competência],"<"&RESUMO!$D$5,Saidas[Centro de Custos],X!$E$14,Saidas[Status],X!$E$13) -> 5135 | U3: =X!V2 -> Receitas Operacionais | V3: =SUMIFS(Entradas[Valores],Entradas[Categoria],U3,Entradas[Data da Competência],">="&MesAtual,Entradas[Data da Competência],"<"&EDATE(MesAtual,1)) -> 0
A4: =A3+1 -> 46246 | B4: =DAY(A4) -> 12 | C4: =SUMIFS(Entradas[Valores],Entradas[Data do Recebimento],">="&A4,Entradas[Data do Recebimento],"<"&A4+1,Entradas[Centro de Custos], IF($F$1="Todos", "<>-", $F$1)) -> 0 | D4: =SUMIFS(Saidas[Valores],Saidas[Data do Pagamento],">="&A4,Saidas[Data do Pagamento],"<"&A4+1,Saidas[Centro de Custos], IF($F$1="Todos", "<>-", $F$1)) -> 0 | E4: =C4-D4+E3 -> 24615 | G4: =EDATE(G3,1) -> 46113 | H4: =TEXT(G4,"MMM-YYYY") -> abr.-2026 | I4: =SUMIFS(Entradas[Valores],Entradas[Data da Competência],">="&G4,Entradas[Data da Competência],"<"&EDATE(G4,1),Entradas[Centro de Custos], IF($F$1="Todos", "<>-", $F$1)) -> 0 | J4: =SUMIFS(Saidas[Valores],Saidas[Data da Competência],">="&G4,Saidas[Data da Competência],"<"&EDATE(G4,1),Saidas[Centro de Custos], IF($F$1="Todos", "<>-", $F$1)) -> 0 | K4: =I4-J4 -> 0 | M4: Luiz Castro | N4: =SUMIFS(Entradas[Valores],Entradas[Cliente],M4,Entradas[Data da Competência],">="&RESUMO!$C$4,Entradas[Data da Competência],"<"&RESUMO!$D$5,Entradas[Centro de Custos],X!$E$14,Entradas[Status],X!$E$13) -> 9500 | P4: Fornecedor 03 | Q4: =SUMIFS(Saidas[Valores],Saidas[Fornecedor],P4,Saidas[Data da Competência],">="&RESUMO!$C$4,Saidas[Data da Competência],"<"&RESUMO!$D$5,Saidas[Centro de Custos],X!$E$14,Saidas[Status],X!$E$13) -> 11740 | U4: =X!V3 -> Outras Receitas Operacionais | V4: =SUMIFS(Entradas[Valores],Entradas[Categoria],U4,Entradas[Data da Competência],">="&MesAtual,Entradas[Data da Competência],"<"&EDATE(MesAtual,1)) -> 0
A5: =A4+1 -> 46247 | B5: =DAY(A5) -> 13 | C5: =SUMIFS(Entradas[Valores],Entradas[Data do Recebimento],">="&A5,Entradas[Data do Recebimento],"<"&A5+1,Entradas[Centro de Custos], IF($F$1="Todos", "<>-", $F$1)) -> 0 | D5: =SUMIFS(Saidas[Valores],Saidas[Data do Pagamento],">="&A5,Saidas[Data do Pagamento],"<"&A5+1,Saidas[Centro de Custos], IF($F$1="Todos", "<>-", $F$1)) -> 0 | E5: =C5-D5+E4 -> 24615 | G5: =EDATE(G4,1) -> 46143 | H5: =TEXT(G5,"MMM-YYYY") -> mai.-2026 | I5: =SUMIFS(Entradas[Valores],Entradas[Data da Competência],">="&G5,Entradas[Data da Competência],"<"&EDATE(G5,1),Entradas[Centro de Custos], IF($F$1="Todos", "<>-", $F$1)) -> 0 | J5: =SUMIFS(Saidas[Valores],Saidas[Data da Competência],">="&G5,Saidas[Data da Competência],"<"&EDATE(G5,1),Saidas[Centro de Custos], IF($F$1="Todos", "<>-", $F$1)) -> 0 | K5: =I5-J5 -> 0 | M5: Rafael Paiva | N5: =SUMIFS(Entradas[Valores],Entradas[Cliente],M5,Entradas[Data da Competência],">="&RESUMO!$C$4,Entradas[Data da Competência],"<"&RESUMO!$D$5,Entradas[Centro de Custos],X!$E$14,Entradas[Status],X!$E$13) -> 9400 | Q5: =SUMIFS(Saidas[Valores],Saidas[Fornecedor],P5,Saidas[Data da Competência],">="&RESUMO!$C$4,Saidas[Data da Competência],"<"&RESUMO!$D$5,Saidas[Centro de Custos],X!$E$14,Saidas[Status],X!$E$13) -> 0 | U5: =X!V4 -> Receitas Financeiras | V5: =SUMIFS(Entradas[Valores],Entradas[Categoria],U5,Entradas[Data da Competência],">="&MesAtual,Entradas[Data da Competência],"<"&EDATE(MesAtual,1)) -> 0
A6: =A5+1 -> 46248 | B6: =DAY(A6) -> 14 | C6: =SUMIFS(Entradas[Valores],Entradas[Data do Recebimento],">="&A6,Entradas[Data do Recebimento],"<"&A6+1,Entradas[Centro de Custos], IF($F$1="Todos", "<>-", $F$1)) -> 0 | D6: =SUMIFS(Saidas[Valores],Saidas[Data do Pagamento],">="&A6,Saidas[Data do Pagamento],"<"&A6+1,Saidas[Centro de Custos], IF($F$1="Todos", "<>-", $F$1)) -> 0 | E6: =C6-D6+E5 -> 24615 | G6: =EDATE(G5,1) -> 46174 | H6: =TEXT(G6,"MMM-YYYY") -> jun.-2026 | I6: =SUMIFS(Entradas[Valores],Entradas[Data da Competência],">="&G6,Entradas[Data da Competência],"<"&EDATE(G6,1),Entradas[Centro de Custos], IF($F$1="Todos", "<>-", $F$1)) -> 0 | J6: =SUMIFS(Saidas[Valores],Saidas[Data da Competência],">="&G6,Saidas[Data da Competência],"<"&EDATE(G6,1),Saidas[Centro de Custos], IF($F$1="Todos", "<>-", $F$1)) -> 0 | K6: =I6-J6 -> 0 | N6: =SUMIFS(Entradas[Valores],Entradas[Cliente],M6,Entradas[Data da Competência],">="&RESUMO!$C$4,Entradas[Data da Competência],"<"&RESUMO!$D$5,Entradas[Centro de Custos],X!$E$14,Entradas[Status],X!$E$13) -> 0 | Q6: =SUMIFS(Saidas[Valores],Saidas[Fornecedor],P6,Saidas[Data da Competência],">="&RESUMO!$C$4,Saidas[Data da Competência],"<"&RESUMO!$D$5,Saidas[Centro de Custos],X!$E$14,Saidas[Status],X!$E$13) -> 0 | U6: =X!V5 -> Receitas não operacionais | V6: =SUMIFS(Entradas[Valores],Entradas[Categoria],U6,Entradas[Data da Competência],">="&MesAtual,Entradas[Data da Competência],"<"&EDATE(MesAtual,1)) -> 0
A7: =A6+1 -> 46249 | B7: =DAY(A7) -> 15 | C7: =SUMIFS(Entradas[Valores],Entradas[Data do Recebimento],">="&A7,Entradas[Data do Recebimento],"<"&A7+1,Entradas[Centro de Custos], IF($F$1="Todos", "<>-", $F$1)) -> 0 | D7: =SUMIFS(Saidas[Valores],Saidas[Data do Pagamento],">="&A7,Saidas[Data do Pagamento],"<"&A7+1,Saidas[Centro de Custos], IF($F$1="Todos", "<>-", $F$1)) -> 0 | E7: =C7-D7+E6 -> 24615 | G7: =EDATE(G6,1) -> 46204 | H7: =TEXT(G7,"MMM-YYYY") -> jul.-2026 | I7: =SUMIFS(Entradas[Valores],Entradas[Data da Competência],">="&G7,Entradas[Data da Competência],"<"&EDATE(G7,1),Entradas[Centro de Custos], IF($F$1="Todos", "<>-", $F$1)) -> 0 | J7: =SUMIFS(Saidas[Valores],Saidas[Data da Competência],">="&G7,Saidas[Data da Competência],"<"&EDATE(G7,1),Saidas[Centro de Custos], IF($F$1="Todos", "<>-", $F$1)) -> 0 | K7: =I7-J7 -> 0 | N7: =SUMIFS(Entradas[Valores],Entradas[Cliente],M7,Entradas[Data da Competência],">="&RESUMO!$C$4,Entradas[Data da Competência],"<"&RESUMO!$D$5,Entradas[Centro de Custos],X!$E$14,Entradas[Status],X!$E$13) -> 0 | Q7: =SUMIFS(Saidas[Valores],Saidas[Fornecedor],P7,Saidas[Data da Competência],">="&RESUMO!$C$4,Saidas[Data da Competência],"<"&RESUMO!$D$5,Saidas[Centro de Custos],X!$E$14,Saidas[Status],X!$E$13) -> 0
A8: =A7+1 -> 46250 | B8: =DAY(A8) -> 16 | C8: =SUMIFS(Entradas[Valores],Entradas[Data do Recebimento],">="&A8,Entradas[Data do Recebimento],"<"&A8+1,Entradas[Centro de Custos], IF($F$1="Todos", "<>-", $F$1)) -> 0 | D8: =SUMIFS(Saidas[Valores],Saidas[Data do Pagamento],">="&A8,Saidas[Data do Pagamento],"<"&A8+1,Saidas[Centro de Custos], IF($F$1="Todos", "<>-", $F$1)) -> 0 | E8: =C8-D8+E7 -> 24615 | G8: =EDATE(G7,1) -> 46235 | H8: =TEXT(G8,"MMM-YYYY") -> ago.-2026 | I8: =SUMIFS(Entradas[Valores],Entradas[Data da Competência],">="&G8,Entradas[Data da Competência],"<"&EDATE(G8,1),Entradas[Centro de Custos], IF($F$1="Todos", "<>-", $F$1)) -> 0 | J8: =SUMIFS(Saidas[Valores],Saidas[Data da Competência],">="&G8,Saidas[Data da Competência],"<"&EDATE(G8,1),Saidas[Centro de Custos], IF($F$1="Todos", "<>-", $F$1)) -> 0 | K8: =I8-J8 -> 0 | N8: =SUMIFS(Entradas[Valores],Entradas[Cliente],M8,Entradas[Data da Competência],">="&RESUMO!$C$4,Entradas[Data da Competência],"<"&RESUMO!$D$5,Entradas[Centro de Custos],X!$E$14,Entradas[Status],X!$E$13) -> 0 | Q8: =SUMIFS(Saidas[Valores],Saidas[Fornecedor],P8,Saidas[Data da Competência],">="&RESUMO!$C$4,Saidas[Data da Competência],"<"&RESUMO!$D$5,Saidas[Centro de Custos],X!$E$14,Saidas[Status],X!$E$13) -> 0
A9: =A8+1 -> 46251 | B9: =DAY(A9) -> 17 | C9: =SUMIFS(Entradas[Valores],Entradas[Data do Recebimento],">="&A9,Entradas[Data do Recebimento],"<"&A9+1,Entradas[Centro de Custos], IF($F$1="Todos", "<>-", $F$1)) -> 0 | D9: =SUMIFS(Saidas[Valores],Saidas[Data do Pagamento],">="&A9,Saidas[Data do Pagamento],"<"&A9+1,Saidas[Centro de Custos], IF($F$1="Todos", "<>-", $F$1)) -> 0 | E9: =C9-D9+E8 -> 24615 | N9: =SUMIFS(Entradas[Valores],Entradas[Cliente],M9,Entradas[Data da Competência],">="&RESUMO!$C$4,Entradas[Data da Competência],"<"&RESUMO!$D$5,Entradas[Centro de Custos],X!$E$14,Entradas[Status],X!$E$13) -> 0 | Q9: =SUMIFS(Saidas[Valores],Saidas[Fornecedor],P9,Saidas[Data da Competência],">="&RESUMO!$C$4,Saidas[Data da Competência],"<"&RESUMO!$D$5,Saidas[Centro de Custos],X!$E$14,Saidas[Status],X!$E$13) -> 0 | U9: DESPESAS NO PERÍODO
A10: =A9+1 -> 46252 | B10: =DAY(A10) -> 18 | C10: =SUMIFS(Entradas[Valores],Entradas[Data do Recebimento],">="&A10,Entradas[Data do Recebimento],"<"&A10+1,Entradas[Centro de Custos], IF($F$1="Todos", "<>-", $F$1)) -> 0 | D10: =SUMIFS(Saidas[Valores],Saidas[Data do Pagamento],">="&A10,Saidas[Data do Pagamento],"<"&A10+1,Saidas[Centro de Custos], IF($F$1="Todos", "<>-", $F$1)) -> 0 | E10: =C10-D10+E9 -> 24615 | N10: =SUMIFS(Entradas[Valores],Entradas[Cliente],M10,Entradas[Data da Competência],">="&RESUMO!$C$4,Entradas[Data da Competência],"<"&RESUMO!$D$5,Entradas[Centro de Custos],X!$E$14,Entradas[Status],X!$E$13) -> 0 | Q10: =SUMIFS(Saidas[Valores],Saidas[Fornecedor],P10,Saidas[Data da Competência],">="&RESUMO!$C$4,Saidas[Data da Competência],"<"&RESUMO!$D$5,Saidas[Centro de Custos],X!$E$14,Saidas[Status],X!$E$13) -> 0 | U10: =X!V6 -> Deduções sobre vendas | V10: =SUMIFS(Saidas[Valores],Saidas[Categoria],U10,Saidas[Data da Competência],">="&MesAtual,Saidas[Data da Competência],"<"&EDATE(MesAtual,1)) -> 0
A11: =A10+1 -> 46253 | B11: =DAY(A11) -> 19 | C11: =SUMIFS(Entradas[Valores],Entradas[Data do Recebimento],">="&A11,Entradas[Data do Recebimento],"<"&A11+1,Entradas[Centro de Custos], IF($F$1="Todos", "<>-", $F$1)) -> 0 | D11: =SUMIFS(Saidas[Valores],Saidas[Data do Pagamento],">="&A11,Saidas[Data do Pagamento],"<"&A11+1,Saidas[Centro de Custos], IF($F$1="Todos", "<>-", $F$1)) -> 0 | E11: =C11-D11+E10 -> 24615 | N11: =SUMIFS(Entradas[Valores],Entradas[Cliente],M11,Entradas[Data da Competência],">="&RESUMO!$C$4,Entradas[Data da Competência],"<"&RESUMO!$D$5,Entradas[Centro de Custos],X!$E$14,Entradas[Status],X!$E$13) -> 0 | Q11: =SUMIFS(Saidas[Valores],Saidas[Fornecedor],P11,Saidas[Data da Competência],">="&RESUMO!$C$4,Saidas[Data da Competência],"<"&RESUMO!$D$5,Saidas[Centro de Custos],X!$E$14,Saidas[Status],X!$E$13) -> 0 | U11: =X!V7 -> Custo das Vendas | V11: =SUMIFS(Saidas[Valores],Saidas[Categoria],U11,Saidas[Data da Competência],">="&MesAtual,Saidas[Data da Competência],"<"&EDATE(MesAtual,1)) -> 0
A12: =A11+1 -> 46254 | B12: =DAY(A12) -> 20 | C12: =SUMIFS(Entradas[Valores],Entradas[Data do Recebimento],">="&A12,Entradas[Data do Recebimento],"<"&A12+1,Entradas[Centro de Custos], IF($F$1="Todos", "<>-", $F$1)) -> 0 | D12: =SUMIFS(Saidas[Valores],Saidas[Data do Pagamento],">="&A12,Saidas[Data do Pagamento],"<"&A12+1,Saidas[Centro de Custos], IF($F$1="Todos", "<>-", $F$1)) -> 0 | E12: =C12-D12+E11 -> 24615 | N12: =SUMIFS(Entradas[Valores],Entradas[Cliente],M12,Entradas[Data da Competência],">="&RESUMO!$C$4,Entradas[Data da Competência],"<"&RESUMO!$D$5,Entradas[Centro de Custos],X!$E$14,Entradas[Status],X!$E$13) -> 0 | Q12: =SUMIFS(Saidas[Valores],Saidas[Fornecedor],P12,Saidas[Data da Competência],">="&RESUMO!$C$4,Saidas[Data da Competência],"<"&RESUMO!$D$5,Saidas[Centro de Custos],X!$E$14,Saidas[Status],X!$E$13) -> 0 | U12: =X!V8 -> Despesas administrativas | V12: =SUMIFS(Saidas[Valores],Saidas[Categoria],U12,Saidas[Data da Competência],">="&MesAtual,Saidas[Data da Competência],"<"&EDATE(MesAtual,1)) -> 0
A13: =A12+1 -> 46255 | B13: =DAY(A13) -> 21 | C13: =SUMIFS(Entradas[Valores],Entradas[Data do Recebimento],">="&A13,Entradas[Data do Recebimento],"<"&A13+1,Entradas[Centro de Custos], IF($F$1="Todos", "<>-", $F$1)) -> 0 | D13: =SUMIFS(Saidas[Valores],Saidas[Data do Pagamento],">="&A13,Saidas[Data do Pagamento],"<"&A13+1,Saidas[Centro de Custos], IF($F$1="Todos", "<>-", $F$1)) -> 0 | E13: =C13-D13+E12 -> 24615 | N13: =SUMIFS(Entradas[Valores],Entradas[Cliente],M13,Entradas[Data da Competência],">="&RESUMO!$C$4,Entradas[Data da Competência],"<"&RESUMO!$D$5,Entradas[Centro de Custos],X!$E$14,Entradas[Status],X!$E$13) -> 0 | Q13: =SUMIFS(Saidas[Valores],Saidas[Fornecedor],P13,Saidas[Data da Competência],">="&RESUMO!$C$4,Saidas[Data da Competência],"<"&RESUMO!$D$5,Saidas[Centro de Custos],X!$E$14,Saidas[Status],X!$E$13) -> 0 | U13: =X!V9 -> Despesa com Pessoal | V13: =SUMIFS(Saidas[Valores],Saidas[Categoria],U13,Saidas[Data da Competência],">="&MesAtual,Saidas[Data da Competência],"<"&EDATE(MesAtual,1)) -> 0
A14: =A13+1 -> 46256 | B14: =DAY(A14) -> 22 | C14: =SUMIFS(Entradas[Valores],Entradas[Data do Recebimento],">="&A14,Entradas[Data do Recebimento],"<"&A14+1,Entradas[Centro de Custos], IF($F$1="Todos", "<>-", $F$1)) -> 0 | D14: =SUMIFS(Saidas[Valores],Saidas[Data do Pagamento],">="&A14,Saidas[Data do Pagamento],"<"&A14+1,Saidas[Centro de Custos], IF($F$1="Todos", "<>-", $F$1)) -> 0 | E14: =C14-D14+E13 -> 24615 | N14: =SUMIFS(Entradas[Valores],Entradas[Cliente],M14,Entradas[Data da Competência],">="&RESUMO!$C$4,Entradas[Data da Competência],"<"&RESUMO!$D$5,Entradas[Centro de Custos],X!$E$14,Entradas[Status],X!$E$13) -> 0 | Q14: =SUMIFS(Saidas[Valores],Saidas[Fornecedor],P14,Saidas[Data da Competência],">="&RESUMO!$C$4,Saidas[Data da Competência],"<"&RESUMO!$D$5,Saidas[Centro de Custos],X!$E$14,Saidas[Status],X!$E$13) -> 0 | U14: =X!V11 -> Despesa Financeira | V14: =SUMIFS(Saidas[Valores],Saidas[Categoria],U14,Saidas[Data da Competência],">="&MesAtual,Saidas[Data da Competência],"<"&EDATE(MesAtual,1)) -> 0
A15: =A14+1 -> 46257 | B15: =DAY(A15) -> 23 | C15: =SUMIFS(Entradas[Valores],Entradas[Data do Recebimento],">="&A15,Entradas[Data do Recebimento],"<"&A15+1,Entradas[Centro de Custos], IF($F$1="Todos", "<>-", $F$1)) -> 0 | D15: =SUMIFS(Saidas[Valores],Saidas[Data do Pagamento],">="&A15,Saidas[Data do Pagamento],"<"&A15+1,Saidas[Centro de Custos], IF($F$1="Todos", "<>-", $F$1)) -> 0 | E15: =C15-D15+E14 -> 24615 | N15: =SUMIFS(Entradas[Valores],Entradas[Cliente],M15,Entradas[Data da Competência],">="&RESUMO!$C$4,Entradas[Data da Competência],"<"&RESUMO!$D$5,Entradas[Centro de Custos],X!$E$14,Entradas[Status],X!$E$13) -> 0 | Q15: =SUMIFS(Saidas[Valores],Saidas[Fornecedor],P15,Saidas[Data da Competência],">="&RESUMO!$C$4,Saidas[Data da Competência],"<"&RESUMO!$D$5,Saidas[Centro de Custos],X!$E$14,Saidas[Status],X!$E$13) -> 0 | U15: =X!V12 -> Despesas não operacionais | V15: =SUMIFS(Saidas[Valores],Saidas[Categoria],U15,Saidas[Data da Competência],">="&MesAtual,Saidas[Data da Competência],"<"&EDATE(MesAtual,1)) -> 0
A16: =A15+1 -> 46258 | B16: =DAY(A16) -> 24 | C16: =SUMIFS(Entradas[Valores],Entradas[Data do Recebimento],">="&A16,Entradas[Data do Recebimento],"<"&A16+1,Entradas[Centro de Custos], IF($F$1="Todos", "<>-", $F$1)) -> 0 | D16: =SUMIFS(Saidas[Valores],Saidas[Data do Pagamento],">="&A16,Saidas[Data do Pagamento],"<"&A16+1,Saidas[Centro de Custos], IF($F$1="Todos", "<>-", $F$1)) -> 0 | E16: =C16-D16+E15 -> 24615 | N16: =SUMIFS(Entradas[Valores],Entradas[Cliente],M16,Entradas[Data da Competência],">="&RESUMO!$C$4,Entradas[Data da Competência],"<"&RESUMO!$D$5,Entradas[Centro de Custos],X!$E$14,Entradas[Status],X!$E$13) -> 0 | Q16: =SUMIFS(Saidas[Valores],Saidas[Fornecedor],P16,Saidas[Data da Competência],">="&RESUMO!$C$4,Saidas[Data da Competência],"<"&RESUMO!$D$5,Saidas[Centro de Custos],X!$E$14,Saidas[Status],X!$E$13) -> 0 | U16: =X!V13 -> Impostos | V16: =SUMIFS(Saidas[Valores],Saidas[Categoria],U16,Saidas[Data da Competência],">="&MesAtual,Saidas[Data da Competência],"<"&EDATE(MesAtual,1)) -> 0
A17: =A16+1 -> 46259 | B17: =DAY(A17) -> 25 | C17: =SUMIFS(Entradas[Valores],Entradas[Data do Recebimento],">="&A17,Entradas[Data do Recebimento],"<"&A17+1,Entradas[Centro de Custos], IF($F$1="Todos", "<>-", $F$1)) -> 0 | D17: =SUMIFS(Saidas[Valores],Saidas[Data do Pagamento],">="&A17,Saidas[Data do Pagamento],"<"&A17+1,Saidas[Centro de Custos], IF($F$1="Todos", "<>-", $F$1)) -> 0 | E17: =C17-D17+E16 -> 24615 | N17: =SUMIFS(Entradas[Valores],Entradas[Cliente],M17,Entradas[Data da Competência],">="&RESUMO!$C$4,Entradas[Data da Competência],"<"&RESUMO!$D$5,Entradas[Centro de Custos],X!$E$14,Entradas[Status],X!$E$13) -> 0 | Q17: =SUMIFS(Saidas[Valores],Saidas[Fornecedor],P17,Saidas[Data da Competência],">="&RESUMO!$C$4,Saidas[Data da Competência],"<"&RESUMO!$D$5,Saidas[Centro de Custos],X!$E$14,Saidas[Status],X!$E$13) -> 0 | U17: =X!V14 -> Participação e Dividendos | V17: =SUMIFS(Saidas[Valores],Saidas[Categoria],U17,Saidas[Data da Competência],">="&MesAtual,Saidas[Data da Competência],"<"&EDATE(MesAtual,1)) -> 0
